Workbook
Name _________HOJ1: #REF!
Name _________HOJ1: #REF!
Name _________HOJ1: #REF!
Name _________HOJ1: #REF!
Name _________HOJ1: #REF!
Name _________HOJ1: #REF!
Name _________HOJ1: #REF!
Name _________HOJ1: #REF!
Name _________HOJ1: #REF!
Name _________HOJ1: #REF!
Name _________HOJ1: #REF!
Name _________HOJ1: #REF!
Name _________HOJ1: #REF!
Name _________HOJ1: #REF!
Name _________HOJ1: #REF!
Name _________HOJ2: #REF!
Name _________HOJ2: #REF!
Name _________HOJ2: #REF!
Name _________HOJ2: #REF!
Name _________HOJ2: #REF!
Name _________HOJ2: #REF!
Name _________HOJ2: #REF!
Name _________HOJ2: #REF!
Name _________HOJ2: #REF!
Name _________HOJ2: #REF!
Name _________HOJ2: #REF!
Name _________HOJ2: #REF!
Name _________HOJ2: #REF!
Name _________HOJ2: #REF!
Name _________HOJ2: #REF!
Name _________HOJ3: #REF!
Name _________HOJ3: #REF!
Name _________HOJ3: #REF!
Name _________HOJ3: #REF!
Name _________HOJ3: #REF!
Name _________HOJ3: #REF!
Name _________HOJ3: #REF!
Name _________HOJ3: #REF!
Name _________HOJ3: #REF!
Name _________HOJ3: #REF!
Name _________HOJ3: #REF!
Name _________HOJ3: #REF!
Name _________HOJ3: #REF!
Name _________HOJ3: #REF!
Name _________HOJ3: #REF!
Name ________HOJ1: #REF!
Name ________HOJ1: #REF!
Name ________HOJ1: #REF!
Name ________HOJ1: #REF!
Name ________HOJ1: #REF!
Name ________HOJ1: #REF!
Name ________HOJ1: #REF!
Name ________HOJ1: #REF!
Name ________HOJ1: #REF!
Name ________HOJ1: #REF!
Name ________HOJ1: #REF!
Name ________HOJ1: #REF!
Name ________HOJ1: #REF!
Name ________HOJ1: #REF!
Name ________HOJ1: #REF!

Sheet Presupuesto Hospital
C6: ITEM | D6: DESCRIPCIÓN | E6: UNID. | F6: CANT. | G6: PRECIO | H6: PARCIAL
D7: COMPONENTE 01: SUFICIENTE Y ADECUADA INFRAESTRUCTURA Y MANTENIMIENTO PARA LA PRESTACIÓN DE SERVICIOS DE SALUD | H7: =+H8+H62+H325+H635+H1139+H1966+H2185+H2232 -> 81030968
B8: X | C8: OE.1 | D8: OBRAS PROVISIONALES, TRABAJOS PRELIMINARES, SEGURIDAD Y SALUD. | H8: =+H9+H52 -> 940011.29 | I8: 940011.29 | J8: =+I8-H8 -> 0
C9: OE.1.1 | D9: OBRAS PROVISIONALES Y TRABAJOS PRELIMINARES | H9: =+H10+H19+H29+H32+H39+H45+H47+H49 -> 541853.9
C10: OE.1.1.1 | D10: CONSTRUCCIONES PROVISIONALES | H10: =SUM(H11:H18) -> 69311.57
C11: OE.1.1.1.1 | D11: Oficinas | E11: m² | F11: 18 | G11: 157.37 | H11: =+ROUND(+IF(F11="",0,F11*G11),2) -> 2832.66
C12: OE.1.1.1.2 | D12: Almacenes | E12: m² | F12: 70 | G12: 109.44 | H12: =+ROUND(+IF(F12="",0,F12*G12),2) -> 7660.8
C13: OE.1.1.1.3 | D13: Casetas de guardianÍa | E13: m² | F13: 10 | G13: 147.84 | H13: =+ROUND(+IF(F13="",0,F13*G13),2) -> 1478.4
C14: OE.1.1.1.5 | D14: Vestuarios | E14: m² | F14: 40 | G14: 130.85 | H14: =+ROUND(+IF(F14="",0,F14*G14),2) -> 5234
C15: OE.1.1.1.6 | D15: Servicios higienicos | E15: m² | F15: 18 | G15: 282.01 | H15: =+ROUND(+IF(F15="",0,F15*G15),2) -> 5076.18
C16: OE.1.1.1.7 | D16: Cercos Provisional de calamina | E16: m | F16: 234 | G16: 53.39 | H16: =+ROUND(+IF(F16="",0,F16*G16),2) -> 12493.26
C17: OE.1.1.1.8 | D17: Cartel de identificación de Obra de 4.80m x 3.60 m | E17: und | F17: 2 | G17: 2517.15 | H17: =+ROUND(+IF(F17="",0,F17*G17),2) -> 5034.3
C18: OE.1.1.1.9 | D18: Suministro e instalacion de equipo para transporte vertical de materiales | E18: gbl | F18: 1 | G18: 29501.97 | H18: =+ROUND(+IF(F18="",0,F18*G18),2) -> 29501.97
C19: OE.1.1.2 | D19: INSTALACIONES PROVISIONALES | H19: =SUM(H20:H28)/2 -> 125356.38
C20: OE.1.1.2.1 | D20: AGUA PARA LA CONSTRUCCIÓN | H20: =SUM(H21) -> 7199.99
C21: OE.1.1.2.1.1 | D21: Almacenamiento y distribución | E21: gbl | F21: 1 | G21: 7199.99 | H21: =+ROUND(+IF(F21="",0,F21*G21),2) -> 7199.99
C22: OE.1.1.2.2 | D22: DESAGÜE PARA LA CONSTRUCCIÓN | H22: =SUM(H23) -> 7199.99
C23: OE.1.1.2.2.1 | D23: Desagüe para la construcción | E23: glb | F23: 1 | G23: 7199.99 | H23: =+ROUND(+IF(F23="",0,F23*G23),2) -> 7199.99
C24: OE.1.1.2.3 | D24: ENERGÍA ELÉCTRICA PROVISIONAL | H24: =SUM(H25) -> 108902.4
C25: OE.1.1.2.3.3 | D25: Servicio extraordinario de energia electrica | E25: mes | F25: 24 | G25: 4537.6 | H25: =+ROUND(+IF(F25="",0,F25*G25),2) -> 108902.4
C26: OE.1.1.2.4 | D26: INSTALACIÓN TELEFÓNICA Y COMUNICACIÓN PROVISIONAL | H26: =SUM(H27:H28) -> 2054
C27: OE.1.1.2.4.1 | D27: Conexion e Instalación | E27: glb | F27: 1 | G27: 520 | H27: =+ROUND(+IF(F27="",0,F27*G27),2) -> 520
C28: OE.1.1.2.4.2 | D28: Consumo y mantenimiento | E28: glb | F28: 1 | G28: 1534 | H28: =+ROUND(+IF(F28="",0,F28*G28),2) -> 1534
C29: OE.1.1.4 | D29: ELIMINACIÓN DE OBSTRUCCIONES | H29: =SUM(H30:H31) -> 298.27
C30: OE.1.1.4.1 | D30: Tala de Arboles | E30: und | F30: 7 | G30: 17.72 | H30: =+ROUND(+IF(F30="",0,F30*G30),2) -> 124.04
C31: OE.1.1.4.2 | D31: Eliminación de Raices | E31: und | F31: 7 | G31: 24.89 | H31: =+ROUND(+IF(F31="",0,F31*G31),2) -> 174.23
C32: OE.1.1.5 | D32: REMOCIONES | H32: =SUM(H33:H38) -> 22288.74
C33: OE.1.1.5.1 | D33: Remoción de Puertas | E33: und | F33: 113 | G33: 23.64 | H33: =+ROUND(+IF(F33="",0,F33*G33),2) -> 2671.32
C34: OE.1.1.5.2 | D34: Remoción de Ventanas | E34: und | F34: 123 | G34: 23.64 | H34: =+ROUND(+IF(F34="",0,F34*G34),2) -> 2907.72
C35: OE.1.1.5.3 | D35: Remoción de Aparatos Sanitarios | E35: und | F35: 35 | G35: 25.21 | H35: =+ROUND(+IF(F35="",0,F35*G35),2) -> 882.35
C36: OE.1.1.5.4 | D36: Remoción de Tijerales de madera | E36: und | F36: 77 | G36: 47.28 | H36: =+ROUND(+IF(F36="",0,F36*G36),2) -> 3640.56
C37: OE.1.1.5.5 | D37: Remoción de Cobertura | E37: m² | F37: 2540.97 | G37: 4.73 | H37: =+ROUND(+IF(F37="",0,F37*G37),2) -> 12018.79
C38: OE.1.1.5.6 | D38: Remoción de Estructuras Metálicas | E38: m² | F38: 50 | G38: 3.36 | H38: =+ROUND(+IF(F38="",0,F38*G38),2) -> 168
C39: OE.1.1.6 | D39: DEMOLICIONES | H39: =SUM(H40:H44) -> 261717.22
C40: OE.1.1.6.1 | D40: Demolicion de muros de ladrillo incluye cimentaciones | E40: m³ | F40: 596.35 | G40: 19.99 | H40: =+ROUND(+IF(F40="",0,F40*G40),2) -> 11921.04
C41: OE.1.1.6.2 | D41: Demolicion de muros de adobe incluye cimentaciones | E41: m³ | F41: 127.38 | G41: 63.64 | H41: =+ROUND(+IF(F41="",0,F41*G41),2) -> 8106.46
C42: OE.1.1.6.3 | D42: DEMOLICIONES DE MUROS DE CONTENCION DE PIEDRA INC. CIMENTACIONES | E42: m³ | F42: 434.35 | G42: 173.49 | H42: =+ROUND(+IF(F42="",0,F42*G42),2) -> 75355.38
C43: OE.1.1.6.4 | D43: Demolicion de Pisos y falso pisos - Manual | E43: m² | F43: 474.2 | G43: 16.77 | H43: =+ROUND(+IF(F43="",0,F43*G43),2) -> 7952.33
C44: OE.1.1.6.5 | D44: Eliminación de Demoliciones | E44: m³ | F44: 1668.76 | G44: 94.91 | H44: =+ROUND(+IF(F44="",0,F44*G44),2) -> 158382.01
C45: OE.1.1.7 | D45: MOVILIZACIÓN DE CAMPAMENTO, MAQUINARIA Y HERRAMIENTAS | H45: =SUM(H46) -> 2400
C46: OE.1.1.7.2 | D46: Movilización y desmovilización de equipos | E46: glb | F46: 1 | G46: 2400 | H46: =+ROUND(+IF(F46="",0,F46*G46),2) -> 2400
C47: OE.1.1.8 | D47: APUNTALAMIENTOS DE CONSTRUCCIONES EXISTENTES | H47: =SUM(H48) -> 53.06
C48: OE.1.1.8.1 | D48: Apuntalamiento de Construcciones Existentes | E48: glb | F48: 1 | G48: 53.06 | H48: =+ROUND(+IF(F48="",0,F48*G48),2) -> 53.06
C49: OE.1.1.9 | D49: TRAZOS, NIVELES Y REPLANTEO | H49: =SUM(H50:H51) -> 60428.66
C50: OE.1.1.9.1 | D50: Trazo, niveles y replanteo preliminar | E50: m² | F50: 6451.57 | G50: 3.3 | H50: =+ROUND(+IF(F50="",0,F50*G50),2) -> 21290.18
C51: OE.1.1.9.2 | D51: Replanteo durante el proceso | E51: mes | F51: 12 | G51: 3261.54 | H51: =+ROUND(+IF(F51="",0,F51*G51),2) -> 39138.48
C52: OE.1.2 | D52: SEGURIDAD Y SALUD | H52: =+H53+H59 -> 398157.39
C53: OE.1.2.1 | D53: ELABORACIÓN, IMPLEMENTACIÓN Y ADMINISTRACIÓN DEL PLAN DE SEGURIDAD Y SALUD EN EL TRABAJO | H53: =SUM(H54:H58) -> 395694.3
C54: OE.1.2.1.1 | D54: Elaboracion, Implementacion y administracion del Plan de Seguridad y Salud en el Trabajo | E54: glb | F54: 1 | G54: 3000.01 | H54: =+ROUND(+IF(F54="",0,F54*G54),2) -> 3000.01
C55: OE.1.2.1.2 | D55: Equipos de Proteccion Individual | E55: und | F55: 300 | G55: 1063.85 | H55: =+ROUND(+IF(F55="",0,F55*G55),2) -> 319155
C56: OE.1.2.1.3 | D56: Equipos de Proteccion Colectiva | E56: glb | F56: 1 | G56: 70980 | H56: =+ROUND(+IF(F56="",0,F56*G56),2) -> 70980
C57: OE.1.2.1.4 | D57: Señalizacion Temporal de Seguridad | E57: glb | F57: 1 | G57: 1575.38 | H57: =+ROUND(+IF(F57="",0,F57*G57),2) -> 1575.38
C58: OE.1.2.1.5 | D58: Capacitacion en Seguridad y Salud | E58: glb | F58: 1 | G58: 983.91 | H58: =+ROUND(+IF(F58="",0,F58*G58),2) -> 983.91
C59: OE.1.2.2 | D59: RECURSOS PARA RESPUESTAS ANTE EMERGENCIAS EN SEGURIDAD Y SALUD DURANTE EL TRABAJO | H59: =SUM(H60:H61) -> 2463.09
C60: OE.1.2.2.1 | D60: Equipos de Primeros Auxilios y de Socorro | E60: glb | F60: 1 | G60: 696.4 | H60: =+ROUND(+IF(F60="",0,F60*G60),2) -> 696.4
C61: OE.1.2.2.2 | D61: Equipos contra incendios | E61: glb | F61: 1 | G61: 1766.69 | H61: =+ROUND(+IF(F61="",0,F61*G61),2) -> 1766.69
B62: X | C62: OE.2 | D62: ESTRUCTURAS. | H62: =+H63+H83+H94+H191+H307 -> 32710358 | I62: 32710358 | J62: =+I62-H62 -> 0
C63: OE.2.1 | D63: MOVIMIENTO DE TIERRAS | H63: =+H64+H66+H71+H73+H78+H80 -> 3521435.1
C64: OE.2.1.1 | D64: NIVELACIÓN DE TERRENO | H64: =SUM(H65) -> 8357.41
C65: OE.2.1.1.1 | D65: Nivelación con maquinaria a nivel de sub razante | E65: m² | F65: 4037.395 | G65: 2.07 | H65: =+ROUND(+IF(F65="",0,F65*G65),2) -> 8357.41
C66: OE.2.1.2 | D66: EXCAVACIONES | H66: =SUM(H67:H70)/2 -> 302181.11
C67: OE.2.1.2.1 | D67: EXCAVACIONES MASIVAS CON MAQUINARIA | H67: =SUM(H68) -> 55594.93
C68: OE.2.1.2.1.1 | D68: Excavaciones masivas para instalación de muros pantalla | E68: m³ | F68: 1810.32 | G68: 30.71 | H68: =+ROUND(+IF(F68="",0,F68*G68),2) -> 55594.93
C69: OE.2.1.2.2 | D69: EXCAVACIONES SIMPLES CON MAQUINARIA | H69: =SUM(H70) -> 246586.18
C70: OE.2.1.2.2.1 | D70: Excavaciones simples en material suelto -maquinaria | E70: m³ | F70: 8029.5075 | G70: 30.71 | H70: =+ROUND(+IF(F70="",0,F70*G70),2) -> 246586.18
C71: OE.2.1.3 | D71: CORTE DE PLATAFORMA | H71: =SUM(H72) -> 231795.72
C72: OE.2.1.3.1 | D72: Corte de plataforma con maquinaria en terreno natural | E72: m³ | F72: 23249.32 | G72: 9.97 | H72: =+ROUND(+IF(F72="",0,F72*G72),2) -> 231795.72
C73: OE.2.1.4 | D73: RELLENOS | H73: =SUM(H74:H77)/2 -> 531764.17
C74: OE.2.1.4.2 | D74: RELLENOS CON MATERIAL DE PRÉSTAMO | H74: =SUM(H75:H77) -> 531764.17
C75: OE.2.1.4.2.1 | D75: Relleno y compactado con material de prestamo en estructuras | E75: m³ | F75: 5019.8312 | G75: 89.45 | H75: =+ROUND(+IF(F75="",0,F75*G75),2) -> 449023.9
C76: OE.2.1.4.2.2 | D76: Relleno y compactado con material afirmado + bolonería de diam=6" | E76: m³ | F76: 752.0387 | G76: 79.08 | H76: =+ROUND(+IF(F76="",0,F76*G76),2) -> 59471.22
C77: OE.2.1.4.2.3 | D77: Relleno y compactado con material granular | E77: m³ | F77: 205.104 | G77: 113.45 | H77: =+ROUND(+IF(F77="",0,F77*G77),2) -> 23269.05
C78: OE.2.1.5 | D78: NIVELACION INTERIOR Y APISONADO | H78: =SUM(H79) -> 51333.09
C79: OE.2.1.5.1 | D79: Nivelación interior y apisonado | E79: m² | F79: 3771.7185 | G79: 13.61 | H79: =+ROUND(+IF(F79="",0,F79*G79),2) -> 51333.09
C80: OE.2.1.6 | D80: ELIMINACION DE MATERIAL EXCEDENTE | H80: =SUM(H81:H82) -> 2396003.6
C81: OE.2.1.6.1 | D81: Acarreo de material exedente manual | E81: m³ | F81: 9058.7215 | G81: 21.01 | H81: =+ROUND(+IF(F81="",0,F81*G81),2) -> 190323.74
C82: OE.2.1.6.3 | D82: Eliminación de material excedente con maquinaria a DME | E82: m³ | F82: 34345.685 | G82: 64.22 | H82: =+ROUND(+IF(F82="",0,F82*G82),2) -> 2205679.9
C83: OE.2.2 | D83: OBRAS CONCRETO SIMPLE | H83: =+H84+H87+H89+H91 -> 420391.23
C84: OE.2.2.1 | D84: CIMIENTOS CORRIDOS | H84: =SUM(H85:H86) -> 140292.37
C85: OE.2.2.1.1 | D85: Cimiento corridos - Concreto f'c=175 kg/cm2 | E85: m³ | F85: 195.70575 | G85: 456.34 | H85: =+ROUND(+IF(F85="",0,F85*G85),2) -> 89308.36
C86: OE.2.2.1.2 | D86: Cimiento Corrido - Encofrado y desencofrado | E86: m² | F86: 785.3359 | G86: 64.92 | H86: =+ROUND(+IF(F86="",0,F86*G86),2) -> 50984.01
C87: OE.2.2.2 | D87: SUB ZAPATAS O FALSA ZAPATA | H87: =SUM(H88) -> 131152
C88: OE.2.2.2.1 | D88: Falsa zapata f´c=100kg/cm2 + 30% P.G 10" max. | E88: m³ | F88: 400 | G88: 327.88 | H88: =+ROUND(+IF(F88="",0,F88*G88),2) -> 131152
C89: OE.2.2.3 | D89: SOLADOS | H89: =SUM(H90) -> 109927.48
C90: OE.2.2.3.1 | D90: Solado f´c=100 kg/cm2, H=10 CM | E90: m² | F90: 2673.3337 | G90: 41.12 | H90: =+ROUND(+IF(F90="",0,F90*G90),2) -> 109927.48
C91: OE.2.2.5 | D91: ESTRUCTURA DE SOSTENIMIENTO DE EXCAVACIONES | H91: =SUM(H92:H93) -> 39019.38
C92: OE.2.2.5.1 | D92: Calzaduras- concreto f'c=140 kg/cm2+30% P.M | E92: m³ | F92: 86.475 | G92: 418.22 | H92: =+ROUND(+IF(F92="",0,F92*G92),2) -> 36165.57
C93: OE.2.2.5.2 | D93: Calzadura - Encofrado y Desencofrado | E93: m² | F93: 68.75 | G93: 41.51 | H93: =+ROUND(+IF(F93="",0,F93*G93),2) -> 2853.81
C94: OE.2.3 | D94: OBRAS DE CONCRETO ARMADO | H94: =+H95+H98+H102+H106+H110+H136+H144+H151+H173+H177+H187 -> 27305693
C95: OE.2.3.2 | D95: ZAPATAS | H95: =SUM(H96:H97) -> 617879.96
C96: OE.2.3.2.1 | D96: Zapatas - Concreto pre mezclado F'C=210 KG/CM2 | E96: m³ | F96: 685.4474 | G96: 479.29 | H96: =+ROUND(+IF(F96="",0,F96*G96),2) -> 328528.08
C97: OE.2.3.2.3 | D97: Zapatas - Acero f'y=4200 kg/cm2 | E97: kg | F97: 43577.09 | G97: 6.64 | H97: =+ROUND(+IF(F97="",0,F97*G97),2) -> 289351.88
C98: OE.2.3.3 | D98: VIGAS DE CIMENTACIÓN | H98: =SUM(H99:H101) -> 407294.51
C99: OE.2.3.3.1 | D99: Viga de cimentación - concreto pre mezclado F'C=210 KG/CM2 | E99: m³ | F99: 280.6161 | G99: 478.59 | H99: =+ROUND(+IF(F99="",0,F99*G99),2) -> 134300.06
C100: OE.2.3.3.2 | D100: Vigas de Cimentación - Encofrado y desencofrado | E100: m² | F100: 956.202 | G100: 65.51 | H100: =+ROUND(+IF(F100="",0,F100*G100),2) -> 62640.79
C101: OE.2.3.3.3 | D101: Vigas de Cimentación - Acero f'y=4200 kg/cm2 | E101: kg | F101: 31679.768 | G101: 6.64 | H101: =+ROUND(+IF(F101="",0,F101*G101),2) -> 210353.66
C102: OE.2.3.4 | D102: LOSAS DE CIMENTACIÓN | H102: =SUM(H103:H105) -> 628699.85
C103: OE.2.3.4.1 | D103: Losas de cimentación - concreto pre mezclado F'C=210 KG/CM2 | E103: m³ | F103: 580.67915 | G103: 478.59 | H103: =+ROUND(+IF(F103="",0,F103*G103),2) -> 277907.23
C104: OE.2.3.4.2 | D104: Losa de Cimentación - Encofrado y Desencofrado | E104: m² | F104: 321.961 | G104: 42.24 | H104: =+ROUND(+IF(F104="",0,F104*G104),2) -> 13599.63
C105: OE.2.3.4.3 | D105: Losa de Cimentación - Acero f'y=4200 kg/cm2 | E105: kg | F105: 50782.077 | G105: 6.64 | H105: =+ROUND(+IF(F105="",0,F105*G105),2) -> 337192.99
...

Sheet Presupuesto Contingencia
C6: Item | D6: DESCRIPCION | E6: Und | F6: Metrado | G6: PU | H6: Parcial
B7: X | C7: OE.1 | D7: OBRAS PROVISIONALES, TRABAJOS PRELIMINARES, SEGURIDAD Y SALUD. | H7: =+H8+H25 -> 174052.15 | I7: 174052.15 | J7: =+I7-H7 -> 0
C8: OE.1.1 | D8: OBRAS PROVISIONALES Y TRABAJOS PRELIMINARES | H8: =+H9+H13+H16+H19+H22 -> 114613.09
C9: OE.1.1.1 | D9: CONSTRUCCIONES PROVISIONALES | H9: =SUM(H10:H12) -> 10491.66
C10: OE.1.1.1.1 | D10: Almacén Oficina y Caseta de Guardiania | E10: m2 | F10: 58 | G10: 80.81 | H10: =+ROUND(+IF(F10="",0,F10*G10),2) -> 4686.98
C11: OE.1.1.1.6 | D11: Servicios higienicos | E11: m2 | F11: 31 | G11: 165.45 | H11: =+ROUND(+IF(F11="",0,F11*G11),2) -> 5128.95
C12: OE.1.1.1.8 | D12: Cartel de Obra de 2.40X3.60 | E12: und | F12: 1 | G12: 675.73 | H12: =+ROUND(+IF(F12="",0,F12*G12),2) -> 675.73
C13: OE.1.1.2 | D13: INSTALACIONES PROVISIONALES | H13: =SUM(H14:H15) -> 4292.1
C14: OE.1.1.2.3 | D14: Energia Electrica Provisional | E14: glb | F14: 1 | G14: 2824.9 | H14: =+ROUND(+IF(F14="",0,F14*G14),2) -> 2824.9
C15: OE.1.1.2.4 | D15: Abastecimiento Provisional de agua | E15: glb | F15: 1 | G15: 1467.2 | H15: =+ROUND(+IF(F15="",0,F15*G15),2) -> 1467.2
C16: OE.1.1.3 | D16: TRABAJOS PRELIMINARES | H16: =SUM(H17:H18)/2 -> 23350.92
C17: OE.1.1.3.1 | D17: LIMPIEZA DE TERRENO | H17: =SUM(H18) -> 23350.92
C18: OE.1.1.3.1.1 | D18: Eliminación de maleza y arbustos de fácil extracción | E18: m2 | F18: 1737.42 | G18: 13.44 | H18: =+ROUND(+IF(F18="",0,F18*G18),2) -> 23350.92
C19: OE.1.1.7 | D19: MOVILIZACIÓN DE CAMPAMENTO, MAQUINARIA Y HERRAMIENTAS | H19: =SUM(H20:H21) -> 61068.65
C20: OE.1.1.7.1 | D20: Movilización y desmovilización de equipos | E20: glb | F20: 1 | G20: 1868.65 | H20: =+ROUND(+IF(F20="",0,F20*G20),2) -> 1868.65
C21: OE.1.1.7.2 | D21: Flete Terrestre | E21: glb | F21: 1 | G21: 59200 | H21: =+ROUND(+IF(F21="",0,F21*G21),2) -> 59200
C22: OE.1.1.9 | D22: TRAZOS, NIVELES Y REPLANTEO | H22: =SUM(H23:H24) -> 15409.76
C23: OE.1.1.9.1 | D23: Trazo, niveles y replanteo preliminar | E23: m2 | F23: 3081.95 | G23: 1.1 | H23: =+ROUND(+IF(F23="",0,F23*G23),2) -> 3390.15
C24: OE.1.1.9.2 | D24: Trazo y Replanteo durante el proceso | E24: m2 | F24: 3081.95 | G24: 3.9 | H24: =+ROUND(+IF(F24="",0,F24*G24),2) -> 12019.61
C25: OE.1.2 | D25: SEGURIDAD Y SALUD | H25: =+H26+H32+H35 -> 59439.06
C26: OE.1.2.1 | D26: ELABORACIÓN, IMPLEMENTACIÓN Y ADMINISTRACIÓN DEL PLAN DE SEGURIDAD Y SALUD EN EL TRABAJO | H26: =SUM(H27:H31) -> 33836.29
C27: OE.1.2.1.1 | D27: Elaboracion, Implementacion y administracion del Plan de Seguridad y Salud en el Trabajo | E27: glb | F27: 1 | G27: 3000 | H27: =+ROUND(+IF(F27="",0,F27*G27),2) -> 3000
C28: OE.1.2.1.2 | D28: Equipos de Proteccion Individual | E28: und | F28: 60 | G28: 358.21 | H28: =+ROUND(+IF(F28="",0,F28*G28),2) -> 21492.6
C29: OE.1.2.1.3 | D29: Equipos de Proteccion Colectiva | E29: glb | F29: 1 | G29: 3832.98 | H29: =+ROUND(+IF(F29="",0,F29*G29),2) -> 3832.98
C30: OE.1.2.1.4 | D30: Señalizacion Temporal de Seguridad | E30: glb | F30: 1 | G30: 4349.72 | H30: =+ROUND(+IF(F30="",0,F30*G30),2) -> 4349.72
C31: OE.1.2.1.5 | D31: Capacitacion en Seguridad y Salud | E31: glb | F31: 1 | G31: 1160.99 | H31: =+ROUND(+IF(F31="",0,F31*G31),2) -> 1160.99
C32: OE.1.2.2 | D32: RECURSOS PARA RESPUESTAS ANTE EMERGENCIAS EN SEGURIDAD Y SALUD DURANTE EL TRABAJO | H32: =SUM(H33:H34) -> 4760.06
C33: OE.1.2.2.1 | D33: Equipos de Primeros Auxilios y de Socorro | E33: glb | F33: 1 | G33: 1590.01 | H33: =+ROUND(+IF(F33="",0,F33*G33),2) -> 1590.01
C34: OE.1.2.2.2 | D34: Equipos contra incendios | E34: glb | F34: 1 | G34: 3170.05 | H34: =+ROUND(+IF(F34="",0,F34*G34),2) -> 3170.05
C35: OE.1.2.3 | D35: PLAN PARA LA VIGILANCIA PREVENCION Y CONTROL DE COVID EN EL TRABAJO | H35: =SUM(H36:H40) -> 20842.71
C36: OE.1.2.3.1 | D36: Plan para la vigilancia prevención y control de COVID en el trabajo | E36: und | F36: 1 | G36: 2499.99 | H36: =+ROUND(+IF(F36="",0,F36*G36),2) -> 2499.99
C37: OE.1.2.3.2 | D37: Equipos de Proteccion Individual -Covid19 | E37: und | F37: 60 | G37: 71.42 | H37: =+ROUND(+IF(F37="",0,F37*G37),2) -> 4285.2
C38: OE.1.2.3.3 | D38: Equipos de Proteccion Colectivo ante el COVID-19 | E38: glb | F38: 1 | G38: 2896.72 | H38: =+ROUND(+IF(F38="",0,F38*G38),2) -> 2896.72
C39: OE.1.2.3.4 | D39: Señalización temporal de seguridad ante el COVID-19 | E39: glb | F39: 1 | G39: 660.8 | H39: =+ROUND(+IF(F39="",0,F39*G39),2) -> 660.8
C40: OE.1.2.3.5 | D40: Servicio de Pruebas COVID - 19 | E40: und | F40: 60 | G40: 175 | H40: =+ROUND(+IF(F40="",0,F40*G40),2) -> 10500
B41: X | C41: OE.2 | D41: ESTRUCTURAS. | H41: =+H42+H58+H63+H84+H106 -> 2695167.6 | I41: 2695167.6 | J41: =+I41-H41 -> 0
C42: OE.2.1 | D42: MOVIMIENTO DE TIERRAS | H42: =+H43+H45+H49+H52+H55 -> 313990.51
C43: OE.2.1.1 | D43: EXCAVACIONES MASIVA | H43: =SUM(H44) -> 7815.21
C44: OE.2.1.1.1 | D44: Excavacion con maquinaria | E44: m3 | F44: 1662.81 | G44: 4.7 | H44: =+ROUND(+IF(F44="",0,F44*G44),2) -> 7815.21
C45: OE.2.1.2 | D45: EXCAVACIONES | H45: =SUM(H46:H48)/2 -> 7917.4
C46: OE.2.1.2.1 | D46: EXCAVACIONES SIMPLES | H46: =SUM(H47:H48) -> 7917.4
C47: OE.2.1.2.1.1 | D47: Excavacion manual de zanjas para Zapatas | E47: m3 | F47: 136.68 | G47: 42.02 | H47: =+ROUND(+IF(F47="",0,F47*G47),2) -> 5743.29
C48: OE.2.1.2.1.2 | D48: Excavacion manual de zanjas para Vigas de Cimentación | E48: m3 | F48: 51.74 | G48: 42.02 | H48: =+ROUND(+IF(F48="",0,F48*G48),2) -> 2174.11
C49: OE.2.1.4 | D49: RELLENOS | H49: =SUM(H50:H51) -> 179815.23
C50: OE.2.1.4.1 | D50: Relleno compactado con material de prestamo | E50: m3 | F50: 2025 | G50: 65.58 | H50: =+ROUND(+IF(F50="",0,F50*G50),2) -> 132799.5
C51: OE.2.1.4.2 | D51: Relleno compactado c/equipo con material de afirmado e=0.15m | E51: m2 | F51: 3313.3 | G51: 14.19 | H51: =+ROUND(+IF(F51="",0,F51*G51),2) -> 47015.73
C52: OE.2.1.5. | D52: NIVELACION INTERIOR Y APISONADO | H52: =SUM(H53:H54) -> 8367.4
C53: OE.2.1.5.1 | D53: Nivelacion interior y apisonado para f.piso,patio y veredas | E53: m2 | F53: 1676.35 | G53: 4.41 | H53: =+ROUND(+IF(F53="",0,F53*G53),2) -> 7392.7
C54: OE.2.1.5.2 | D54: Nivelación y compactación en área(fondo) de cimentación | E54: m2 | F54: 221.02 | G54: 4.41 | H54: =+ROUND(+IF(F54="",0,F54*G54),2) -> 974.7
C55: OE.2.1.6 | D55: ELIMINACION DE MATERIAL EXCEDENTE | H55: =SUM(H56:H57) -> 110075.27
C56: OE.2.1.6.1 | D56: Acarreo de material excavado a punto de carguio | E56: m3 | F56: 396.58 | G56: 21.01 | H56: =+ROUND(+IF(F56="",0,F56*G56),2) -> 8332.15
C57: OE.2.1.6.2 | D57: Eliminacion de material excedente con maquinaria | E57: m3 | F57: 2298.76 | G57: 44.26 | H57: =+ROUND(+IF(F57="",0,F57*G57),2) -> 101743.12
C58: OE.2.2 | D58: OBRAS DE CONCRETO SIMPLE | H58: =+H59+H61 -> 8165.86
C59: OE.2.2.2 | D59: FALSA ZAPATA | H59: =SUM(H60) -> 3117.6
C60: OE.2.2.2.1 | D60: Falsa zapata, concreto=100kg/cm2 + 50% P.G | E60: m3 | F60: 12 | G60: 259.8 | H60: =+ROUND(+IF(F60="",0,F60*G60),2) -> 3117.6
C61: OE.2.2.3 | D61: SOLADOS | H61: =SUM(H62) -> 5048.26
C62: OE.2.2.3.1 | D62: Solado para zapata e=0.10m, f'c=100kg/cm2 | E62: m2 | F62: 117.73 | G62: 42.88 | H62: =+ROUND(+IF(F62="",0,F62*G62),2) -> 5048.26
C63: OE.2.3 | D63: OBRAS DE CONCRETO ARMADO | H63: =+H64+H67+H71+H75+H80 -> 238779
C64: OE.2.3.2 | D64: ZAPATAS | H64: =SUM(H65:H66) -> 48460.13
C65: OE.2.3.2.1 | D65: Zapatas - Concreto f'c=210 kg/cm2 | E65: m3 | F65: 60.83 | G65: 439.55 | H65: =+ROUND(+IF(F65="",0,F65*G65),2) -> 26737.83
C66: OE.2.3.2.3 | D66: Zapatas - Acero f'y=4200 kg/cm2 | E66: kg | F66: 3025.39 | G66: 7.18 | H66: =+ROUND(+IF(F66="",0,F66*G66),2) -> 21722.3
C67: OE.2.3.3 | D67: VIGAS DE CIMENTACIÓN | H67: =SUM(H68:H70) -> 60035.73
C68: OE.2.3.3.1 | D68: Vigas de Conexión - Concreto f'c= 210 kg/cm2 | E68: m3 | F68: 40.33 | G68: 456.98 | H68: =+ROUND(+IF(F68="",0,F68*G68),2) -> 18430
C69: OE.2.3.3.2 | D69: Vigas de Conexión - Encofrado y desencofrado | E69: m2 | F69: 185.55 | G69: 68.05 | H69: =+ROUND(+IF(F69="",0,F69*G69),2) -> 12626.68
C70: OE.2.3.3.3 | D70: Vigas de Conexión - Acero f'y=4200 kg/cm2 | E70: kg | F70: 4036.08 | G70: 7.18 | H70: =+ROUND(+IF(F70="",0,F70*G70),2) -> 28979.05
C71: OE.2.3.7 | D71: PEDESTALES | H71: =SUM(H72:H74) -> 15363.33
C72: OE.2.3.7.1 | D72: Pedestales - Concreto f'c=210 kg/cm2 | E72: m3 | F72: 13.81 | G72: 544.15 | H72: =+ROUND(+IF(F72="",0,F72*G72),2) -> 7514.71
C73: OE.2.3.7.2 | D73: Pedestales - Encofrado y desencofrado | E73: m2 | F73: 92.43 | G73: 55.68 | H73: =+ROUND(+IF(F73="",0,F73*G73),2) -> 5146.5
C74: OE.2.3.7.3 | D74: Pedestales - Acero f'y=4200 kg/cm2 | E74: kg | F74: 376.34 | G74: 7.18 | H74: =+ROUND(+IF(F74="",0,F74*G74),2) -> 2702.12
C75: OE.2.3.9 | D75: LOSAS | H75: =SUM(H76:H79)/2 -> 53848.32
C76: OE.2.3.9.7 | D76: LOSAS COLABORANTE | H76: =SUM(H77:H79) -> 53848.32
C77: OE.2.3.9.7.1 | D77: Losa Colaborante - Concreto f'c=210 kg/cm2 | E77: m3 | F77: 29.8 | G77: 475.08 | H77: =+ROUND(+IF(F77="",0,F77*G77),2) -> 14157.38
C78: OE.2.3.9.7.2 | D78: Losa colaborante.- PLANCHA AD-900 calibre 22 ó equivalente | E78: m2 | F78: 298.03 | G78: 120.87 | H78: =+ROUND(+IF(F78="",0,F78*G78),2) -> 36022.89
C79: OE.2.3.9.7.3 | D79: Losa Colaborante - Acero Fy=4,200 kg/cm2 | E79: kg | F79: 529.3 | G79: 6.93 | H79: =+ROUND(+IF(F79="",0,F79*G79),2) -> 3668.05
C80: OE.2.3.12 | D80: CISTERNA | H80: =SUM(H81:H83) -> 61071.49
C81: OE.2.3.12.1 | D81: Cisternas -Concreto f´c=280kg/cm2 | E81: m3 | F81: 34.63 | G81: 661.41 | H81: =+ROUND(+IF(F81="",0,F81*G81),2) -> 22904.63
C82: OE.2.3.12.2 | D82: Cisternas -encofrado y desencofrado | E82: m2 | F82: 75.6 | G82: 74.31 | H82: =+ROUND(+IF(F82="",0,F82*G82),2) -> 5617.84
C83: OE.2.3.12.3 | D83: Cisternas -Acero fy=4200 kg/cm2 | E83: kg | F83: 4533.29 | G83: 7.18 | H83: =+ROUND(+IF(F83="",0,F83*G83),2) -> 32549.02
C84: OE.2.4 | D84: ESTRUCTURAS METÁLICAS | H84: =+H85+H92+H100+H104 -> 1953377.8
C85: OE.2.4.1 | D85: COLUMNAS METALICAS | H85: =SUM(H86:H91) -> 316683.08
C86: OE.2.4.1.1.1 | D86: Columnas metalicas | E86: kg | F86: 24526.69 | G86: 11.58 | H86: =+ROUND(+IF(F86="",0,F86*G86),2) -> 284019.07
C87: OE.2.4.1.1.2 | D87: Placa Base | E87: kg | F87: 1249 | G87: 8.89 | H87: =+ROUND(+IF(F87="",0,F87*G87),2) -> 11103.61
C88: OE.2.4.1.1.3 | D88: Pernos 1" (L=450mm) en placa base columnas | E88: und | F88: 40 | G88: 104.67 | H88: =+ROUND(+IF(F88="",0,F88*G88),2) -> 4186.8
C89: OE.2.4.1.1.4 | D89: Pernos 3/4" (L=450mm) en placa base columnas | E89: und | F89: 68 | G89: 86.1 | H89: =+ROUND(+IF(F89="",0,F89*G89),2) -> 5854.8
C90: OE.2.4.1.1.5 | D90: Pernos 5/8" (L=450mm) en placa base columnas | E90: und | F90: 144 | G90: 68.55 | H90: =+ROUND(+IF(F90="",0,F90*G90),2) -> 9871.2
C91: OE.2.4.1.1.6 | D91: Pernos ØM16 A490 (L=400mm) en placa base columnas | E91: und | F91: 40 | G91: 41.19 | H91: =+ROUND(+IF(F91="",0,F91*G91),2) -> 1647.6
C92: OE.2.4.2 | D92: VIGAS METALICAS | H92: =SUM(H93:H95) -> 1623087.2
C93: OE.2.4.2.1.1 | D93: Vigas Metalicas | E93: kg | F93: 132790.72 | G93: 10.86 | H93: =+ROUND(+IF(F93="",0,F93*G93),2) -> 1442107.2
C94: OE.2.4.2.2.1 | D94: Plancha Metalica | E94: kg | F94: 13273.41 | G94: 6.91 | H94: =+ROUND(+IF(F94="",0,F94*G94),2) -> 91719.26
C95: OE.2.4.2.2.2 | D95: PERNOS | H95: =SUM(H96:H99) -> 89260.77
C96: OE.2.4.2.2.2.1 | D96: Pernos 1/2" | E96: und | F96: 1596 | G96: 4.44 | H96: =+ROUND(+IF(F96="",0,F96*G96),2) -> 7086.24
C97: OE.2.4.2.2.2.2 | D97: Pernos 5/8" | E97: und | F97: 1897 | G97: 7.59 | H97: =+ROUND(+IF(F97="",0,F97*G97),2) -> 14398.23
C98: OE.2.4.2.2.2.3 | D98: Pernos 3/4" | E98: und | F98: 3422 | G98: 11.05 | H98: =+ROUND(+IF(F98="",0,F98*G98),2) -> 37813.1
C99: OE.2.4.2.2.2.4 | D99: Pernos 7/8" | E99: und | F99: 1952 | G99: 15.35 | H99: =+ROUND(+IF(F99="",0,F99*G99),2) -> 29963.2
C100: OE.2.4.3 | D100: TIJERALES METALICO | H100: =+H101+SUM(H102:H103)/2 -> 8557.52
C101: OE.2.4.3.1 | D101: Tijeral Metalico - caseta TM-Ca | E101: kg | F101: 929.56 | G101: 8.6 | H101: =+ROUND(+IF(F101="",0,F101*G101),2) -> 7994.22
C102: OE.2.4.3.1.1 | D102: PLANCHAS METALICAS | H102: =SUM(H103) -> 563.3
C103: OE.2.4.3.1.1.1 | D103: Plancha Metalica-Espesor de 6mm | E103: kg | F103: 81.52 | G103: 6.91 | H103: =+ROUND(+IF(F103="",0,F103*G103),2) -> 563.3
C104: OE.2.4.4 | D104: CORREAS METALICAS | H104: =SUM(H105) -> 5049.97
C105: OE.2.4.4.1 | D105: Correas metalicas de 75x75x3mm | E105: kg | F105: 612.86 | G105: 8.24 | H105: =+ROUND(+IF(F105="",0,F105*G105),2) -> 5049.97
...

Sheet MM-1
B3: MAYORES METRADOS N°1
B5: Item | C5: DESCRIPCION | D5: Und | E5: Metrado | F5: PU | G5: Parcial
B6: OE.1 | C6: OBRAS PROVISIONALES, TRABAJOS PRELIMINARES, SEGURIDAD Y SALUD._x000D_ | G6: =+G7 -> 39430.86
B7: OE.1.1 | C7: OBRAS PROVISIONALES Y TRABAJOS PRELIMINARES | G7: =+G8+G12 -> 39430.86
B8: OE.1.1.1 | C8: CONSTRUCCIONES PROVISIONALES | G8: =SUM(G9:G11) -> 23759.82
B9: OE.1.1.1.1 | C9: Almacén Oficina y Caseta de Guardiania | D9: m2 | E9: 214 | F9: 80.81 | G9: =+ROUND(E9*F9,2) -> 17293.34
B10: OE.1.1.1.6 | C10: Servicios higienicos | D10: m2 | E10: 35 | F10: 165.45 | G10: =+ROUND(E10*F10,2) -> 5790.75
B11: OE.1.1.1.8 | C11: Cartel de Obra de 2.40X3.60 | D11: und | E11: 1 | F11: 675.73 | G11: =+ROUND(E11*F11,2) -> 675.73
B12: OE.1.1.3 | C12: TRABAJOS PRELIMINARES | G12: =SUM(G13:G14)/2 -> 15671.04
B13: OE.1.1.3.1 | C13: LIMPIEZA DE TERRENO | G13: =SUM(G14) -> 15671.04
B14: OE.1.1.3.1.1 | C14: Eliminación de maleza y arbustos de fácil extracción | D14: m2 | E14: 1166 | F14: 13.44 | G14: =+ROUND(E14*F14,2) -> 15671.04
B15: OE.2 | C15: ESTRUCTURAS | G15: =+G16 -> 7126.54
B16: OE.2.1 | C16: MOVIMIENTO DE TIERRAS | G16: =+G17+G19 -> 7126.54
B17: OE.2.1.5. | C17: NIVELACION INTERIOR Y APISONADO | G17: =SUM(G18) -> 5622.75
B18: OE.2.1.5.1 | C18: Nivelacion interior y apisonado para f.piso,patio y veredas | D18: m2 | E18: 1275 | F18: 4.41 | G18: =+ROUND(E18*F18,2) -> 5622.75
B19: OE.2.6.5 | C19: CONTROL DE CALIDAD | G19: =SUM(G20:G21) -> 1503.79
B20: OE.2.6.5.4 | C20: Rotura de Briquetas de concreto | D20: und | E20: 14 | F20: 50 | G20: =+ROUND(E20*F20,2) -> 700
B21: OE.2.6.5.5 | C21: Pruebas de soldadura | D21: und | E21: 27 | F21: 29.77 | G21: =+ROUND(E21*F21,2) -> 803.79
B22: OE.3 | C22: ARQUITECTURA | G22: =+G23+G26 -> 74554.92
B23: OE.3.3 | C23: CIELORRASOS | G23: =+G24 -> 22653.34
B24: OE.3.3.6 | C24: FALSO CIELO RASO | G24: =SUM(G25) -> 22653.34
B25: OE.3.3.6.1 | C25: FALSO CIELORRASO (BALDOSA DE FIBRA MINERAL BIOSOLUBLE 0.61 x 0.61m, E=14mm.) | D25: m2 | E25: 315.77 | F25: 71.74 | G25: =+ROUND(E25*F25,2) -> 22653.34
B26: OE.3.4 | C26: PISOS Y PAVIMENTOS | G26: =+G27 -> 51901.58
B27: OE.3.4.1 | C27: CONTRAPISOS | G27: =SUM(G28) -> 51901.58
B28: OE.3.4.1.1 | C28: Contrapiso de concreto f'c=175 kg/cm2 e =5 cm | D28: m2 | E28: 1716.89 | F28: 30.23 | G28: =+ROUND(E28*F28,2) -> 51901.58
C29: TOTAL | G29: =+G22+G15+G6 -> 121112.32
G31: 121112.32
G32: =+G31-G29 -> 0

Sheet PN-1
B3: PARTIDAS NUEVAS N°1
B5: Item | C5: DESCRIPCION | D5: Und | E5: Metrado | F5: PU | G5: Parcial
B6: OE.1 | C6: OBRAS PROVISIONALES, TRABAJOS PRELIMINARES, SEGURIDAD Y SALUD._x000D_ | G6: =+G7 -> 132711.56
B7: OE.1.1 | C7: OBRAS PROVISIONALES Y TRABAJOS PRELIMINARES | G7: =+G8 -> 132711.56
B8: OE.1.1.3 | C8: TRABAJOS PRELIMINARES | G8: =SUM(G9:G13)/2 -> 132711.56
B9: OE.1.1.3.1 | C9: LIMPIEZA DE TERRENO | G9: =SUM(G10:G13) -> 132711.56
B10: OE.1.1.3.1.2 | C10: Traslado de material en desuso d=100 m | D10: m3 | E10: 1916 | F10: 40.45 | G10: =+ROUND(E10*F10,2) -> 77502.2
B11: OE.1.1.3.1.3 | C11: Limpieza de terreno | D11: m2 | E11: 3002 | F11: 2.61 | G11: =+ROUND(E11*F11,2) -> 7835.22
B12: OE.1.1.3.1.4 | C12: Acarreo manual de material de desmonte | D12: m3 | E12: 802 | F12: 25.21 | G12: =+ROUND(E12*F12,2) -> 20218.42
B13: OE.1.1.3.1.5 | C13: Eliminacion de desmonte con maquinaria | D13: m3 | E13: 802 | F13: 33.86 | G13: =+ROUND(E13*F13,2) -> 27155.72
B14: OE.2 | C14: ESTRUCTURAS. | G14: =+G15+G19+G32+G62 -> 1683126.1
B15: OE.2.2 | C15: OBRAS DE CONCRETO SIMPLE | G15: =+G16 -> 58685.18
B16: OE.2.2.4 | C16: DADOS DE ANCLAJE | G16: =SUM(G17:G18) -> 58685.18
B17: OE.2.2.4.1 | C17: Dado de anclaje f'c= 210 kg/cm2 | D17: und | E17: 337 | F17: 72.23 | G17: =+ROUND(E17*F17,2) -> 24341.51
B18: OE.2.2.4.2 | C18: Acero en dado de anclaje para cimientos de columna | D18: kg | E18: 1011 | F18: 33.97 | G18: =+ROUND(E18*F18,2) -> 34343.67
B19: OE.2.3 | C19: OBRAS DE CONCRETO ARMADO | G19: =+G20+G25+G29 -> 401553.45
B20: OE.2.3.9 | C20: LOSAS | G20: =SUM(G21:G24)/2 -> 203103.08
B21: OE.2.3.9.8 | C21: LOSAS DE CONCRETO | G21: =SUM(G22:G24) -> 203103.08
B22: OE.2.3.9.8.1 | C22: Concreto f'c=210 kg/cm2 en losa | D22: m3 | E22: 294.95 | F22: 466.32 | G22: =+ROUND(E22*F22,2) -> 137541.08
B23: OE.2.3.9.8.2 | C23: Encofrado y desencofrado en losa de concreto | D23: m2 | E23: 98.09 | F23: 65.1 | G23: =+ROUND(E23*F23,2) -> 6385.66
B24: OE.2.3.9.8.3 | C24: Acero f'y=4200 kg/cm2 en losa de concreto | D24: kg | E24: 8084.2 | F24: 7.32 | G24: =+ROUND(E24*F24,2) -> 59176.34
B25: OE.2.3.13 | C25: SOBRECIMIENTO ARMADO | G25: =SUM(G26:G28) -> 23310.4
B26: OE.2.3.13.1 | C26: Sobrecimiento concreto 1:8+25%PM | D26: m3 | E26: 16.9 | F26: 328.51 | G26: =+ROUND(E26*F26,2) -> 5551.82
B27: OE.2.3.13.2 | C27: Encofrado y desencofrado en sobrecimiento | D27: m2 | E27: 242.48 | F27: 67.61 | G27: =+ROUND(E27*F27,2) -> 16394.07
B28: OE.2.3.13.3 | C28: Acero f'y=4200 kg/cm2 en sobrecimiento | D28: kg | E28: 489.07 | F28: 2.79 | G28: =+ROUND(E28*F28,2) -> 1364.51
B29: OE.2.3.14 | C29: CIMIENTO CORRIDO | G29: =SUM(G30:G31) -> 175139.97
B30: OE.2.3.14.1 | C30: Concreto f'c= 175 kg/cm2 en cimiento | D30: m3 | E30: 135.21 | F30: 379.99 | G30: =+ROUND(E30*F30,2) -> 51378.45
B31: OE.2.3.14.2 | C31: Encofrado y desencofrado en cimiento | D31: m2 | E31: 387.36 | F31: 319.5 | G31: =+ROUND(E31*F31,2) -> 123761.52
B32: OE.2.4 | C32: ESTRUCTURAS METÁLICAS | G32: =+G33+G37+G41 -> 1134817.5
B33: OE.2.4.1 | C33: COLUMNAS METALICAS | G33: =SUM(G34:G36) -> 320358.96
B34: OE.2.4.1.1.7 | C34: Placa Base Inc. Pernos de anclaje | D34: und | E34: 337 | F34: 160.83 | G34: =+ROUND(E34*F34,2) -> 54199.71
B35: OE.2.4.1.1.8 | C35: Armado Columnas metálicas 150x100x4mm (L=6m) | D35: kg | E35: 17685 | F35: 11.46 | G35: =+ROUND(E35*F35,2) -> 202670.1
B36: OE.2.4.1.1.9 | C36: Montaje Columnas metálicas 150x100x4mm (L=6m) | D36: kg | E36: 17685 | F36: 3.59 | G36: =+ROUND(E36*F36,2) -> 63489.15
B37: OE.2.4.2 | C37: VIGAS METALICAS | G37: =SUM(G38:G40) -> 298945.7
B38: OE.2.4.2.2.2.5 | C38: Plancha Metalica Inc.Pernos de sujeción | D38: und | E38: 337 | F38: 136.23 | G38: =+ROUND(E38*F38,2) -> 45909.51
B39: OE.2.4.2.2.2.6 | C39: Armado vigas metálicas 150x100mm e= 3mm | D39: m | E39: 927.45 | F39: 201.95 | G39: =+ROUND(E39*F39,2) -> 187298.53
B40: OE.2.4.2.2.2.7 | C40: Montaje vigas metálicas 150x100 mm e=3mm | D40: m | E40: 927.45 | F40: 70.88 | G40: =+ROUND(E40*F40,2) -> 65737.66
B41: OE.2.4.3 | C41: TIJERALES METALICO | G41: =SUM(G42:G61)/2 -> 515512.85
B42: OE.2.4.3.2 | C42: Armado de Tijeral Metalico | G42: =SUM(G43:G50) -> 285585.65
B43: OE.2.4.3.2.1 | C43: Armado de Tijeral metalico Tipo 01 L=7.00 m | D43: und | E43: 28 | F43: 2166.84 | G43: =+ROUND(E43*F43,2) -> 60671.52
B44: OE.2.4.3.2.2 | C44: Armado de Tijeral metalico Tipo 02 L=6.00 m | D44: und | E44: 72 | F44: 2101.64 | G44: =+ROUND(E44*F44,2) -> 151318.08
B45: OE.2.4.3.2.3 | C45: Armado de Tijeral metalico Tipo 03 L=3.50 m | D45: und | E45: 1 | F45: 1309.99 | G45: =+ROUND(E45*F45,2) -> 1309.99
B46: OE.2.4.3.2.4 | C46: Armado de Tijeral metalico Tipo 04 L=3.10 m | D46: und | E46: 13 | F46: 1280.92 | G46: =+ROUND(E46*F46,2) -> 16651.96
B47: OE.2.4.3.2.5 | C47: Armado de Tijeral metalico Tipo 05 L=3.00 m | D47: und | E47: 2 | F47: 1316.4 | G47: =+ROUND(E47*F47,2) -> 2632.8
B48: OE.2.4.3.2.6 | C48: Armado de Tijeral metalico Tipo 06 L=2.60 m | D48: und | E48: 15 | F48: 1238.4 | G48: =+ROUND(E48*F48,2) -> 18576
B49: OE.2.4.3.2.7 | C49: Armado de Tijeral metalico Tipo 07 L=1.90 m | D49: und | E49: 15 | F49: 1202.92 | G49: =+ROUND(E49*F49,2) -> 18043.8
B50: OE.2.4.3.2.8 | C50: Armado de Tijeral metalico Tipo 08 L=1.30 m | D50: und | E50: 15 | F50: 1092.1 | G50: =+ROUND(E50*F50,2) -> 16381.5
B51: OE.2.4.3.3 | C51: Montaje de Tijeral Metalico | G51: =SUM(G52:G59) -> 61735.9
B52: OE.2.4.3.3.1 | C52: Montaje de Tijeral metalico Tipo 01 L=7.00 m | D52: und | E52: 28 | F52: 473.12 | G52: =+ROUND(E52*F52,2) -> 13247.36
B53: OE.2.4.3.3.2 | C53: Montaje de Tijeral metalico Tipo 02 L=6.00 m | D53: und | E53: 72 | F53: 469.92 | G53: =+ROUND(E53*F53,2) -> 33834.24
B54: OE.2.4.3.3.3 | C54: Montaje de Tijeral metalico Tipo 03 L=3.50 m | D54: und | E54: 2 | F54: 292.6 | G54: =+ROUND(E54*F54,2) -> 585.2
B55: OE.2.4.3.3.4 | C55: Montaje de Tijeral metalico Tipo 04 L=3.10 m | D55: und | E55: 13 | F55: 326.39 | G55: =+ROUND(E55*F55,2) -> 4243.07
B56: OE.2.4.3.3.5 | C56: Montaje de Tijeral metalico Tipo 05 L=3.00 m | D56: und | E56: 2 | F56: 326.39 | G56: =+ROUND(E56*F56,2) -> 652.78
B57: OE.2.4.3.3.6 | C57: Montaje de Tijeral metalico Tipo 06 L=2.60 m | D57: und | E57: 15 | F57: 213.71 | G57: =+ROUND(E57*F57,2) -> 3205.65
B58: OE.2.4.3.3.7 | C58: Montaje de Tijeral metalico Tipo 07 L=1.90 m | D58: und | E58: 15 | F58: 213.71 | G58: =+ROUND(E58*F58,2) -> 3205.65
B59: OE.2.4.3.3.8 | C59: Montaje de Tijeral metalico Tipo 08 L=1.30 m | D59: und | E59: 15 | F59: 184.13 | G59: =+ROUND(E59*F59,2) -> 2761.95
B60: OE.2.4.4 | C60: CORREAS METALICAS | G60: =SUM(G61) -> 168191.3
B61: OE.2.4.4.2 | C61: Correas metalicas de 50x50x3mm | D61: m | E61: 3215.28 | F61: 52.31 | G61: =+ROUND(E61*F61,2) -> 168191.3
B62: OE.2.6 | C62: VARIOS | G62: =+G63+G65 -> 88069.92
B63: OE.2.6.6 | C63: CURADO Y PROTECCION DEL CONCRETO | G63: =SUM(G64) -> 9543.58
B64: OE.2.6.6.2 | C64: Curado y Proteccion de Concreto | D64: m2 | E64: 2658.38 | F64: 3.59 | G64: =+ROUND(E64*F64,2) -> 9543.58
B65: OE.2.6.7 | C65: CERCO METÁLICO | G65: =SUM(G66) -> 78526.34
B66: OE.2.6.7.1 | C66: Cerco perimetrico de rejas metalicas | D66: m | E66: 140.64 | F66: 558.35 | G66: =+ROUND(E66*F66,2) -> 78526.34
B67: OE.3 | C67: ARQUITECTURA | G67: =+G68+G72+G75+G84+G93+G100 -> 1945181.4
B68: OE.3.1 | C68: MUROS Y TABIQUES DE ALBAÑILERIA | G68: =+G69 -> 624878.72
B69: OE.3.1.10 | C69: MUROS CON EL SISTEMA DE CONSTRUCCIÓN EN SECO (SISTEMA DRY WALL O SIMILAR) | G69: =SUM(G70:G71) -> 624878.72
B70: OE.3.1.10.5 | C70: Tabique de Fibrocemento de 6 mm(interiores) y Fibrocemento de 12mm (Exterior) perfil 65 mm e=9.04 | D70: m2 | E70: 1770.22 | F70: 194.25 | G70: =+ROUND(E70*F70,2) -> 343865.24
B71: OE.3.1.10.6 | C71: Tabique de Fibrocemento dos caras de 6 mm (interiores) | D71: m2 | E71: 1914 | F71: 146.82 | G71: =+ROUND(E71*F71,2) -> 281013.48
B72: OE.3.3 | C72: CIELORRASOS | G72: =+G73 -> 182063.62
B73: OE.3.3.6 | C73: FALSO CIELO RASO | G73: =SUM(G74) -> 182063.62
B74: OE.3.3.6.4 | C74: Falso Cielorraso (Baldosa Translucida 0.61 x 0.61m) | D74: m2 | E74: 477.92 | F74: 380.95 | G74: =+ROUND(E74*F74,2) -> 182063.62
B75: OE.3.4 | C75: PISOS Y PAVIMENTOS | G75: =+G76+G80 -> 57589.75
B76: OE.3.4.2 | C76: PISOS | G76: =SUM(G77:G79) -> 24789.04
B77: OE.3.4.2.25 | C77: Piso de Cemento Pulido | D77: m2 | E77: 46.41 | F77: 39.74 | G77: =+ROUND(E77*F77,2) -> 1844.33
B78: OE.3.4.2.26 | C78: Piso Vinilico Conductivo | D78: m2 | E78: 33.02 | F78: 191.14 | G78: =+ROUND(E78*F78,2) -> 6311.44
B79: OE.3.4.2.27 | C79: Piso de terrazo | D79: m2 | E79: 147.72 | F79: 112.6 | G79: =+ROUND(E79*F79,2) -> 16633.27
B80: OE.3.4.3 | C80: PISOS DE CONCRETO | G80: =SUM(G81:G83)/2 -> 32800.71
B81: OE.3.4.3.3 | C81: CIRCULACION EN PATIO DE MANIOBRAS | G81: =SUM(G82:G83) -> 32800.71
B82: OE.3.4.3.3.1 | C82: Empedrado e= 10 cm | D82: m2 | E82: 486.33 | F82: 26.17 | G82: =+ROUND(E82*F82,2) -> 12727.26
B83: OE.3.4.3.3.2 | C83: Falso Piso - Concreto f'c=175 kg/cm², e=0.07 m | D83: m3 | E83: 36.47 | F83: 550.41 | G83: =+ROUND(E83*F83,2) -> 20073.45
B84: OE.3.5 | C84: ZOCALOS Y CONTRAZOCALOS | G84: =+G85+G88 -> 117130.92
B85: OE.3.5.1 | C85: ZOCALOS | G85: =SUM(G86:G87) -> 45659.11
B86: OE.3.5.1.12 | C86: Zocalo de porcelanato de 60X 60 cm | D86: m2 | E86: 331.36 | F86: 60.89 | G86: =+ROUND(E86*F86,2) -> 20176.51
B87: OE.3.5.1.13 | C87: Revestimiento Vinilico Conductivo | D87: m2 | E87: 102.74 | F87: 248.03 | G87: =+ROUND(E87*F87,2) -> 25482.6
B88: OE.3.5.2 | C88: CONTRAZOCALOS | G88: =SUM(G89:G92)/2 -> 71471.81
B89: OE.3.5.2.3 | C89: CONTRAZOCALOS DE CERAMICO | G89: =SUM(G90:G92) -> 71471.81
B90: OE.3.5.2.3.3 | C90: Contrazocalo de ceramico (H=10cm) | D90: m | E90: 928.53 | F90: 30.45 | G90: =+ROUND(E90*F90,2) -> 28273.74
B91: OE.3.5.2.3.4 | C91: Contrazocalo de Terrazo (H=10cm) | D91: m | E91: 446.16 | F91: 95.64 | G91: =+ROUND(E91*F91,2) -> 42670.74
B92: OE.3.5.2.3.5 | C92: Contrazocalo de Cemento pulido (H=10cm) | D92: m | E92: 27.96 | F92: 18.86 | G92: =+ROUND(E92*F92,2) -> 527.33
B93: OE.3.6 | C93: COBERTURAS | G93: =+G94+G98 -> 570934.45
B94: OE.3.6.7 | C94: RECUBRIMIENTOS SOBRE ESTRUCTURAS DE MADERA, METAL, ETC. | G94: =SUM(G95:G97) -> 548719.59
B95: OE.3.6.7.4 | C95: Cobertura con panel termoacústico relleno de poliuretano | D95: m2 | E95: 1789.7 | F95: 278.26 | G95: =+ROUND(E95*F95,2) -> 498001.92
B96: OE.3.6.7.5 | C96: Cumbrera para panel termoacústico | D96: m | E96: 250.36 | F96: 31.21 | G96: =+ROUND(E96*F96,2) -> 7813.74
B97: OE.3.6.7.6 | C97: Cobertura con policarbonato e=10 mm | D97: m2 | E97: 556.76 | F97: 77.06 | G97: =+ROUND(E97*F97,2) -> 42903.93
B98: OE.3.6.9 | C98: OTROS | G98: =SUM(G99) -> 22214.86
B99: OE.3.6.9.2 | C99: Cerramiento con policarbonato e=10 mm | D99: m2 | E99: 361.57 | F99: 61.44 | G99: =+ROUND(E99*F99,2) -> 22214.86
B100: OE.3.11 | C100: PINTURA | G100: =SUM(G101:G104) -> 392583.96
B101: OE.3.11.1.4 | C101: Pintura muros interiores c/ latex antibacterial (2 MANOS). C/ IMPRIMANTE | D101: m2 | E101: 4351.2 | F101: 33.84 | G101: =+ROUND(E101*F101,2) -> 147244.61
B102: OE.3.11.1.5 | C102: Pintura muros exteriores c/ latex satinado (2 manos). c/ imprimante | D102: m2 | E102: 1649.28 | F102: 30.84 | G102: =+ROUND(E102*F102,2) -> 50863.8
B103: OE.3.11.1.6 | C103: Empastado y lijado de muros interiores | D103: m2 | E103: 4351.2 | F103: 32.41 | G103: =+ROUND(E103*F103,2) -> 141022.39
...

Sheet DD-1
B4: DEDUCTIVOS
B6: Item | C6: Descripción | D6: Und. | E6: Metrado | F6: Precio S/. | G6: Parcial S/.
B7: OE.2 | C7: ESTRUCTURAS. | G7: =+G8+G11+G28+G50 -> 2148901
B8: OE.2.2 | C8: OBRAS DE CONCRETO SIMPLE | G8: =+G9 -> 3117.6
B9: OE.2.2.2 | C9: FALSA ZAPATA | G9: =SUM(G10) -> 3117.6
B10: OE.2.2.2.1 | C10: Falsa zapata, concreto=100kg/cm2 + 50% P.G | D10: m3 | E10: 12 | F10: 259.8 | G10: =+ROUND(E10*F10,2) -> 3117.6
B11: OE.2.3 | C11: OBRAS DE CONCRETO ARMADO | G11: =+G12+G15+G19+G23 -> 177707.51
B12: OE.2.3.2 | C12: ZAPATAS | G12: =SUM(G13:G14) -> 48460.13
B13: OE.2.3.2.1 | C13: Zapatas - Concreto f'c=210 kg/cm2 | D13: m3 | E13: 60.83 | F13: 439.55 | G13: =+ROUND(E13*F13,2) -> 26737.83
B14: OE.2.3.2.3 | C14: Zapatas - Acero f'y=4200 kg/cm2 | D14: kg | E14: 3025.39 | F14: 7.18 | G14: =+ROUND(E14*F14,2) -> 21722.3
B15: OE.2.3.3 | C15: VIGAS DE CIMENTACIÓN | G15: =SUM(G16:G18) -> 60035.73
B16: OE.2.3.3.1 | C16: Vigas de Conexión - Concreto f'c= 210 kg/cm2 | D16: m3 | E16: 40.33 | F16: 456.98 | G16: =+ROUND(E16*F16,2) -> 18430
B17: OE.2.3.3.2 | C17: Vigas de Conexión - Encofrado y desencofrado | D17: m2 | E17: 185.55 | F17: 68.05 | G17: =+ROUND(E17*F17,2) -> 12626.68
B18: OE.2.3.3.3 | C18: Vigas de Conexión - Acero f'y=4200 kg/cm2 | D18: kg | E18: 4036.08 | F18: 7.18 | G18: =+ROUND(E18*F18,2) -> 28979.05
B19: OE.2.3.7 | C19: PEDESTALES | G19: =SUM(G20:G22) -> 15363.33
B20: OE.2.3.7.1 | C20: Pedestales - Concreto f'c=210 kg/cm2 | D20: m3 | E20: 13.81 | F20: 544.15 | G20: =+ROUND(E20*F20,2) -> 7514.71
B21: OE.2.3.7.2 | C21: Pedestales - Encofrado y desencofrado | D21: m2 | E21: 92.43 | F21: 55.68 | G21: =+ROUND(E21*F21,2) -> 5146.5
B22: OE.2.3.7.3 | C22: Pedestales - Acero f'y=4200 kg/cm2 | D22: kg | E22: 376.34 | F22: 7.18 | G22: =+ROUND(E22*F22,2) -> 2702.12
B23: OE.2.3.9 | C23: LOSAS | G23: =SUM(G24:G27)/2 -> 53848.32
B24: OE.2.3.9.7 | C24: LOSAS COLABORANTE | G24: =SUM(G25:G27) -> 53848.32
B25: OE.2.3.9.7.1 | C25: Losa Colaborante - Concreto f'c=210 kg/cm2 | D25: m3 | E25: 29.8 | F25: 475.08 | G25: =+ROUND(E25*F25,2) -> 14157.38
B26: OE.2.3.9.7.2 | C26: Losa colaborante.- PLANCHA AD-900 calibre 22 ó equivalente | D26: m2 | E26: 298.03 | F26: 120.87 | G26: =+ROUND(E26*F26,2) -> 36022.89
B27: OE.2.3.9.7.3 | C27: Losa Colaborante - Acero Fy=4,200 kg/cm2 | D27: kg | E27: 529.3 | F27: 6.93 | G27: =+ROUND(E27*F27,2) -> 3668.05
B28: OE.2.4 | C28: ESTRUCTURAS METÁLICAS | G28: =+G29+G36+G44+G48 -> 1953377.8
B29: OE.2.4.1 | C29: COLUMNAS METALICAS | G29: =SUM(G30:G35) -> 316683.08
B30: OE.2.4.1.1.1 | C30: Columnas metalicas | D30: kg | E30: 24526.69 | F30: 11.58 | G30: =+ROUND(E30*F30,2) -> 284019.07
B31: OE.2.4.1.1.2 | C31: Placa Base | D31: kg | E31: 1249 | F31: 8.89 | G31: =+ROUND(E31*F31,2) -> 11103.61
B32: OE.2.4.1.1.3 | C32: Pernos 1" (L=450mm) en placa base columnas | D32: und | E32: 40 | F32: 104.67 | G32: =+ROUND(E32*F32,2) -> 4186.8
B33: OE.2.4.1.1.4 | C33: Pernos 3/4" (L=450mm) en placa base columnas | D33: und | E33: 68 | F33: 86.1 | G33: =+ROUND(E33*F33,2) -> 5854.8
B34: OE.2.4.1.1.5 | C34: Pernos 5/8" (L=450mm) en placa base columnas | D34: und | E34: 144 | F34: 68.55 | G34: =+ROUND(E34*F34,2) -> 9871.2
B35: OE.2.4.1.1.6 | C35: Pernos ØM16 A490 (L=400mm) en placa base columnas | D35: und | E35: 40 | F35: 41.19 | G35: =+ROUND(E35*F35,2) -> 1647.6
B36: OE.2.4.2 | C36: VIGAS METALICAS | G36: =SUM(G37:G43)-G39 -> 1623087.2
B37: OE.2.4.2.1.1 | C37: Vigas Metalicas | D37: kg | E37: 132790.72 | F37: 10.86 | G37: =+ROUND(E37*F37,2) -> 1442107.2
B38: OE.2.4.2.2.1 | C38: Plancha Metalica | D38: kg | E38: 13273.41 | F38: 6.91 | G38: =+ROUND(E38*F38,2) -> 91719.26
B39: OE.2.4.2.2.2 | C39: PERNOS | G39: =SUM(G40:G43) -> 89260.77
B40: OE.2.4.2.2.2.1 | C40: Pernos 1/2" | D40: und | E40: 1596 | F40: 4.44 | G40: =+ROUND(E40*F40,2) -> 7086.24
B41: OE.2.4.2.2.2.2 | C41: Pernos 5/8" | D41: und | E41: 1897 | F41: 7.59 | G41: =+ROUND(E41*F41,2) -> 14398.23
B42: OE.2.4.2.2.2.3 | C42: Pernos 3/4" | D42: und | E42: 3422 | F42: 11.05 | G42: =+ROUND(E42*F42,2) -> 37813.1
B43: OE.2.4.2.2.2.4 | C43: Pernos 7/8" | D43: und | E43: 1952 | F43: 15.35 | G43: =+ROUND(E43*F43,2) -> 29963.2
B44: OE.2.4.3 | C44: TIJERALES METALICO | G44: =SUM(G45:G47)-G46 -> 8557.52
B45: OE.2.4.3.1 | C45: Tijeral Metalico - caseta TM-Ca | D45: kg | E45: 929.56 | F45: 8.6 | G45: =+ROUND(E45*F45,2) -> 7994.22
B46: OE.2.4.3.1.1 | C46: PLANCHAS METALICAS | G46: =SUM(G47) -> 563.3
B47: OE.2.4.3.1.1.1 | C47: Plancha Metalica-Espesor de 6mm | D47: kg | E47: 81.52 | F47: 6.91 | G47: =+ROUND(E47*F47,2) -> 563.3
B48: OE.2.4.4 | C48: CORREAS METALICAS | G48: =SUM(G49) -> 5049.97
B49: OE.2.4.4.1 | C49: Correas metalicas de 75x75x3mm | D49: kg | E49: 612.86 | F49: 8.24 | G49: =+ROUND(E49*F49,2) -> 5049.97
B50: OE.2.6 | C50: VARIOS | G50: =+G51+G55 -> 14698.04
B51: OE.2.6.2 | C51: ESCALERA METALICA | G51: =SUM(G52:G54) -> 13596.97
B52: OE.2.6.2.1 | C52: Perfiles | D52: kg | E52: 1520.27 | F52: 8.4 | G52: =+ROUND(E52*F52,2) -> 12770.27
B53: OE.2.6.2.2 | C53: Placa Base e=16mm | D53: kg | E53: 42.39 | F53: 16.96 | G53: =+ROUND(E53*F53,2) -> 718.93
B54: OE.2.6.2.3 | C54: Refuerzo en la base e=6mm | D54: kg | E54: 12.43 | F54: 8.67 | G54: =+ROUND(E54*F54,2) -> 107.77
B55: OE.2.6.6 | C55: CURADO Y PROTECCION DEL CONCRETO | G55: =SUM(G56) -> 1101.07
B56: OE.2.6.6.1 | C56: Curado y Protección de Concreto en Obra con Plástico | D56: mes | E56: 1 | F56: 1101.07 | G56: =+ROUND(E56*F56,2) -> 1101.07
B57: OE.3 | C57: ARQUITECTURA | G57: =+G58+G63+G66+G74+G80+G87+G92 -> 4429007.4
B58: OE.3.1 | C58: MUROS Y TABIQUES DE ALBAÑILERIA | G58: =+G59 -> 109253.67
B59: OE.3.1.10 | C59: MUROS CON EL SISTEMA DE CONSTRUCCIÓN EN SECO (SISTEMA DRY WALL O SIMILAR) | G59: =SUM(G60:G62) -> 109253.67
B60: OE.3.1.10.1 | C60: MURO CON EL SISTEMA DRYWALL DOS CARAS | D60: m2 | E60: 277.65 | F60: 140.54 | G60: =+ROUND(E60*F60,2) -> 39020.93
B61: OE.3.1.10.2 | C61: CERCO PREFABRICADO DE CONCRETO TIPO PLACA H=3.00M. | D61: m | E61: 209.31 | F61: 287 | G61: =+ROUND(E61*F61,2) -> 60071.97
B62: OE.3.1.10.4 | C62: TABIQUE DE DOS CARAS CON UNA PLANCHA DE FIBROCEMENTO SUPERBOARD PRO 12.7 mm | D62: m2 | E62: 72.66 | F62: 139.84 | G62: =+ROUND(E62*F62,2) -> 10160.77
B63: OE.3.3 | C63: CIELORRASOS | G63: =+G64 -> 8630.53
B64: OE.3.3.6 | C64: FALSO CIELO RASO | G64: =SUM(G65) -> 8630.53
B65: OE.3.3.6.2 | C65: FALSO CIELO RASO CON PLACA DE SUPERBOARD (6mm.) | D65: m2 | E65: 154.42 | F65: 55.89 | G65: =+ROUND(E65*F65,2) -> 8630.53
B66: OE.3.4 | C66: PISOS Y PAVIMENTOS | G66: =+G67+G69 -> 39752.48
B67: OE.3.4.2 | C67: PISOS | G67: =SUM(G68) -> 925.44
B68: OE.3.4.2.21 | C68: Piso Ceramico de 45x45 antideslizante de alto transito | D68: m2 | E68: 19.2 | F68: 48.2 | G68: =+ROUND(E68*F68,2) -> 925.44
B69: OE.3.4.3 | C69: PISOS DE CONCRETO | G69: =SUM(G70:G73)/2 -> 38827.04
B70: OE.3.4.3.1 | C70: CIRCULACION INTERIOR | G70: =SUM(G71:G73) -> 38827.04
B71: OE.3.4.3.1.1 | C71: Afirmado y Compactado de 4" con Material Propio | D71: m2 | E71: 554.63 | F71: 3.66 | G71: =+ROUND(E71*F71,2) -> 2029.95
B72: OE.3.4.3.1.2 | C72: Encofrado y desencofrado | D72: m2 | E72: 140.28 | F72: 33.43 | G72: =+ROUND(E72*F72,2) -> 4689.56
B73: OE.3.4.3.1.3 | C73: Concreto f'c=175 kg/cm², e=0.15m | D73: m2 | E73: 554.63 | F73: 57.89 | G73: =+ROUND(E73*F73,2) -> 32107.53
B74: OE.3.5 | C74: ZOCALOS Y CONTRAZOCALOS | G74: =+G75+G77 -> 5176.97
B75: OE.3.5.1 | C75: ZOCALOS | G75: =SUM(G76) -> 2018.57
B76: OE.3.5.1.11 | C76: Zocalo de cerámico de 45 X 45 cm | D76: m2 | E76: 26.1 | F76: 77.34 | G76: =+ROUND(E76*F76,2) -> 2018.57
B77: OE.3.5.2 | C77: CONTRAZOCALOS | G77: =SUM(G78:G79)/2 -> 3158.4
B78: OE.3.5.2.3 | C78: CONTRAZOCALOS DE CERAMICO | G78: =SUM(G79) -> 3158.4
B79: OE.3.5.2.3.2 | C79: Contrazocalo de cerámico de 45x10 cm (H=10cm) | D79: m | E79: 132.04 | F79: 23.92 | G79: =+ROUND(E79*F79,2) -> 3158.4
B80: OE.3.6 | C80: COBERTURAS | G80: =+G81+G85 -> 315978.39
B81: OE.3.6.7 | C81: RECUBRIMIENTOS SOBRE ESTRUCTURAS DE MADERA, METAL, ETC. | G81: =SUM(G82:G84) -> 211076.35
B82: OE.3.6.7.1 | C82: COBERTURA. PANEL COMPUESTA POR 5 CAPAS, PREPINTADO ESTANDAR E=2.25 mm | D82: m2 | E82: 1630.97 | F82: 94.47 | G82: =+ROUND(E82*F82,2) -> 154077.74
B83: OE.3.6.7.2 | C83: COBERTURA. TEJA POLICARBONATO E=1.0 mm. | D83: m2 | E83: 534.56 | F83: 101.41 | G83: =+ROUND(E83*F83,2) -> 54209.73
B84: OE.3.6.7.3 | C84: CUMBRERA LISA, E= 0.5mm | D84: m | E84: 71.4 | F84: 39.06 | G84: =+ROUND(E84*F84,2) -> 2788.88
B85: OE.3.6.9 | C85: OTROS | G85: =SUM(G86) -> 104902.04
B86: OE.3.6.9.1 | C86: CERRAMIENTO CON POLICARBONATO SOLIDO E=6 mm. | D86: m2 | E86: 370.6 | F86: 283.06 | G86: =+ROUND(E86*F86,2) -> 104902.04
B87: OE.3.11 | C87: PINTURA | G87: =+G88 -> 13214.65
B88: OE.3.11.1 | C88: PINTURA DE CIELOS RASOS, VIGAS, COLUMNAS Y PAREDES | G88: =SUM(G89:G91) -> 13214.65
B89: OE.3.11.1.1 | C89: PINTURA CIELORASO C/LATEX SATINADO (2MANOS), C/IMPRIMANTE | D89: m2 | E89: 172.6 | F89: 19.16 | G89: =+ROUND(E89*F89,2) -> 3307.02
B90: OE.3.11.1.2 | C90: PINTURA MUROS INTERIORES C/ LATEX (2 MANOS). C/ IMPRIMANTE | D90: m2 | E90: 321.26 | F90: 19.16 | G90: =+ROUND(E90*F90,2) -> 6155.34
B91: OE.3.11.1.3 | C91: PINTURA MUROS EXTERIORES C/ LATEX (2 MANOS). C/ IMPRIMANTE | D91: m2 | E91: 195.84 | F91: 19.16 | G91: =+ROUND(E91*F91,2) -> 3752.29
B92: OE.3.13 | C92: OTROS | G92: =+G93 -> 3937000.7
B93: OE.3.13.1 | C93: MODULO DE CONTINGENCIA | G93: =SUM(G94) -> 3937000.7
B94: OE.3.13.1.1 | C94: MODULO TIPO A, B, C | D94: m2 | E94: 1055.85 | F94: 3728.75 | G94: =+ROUND(E94*F94,2) -> 3937000.7
B95: TOTAL | G95: =+G57+G7 -> 6577908.3
G97: 6577908.3
G98: =+G97-G95 -> 0

Sheet Compilado de modificaciones
A1: ITEM | B1: DESCRIPCIÓN | C1: UNIDAD | D1: metrado_programado | E1: valorizacion_programada | F1: metrado_anterior_acumulado | G1: valorizacion_anterior
A2: OE.1 | B2: OBRAS PROVISIONALES, TRABAJOS PRELIMINARES, SEGURIDAD Y SALUD.
A3: OE.1.1 | B3: OBRAS PROVISIONALES Y TRABAJOS PRELIMINARES
A4: OE.1.1.1 | B4: CONSTRUCCIONES PROVISIONALES
A5: OE.1.1.1.1 | B5: Oficinas | C5: m² | D5: 1018 | E5: 160202.66 | F5: 1018 | G5: 160202.66 | I5: =F5/D5 -> 1 | J5: =D5-F5 -> 0
A6: OE.1.1.1.2 | B6: Almacenes | C6: m² | D6: 4368.09 | E6: 478043.77 | F6: 4368.09 | G6: 478043.77 | I6: =F6/D6 -> 1 | J6: =D6-F6 -> 0
A7: OE.1.1.1.3 | B7: Casetas de guardianÍa | C7: m² | D7: 92.53 | E7: 13679.63 | F7: 92.53 | G7: 13679.635 | I7: =F7/D7 -> 1 | J7: =D7-F7 -> 0
A8: OE.1.1.1.5 | B8: Vestuarios | C8: m² | D8: 1420 | E8: 185807 | F8: 1420 | G8: 185807 | I8: =F8/D8 -> 1 | J8: =D8-F8 -> 0
A9: OE.1.1.1.6 | B9: Servicios higienicos | C9: m² | D9: 134 | E9: 37789.34 | F9: 114 | G9: 32149.14 | I9: =F9/D9 -> 0.85074627 | J9: =D9-F9 -> 20
A10: OE.1.1.1.7 | B10: Cercos Provisional de calamina | C10: m | D10: 1432.18 | E10: 76464.09 | F10: 1364.58 | G10: 72854.926 | I10: =F10/D10 -> 0.95279923 | J10: =D10-F10 -> 67.6
A11: OE.1.1.1.8 | B11: Cartel de identificación de Obra de 4.80m x 3.60 m | C11: und | D11: 2 | E11: 5034.3 | F11: 2 | G11: 5034.3 | I11: =F11/D11 -> 1 | J11: =D11-F11 -> 0
A12: OE.1.1.1.9 | B12: Suministro e instalacion de equipo para transporte vertical de materiales | C12: gbl | D12: 1 | E12: 29501.97 | F12: 0 | G12: 0 | I12: =F12/D12 -> 0 | J12: =D12-F12 -> 1
A13: OE.1.1.1.10 | B13: Traslado de material en desuso de Belempampa a Coripata y Antonio Lorena (D=750m) | C13: kg | D13: 110000 | E13: 14300 | F13: 110000 | G13: 14300 | I13: =F13/D13 -> 1 | J13: =D13-F13 -> 0
A14: OE.1.1.1.11 | B14: Traslado de materiales de Belempampa a almacén Huancaro (D=1800m) | C14: kg | D14: 2026138.6 | E14: 607841.59 | F14: 2026138.6 | G14: 607841.59 | I14: =F14/D14 -> 1 | J14: =D14-F14 -> 0
A15: OE.1.1.1.12 | B15: Desmontaje y traslado de módulos prefabricados | C15: und | D15: 7 | E15: 12067.09 | F15: 7 | G15: 12067.09 | I15: =F15/D15 -> 1 | J15: =D15-F15 -> 0
A16: OE.1.1.1.13 | B16: Reubicación manual de material en obra D=300 m-Kilogramos | C16: kg | D16: 1845384.9 | E16: 1365584.9 | F16: 1845384.9 | G16: 1365584.9 | I16: =F16/D16 -> 1 | J16: =D16-F16 -> 0
... A21: OE.1.1.1.18 | B21: Orden y limpieza permanente en obra | C21: mes | D21: 24 | E21: 322135.2 | F21: 18 | G21: 241601.4 | I21: =F21/D21 -> 0.75 | J21: =D21-F21 -> 6
A22: OE.1.1.1.19 | B22: Desmontaje de oficinas y almacenes | C22: m² | D22: 4463.15 | E22: 244312.83 | F22: 4365.65 | G22: 238975.68 | I22: =F22/D22 -> 0.97815444 | J22: =D22-F22 -> 97.5 | L22: 455.5
A23: OE.1.1.1.20 | B23: Almacén de estructura metálica | C23: m² | D23: 890 | E23: 432548.9 | F23: 890 | G23: 432548.9 | I23: =F23/D23 -> 1 | J23: =D23-F23 -> 0
A24: OE.1.1.1.21 | B24: Embalado de materiales de almacén para traslado | C24: kg | D24: 455934.64 | E24: 155017.78 | F24: 420197.83 | G24: 142867.26 | I24: =F24/D24 -> 0.92161857 | J24: =D24-F24 -> 35736.81
A25: OE.1.1.1.22 | B25: Habilitación y nivelación de accesos para maquinaria | C25: m² | D25: 6207.53 | E25: 262888.9 | F25: 5886.88 | G25: 249309.37 | I25: =F25/D25 -> 0.94834499 | J25: =D25-F25 -> 320.65
A26: OE.1.1.1.23 | B26: Habilitación de escantillón y soportes para malla de acero | C26: kg | D26: 17372.49 | E26: 72269.56 | F26: 16852.09 | G26: 70104.694 | I26: =F26/D26 -> 0.97004459 | J26: =D26-F26 -> 520.4
A27: OE.1.1.1.24 | B27: Vaciado de falso piso en ambientes provisionales (almacén, vestuarios, ss.hh y otros) | C27: m² | D27: 627.48 | E27: 30846.92 | F27: 476.48 | G27: 23423.757 | I27: =F27/D27 -> 0.75935488 | J27: =D27-F27 -> 151
A28: OE.1.1.1.25 | B28: Habilitación y colocación de mobiliario de 1.20x0.8m | C28: und | D28: 202 | E28: 77374.08 | F28: 192 | G28: 73543.68 | I28: =F28/D28 -> 0.95049505 | J28: =D28-F28 -> 10
A29: OE.1.1.1.26 | B29: Mantenimiento de andamios y estructuras metálicas | C29: und | D29: 130 | E29: 31584.8 | F29: 88 | G29: 21380.48 | I29: =F29/D29 -> 0.67692308 | J29: =D29-F29 -> 42
A30: OE.1.1.1.27 | B30: PUERTAS PROVISIONALES | E30: 9234.81 | G30: 9234.8137 | J30: =D30-F30 -> 0
A31: OE.1.1.1.27.1 | B31: Instalación de puerta provisional metálica | C31: m² | D31: 55.99 | E31: 4626.45 | F31: 55.99 | G31: 4626.4537 | I31: =F31/D31 -> 1 | J31: =D31-F31 -> 0
A32: OE.1.1.1.27.2 | B32: Instalación de puerta provisional de madera para almacén Huancaro | C32: m² | D32: 102 | E32: 4608.36 | F32: 102 | G32: 4608.36 | I32: =F32/D32 -> 1 | J32: =D32-F32 -> 0
A33: OE.1.1.1.28 | B33: HABILITACION DE MOVILIARIOS PARA OBRA | E33: 112270.86 | G33: 110350.41 | J33: =D33-F33 -> 0
A34: OE.1.1.1.28.1 | B34: Habilitación de mobiliario estante L=1.20m x 1.80m | C34: und | D34: 150 | E34: 41152.5 | F34: 143 | G34: 39232.05 | I34: =F34/D34 -> 0.95333333 | J34: =D34-F34 -> 7
A35: OE.1.1.1.28.2 | B35: Habilitación de pizarra acrílica para obra de 1.20m x 2.40m | C35: und | D35: 43 | E35: 14040.36 | F35: 43 | G35: 14040.36 | I35: =F35/D35 -> 1 | J35: =D35-F35 -> 0
A36: OE.1.1.1.28.3 | B36: Habilitado de estantes para almacén de 2.50m x 0.90m con rollizo | C36: m | D36: 126 | E36: 57078 | F36: 126 | G36: 57078 | I36: =F36/D36 -> 1 | J36: =D36-F36 -> 0
A37: OE.1.1.1.29 | B37: CONSTRUCCIONES METALICAS | E37: 198552.98 | G37: 198552.98 | J37: =D37-F37 -> 0
A38: OE.1.1.1.29.1 | B38: Habilitado y colocado de escalera metálica provisional | C38: kg | D38: 15601.45 | E38: 124343.56 | F38: 15601.45 | G38: 124343.56 | I38: =F38/D38 -> 1 | J38: =D38-F38 -> 0
A39: OE.1.1.1.29.2 | B39: Vestuario de estructura metálica | C39: m² | D39: 100 | E39: 10955 | F39: 100 | G39: 10955 | I39: =F39/D39 -> 1 | J39: =D39-F39 -> 0
A40: OE.1.1.1.29.3 | B40: Habilitado y colocado de puente metálico | C40: kg | D40: 7320.18 | E40: 52412.49 | F40: 7320.18 | G40: 52412.489 | I40: =F40/D40 -> 1 | J40: =D40-F40 -> 0
A41: OE.1.1.1.29.4 | B41: Habilitado de soporte de cámaras de vigilancia móvil | C41: und | D41: 20 | E41: 4026.4 | F41: 20 | G41: 4026.4 | I41: =F41/D41 -> 1 | J41: =D41-F41 -> 0
A42: OE.1.1.1.29.5 | B42: Habilitación de escuadra metálica para soporte en voladizo | C42: kg | D42: 557.28 | E42: 6815.53 | F42: 557.28 | G42: 6815.5344 | I42: =F42/D42 -> 1 | J42: =D42-F42 -> 0
A43: OE.1.1.1.30 | B43: CONSTRUCCIONES PROVISIONALES EN OBRA | E43: 13538.42 | G43: 13402.579 | J43: =D43-F43 -> 0
A44: OE.1.1.1.30.1 | B44: Habilitacion e instalacion de esquineros protectores tipo L | C44: und | D44: 440 | E44: 9961.6 | F44: 434 | G44: 9825.76 | I44: =F44/D44 -> 0.98636364 | J44: =D44-F44 -> 6
A45: OE.1.1.1.30.2 | B45: Cobertura de protección provisional en azotea | C45: m² | D45: 74.97 | E45: 3576.82 | F45: 74.97 | G45: 3576.8187 | I45: =F45/D45 -> 1 | J45: =D45-F45 -> 0
A46: OE.1.1.2 | B46: INSTALACIONES PROVISIONALES | E46: 447312.18 | G46: 393811.94 | J46: =D46-F46 -> 0
A47: OE.1.1.2.1 | B47: AGUA PARA LA CONSTRUCCIÓN | E47: 125885.51 | G47: 96214.13 | J47: =D47-F47 -> 0
A48: OE.1.1.2.1.1 | B48: Almacenamiento y distribución | C48: gbl | D48: 1 | E48: 7199.99 | F48: 1 | G48: 7199.99 | I48: =F48/D48 -> 1 | J48: =D48-F48 -> 0
A49: OE.1.1.2.1.2 | B49: Restauración y mantenimiento de instalaciones sanitarias provisionales | C49: mes | D49: 24 | E49: 118685.52 | F49: 18 | G49: 89014.14 | I49: =F49/D49 -> 0.75 | J49: =D49-F49 -> 6
A50: OE.1.1.2.2 | B50: DESAGÜE PARA LA CONSTRUCCIÓN | E50: 7199.99 | G50: 7199.99 | J50: =D50-F50 -> 0
A51: OE.1.1.2.2.1 | B51: Desagüe para la construcción | C51: glb | D51: 1 | E51: 7199.99 | F51: 1 | G51: 7199.99 | I51: =F51/D51 -> 1 | J51: =D51-F51 -> 0
A52: OE.1.1.2.3 | B52: ENERGÍA ELÉCTRICA PROVISIONAL | E52: 312172.68 | G52: 288343.82 | J52: =D52-F52 -> 0
A53: OE.1.1.2.3.3 | B53: Servicio extraordinario de energia electrica | C53: mes | D53: 24 | E53: 108902.4 | F53: 23 | G53: 104364.8 | I53: =F53/D53 -> 0.95833333 | J53: =D53-F53 -> 1
A54: OE.1.1.2.3.4 | B54: Desmontaje y reubicación de instalaciones eléctricas provisionales | C54: mes | D54: 24 | E54: 77165.04 | F54: 18 | G54: 57873.78 | I54: =F54/D54 -> 0.75 | J54: =D54-F54 -> 6
A55: OE.1.1.2.3.5 | B55: Suministro de artefactos de iluminación nocturna en obra | C55: glb | D55: 1 | E55: 17525.24 | F55: 1 | G55: 17525.24 | I55: =F55/D55 -> 1 | J55: =D55-F55 -> 0
A56: OE.1.1.2.3.6 | B56: Adquisición de tablero de control general | C56: glb | D56: 1 | E56: 6660 | F56: 1 | G56: 6660 | I56: =F56/D56 -> 1 | J56: =D56-F56 -> 0
A57: OE.1.1.2.3.7 | B57: Adquisición de tableros de distribución | C57: glb | D57: 1 | E57: 25520 | F57: 1 | G57: 25520 | I57: =F57/D57 -> 1 | J57: =D57-F57 -> 0
A58: OE.1.1.2.3.8 | B58: Adquisición de reflectores | C58: glb | D58: 1 | E58: 33600 | F58: 1 | G58: 33600 | I58: =F58/D58 -> 1 | J58: =D58-F58 -> 0
A59: OE.1.1.2.3.9 | B59: Adquisición de accesorios | C59: glb | D59: 1 | E59: 29000 | F59: 1 | G59: 29000 | I59: =F59/D59 -> 1 | J59: =D59-F59 -> 0
A60: OE.1.1.2.3.10 | B60: Adquisición de cables | C60: glb | D60: 1 | E60: 13800 | F60: 1 | G60: 13800 | I60: =F60/D60 -> 1 | J60: =D60-F60 -> 0
A61: OE.1.1.2.4 | B61: INSTALACIÓN TELEFÓNICA Y COMUNICACIÓN PROVISIONAL | E61: 2054 | G61: 2054 | J61: =D61-F61 -> 0
A62: OE.1.1.2.4.1 | B62: Conexion e Instalación | C62: glb | D62: 1 | E62: 520 | F62: 1 | G62: 520 | I62: =F62/D62 -> 1 | J62: =D62-F62 -> 0
A63: OE.1.1.2.4.2 | B63: Consumo y mantenimiento | C63: glb | D63: 1 | E63: 1534 | F63: 1 | G63: 1534 | I63: =F63/D63 -> 1 | J63: =D63-F63 -> 0
A64: OE.1.1.3 | B64: TRABAJOS PRELIMINARES | E64: 5115480.5 | G64: 4591190.7 | J64: =D64-F64 -> 0
A65: OE.1.1.3.2 | B65: TRABAJOS DE REUBICACION CON MAQUINARIA | E65: 1290847.8 | G65: 887717.47 | J65: =D65-F65 -> 0
A66: OE.1.1.3.2.1 | B66: Reubicación de material en obra con retroexcavadora D=100 m | C66: m³ | D66: 11582 | E66: 625891.28 | F66: 10988.38 | G66: 593812.06 | I66: =F66/D66 -> 0.94874633 | J66: =D66-F66 -> 593.62
A67: OE.1.1.3.2.2 | B67: Reubicación de material en obra con maquinaria D=100 m | C67: kg | D67: 81250 | E67: 11375 | F67: 62000 | G67: 8680 | I67: =F67/D67 -> 0.76307692 | J67: =D67-F67 -> 19250
A68: OE.1.1.3.2.3 | B68: Traslado de materiales con camioneta de almacén Huancaro a Belempampa (D=1800m) | C68: vje | D68: 2086 | E68: 231420.84 | F68: 1436 | G68: 159309.84 | I68: =F68/D68 -> 0.68839885 | J68: =D68-F68 -> 650
A69: OE.1.1.3.2.4 | B69: Traslado de material en desuso de almacén Huancaro a IPD (D=3.4 KM) | C69: vje | D69: 35 | E69: 34516.3 | F69: 35 | G69: 34516.3 | I69: =F69/D69 -> 1 | J69: =D69-F69 -> 0
A70: OE.1.1.3.2.5 | B70: Reubicación de material en obra con minicargador frontal D=100 m | C70: m³ | D70: 3132 | E70: 232707.6 | F70: 575.59 | G70: 42766.337 | I70: =F70/D70 -> 0.18377714 | J70: =D70-F70 -> 2556.41
A71: OE.1.1.3.2.6 | B71: Traslado de material de relleno con camión volquete de 3 m3 de almacén Huancaro a Belempampa (D=1800m) | C71: viaj | D71: 1080 | E71: 154936.8 | F71: 339 | G71: 48632.94 | I71: =F71/D71 -> 0.31388889 | J71: =D71-F71 -> 741
A72: OE.1.1.3.3 | B72: TRABAJOS DE REUBICACION DE MATERIALES | E72: 3610016.2 | G72: 3551957.9 | J72: =D72-F72 -> 0
A73: OE.1.1.3.3.1 | B73: Acarreo de materiales manual en obra D>150 m | C73: tn | D73: 18606.73 | E73: 2757889.5 | F73: 18632.34 | G73: 2761685.4 | I73: =F73/D73 -> 1.0013764 | J73: =D73-F73 -> -25.61
A74: OE.1.1.3.3.2 | B74: Traslado vertical con winche de material en obra h=16m - Kilogramos | C74: kg | D74: 1068540 | E74: 117539.4 | F74: 993299.3 | G74: 109262.92 | I74: =F74/D74 -> 0.92958551 | J74: =D74-F74 -> 75240.7
A75: OE.1.1.3.3.3 | B75: Traslado vertical con winche de material en obra h=16m - metros cúbicos | C75: m³ | D75: 1364 | E75: 65390.16 | F75: 1367 | G75: 65533.98 | I75: =F75/D75 -> 1.0021994 | J75: =D75-F75 -> -3
A76: OE.1.1.3.3.4 | B76: Traslado vertical manual de material en obra h=16 m | C76: kg | D76: 3345985.6 | E76: 669197.12 | F76: 3077377.8 | G76: 615475.57 | I76: =F76/D76 -> 0.91972237 | J76: =D76-F76 -> 268607.79
A77: OE.1.1.3.4 | B77: TRABAJOS COMPLEMENTARIOS | E77: 214616.44 | G77: 151515.36 | J77: =D77-F77 -> 0
A78: OE.1.1.3.4.1 | B78: Rotura manual de piedra para reducción de diámetro (12" a <8") para empedrado | C78: m³ | D78: 686.86 | E78: 76351.36 | F78: 370.5 | G78: 41184.78 | I78: =F78/D78 -> 0.53941123 | J78: =D78-F78 -> 316.36
A79: OE.1.1.3.4.2 | B79: Armado y desarmado de andamios | C79: und | D79: 4800 | E79: 102576 | F79: 4554 | G79: 97318.98 | I79: =F79/D79 -> 0.94875 | J79: =D79-F79 -> 246
A80: OE.1.1.3.4.3 | B80: Rehabilitación de construcciones provisionales | C80: m² | D80: 500 | E80: 3675 | F80: 318.4 | G80: 2340.24 | I80: =F80/D80 -> 0.6368 | J80: =D80-F80 -> 181.6
A81: OE.1.1.3.4.4 | B81: Reubicación de materiales de almacén | C81: mes | D81: 12 | E81: 32014.08 | F81: 4 | G81: 10671.36 | I81: =F81/D81 -> 0.33333333 | J81: =D81-F81 -> 8
A82: OE.1.1.4 | B82: ELIMINACIÓN DE OBSTRUCCIONES | E82: 1407.36 | G82: 1407.36 | J82: =D82-F82 -> 0
A83: OE.1.1.4.1 | B83: Tala de Arboles | C83: und | D83: 12 | E83: 212.64 | F83: 12 | G83: 212.64 | I83: =F83/D83 -> 1 | J83: =D83-F83 -> 0
A84: OE.1.1.4.2 | B84: Eliminación de Raices | C84: und | D84: 48 | E84: 1194.72 | F84: 48 | G84: 1194.72 | I84: =F84/D84 -> 1 | J84: =D84-F84 -> 0
A85: OE.1.1.5 | B85: REMOCIONES | E85: 32701.27 | G85: 32701.272 | J85: =D85-F85 -> 0
A86: OE.1.1.5.1 | B86: Remoción de Puertas | C86: und | D86: 152 | E86: 3593.28 | F86: 152 | G86: 3593.28 | I86: =F86/D86 -> 1 | J86: =D86-F86 -> 0
A87: OE.1.1.5.2 | B87: Remoción de Ventanas | C87: und | D87: 162 | E87: 3829.68 | F87: 162 | G87: 3829.68 | I87: =F87/D87 -> 1 | J87: =D87-F87 -> 0
A88: OE.1.1.5.3 | B88: Remoción de Aparatos Sanitarios | C88: und | D88: 38 | E88: 957.98 | F88: 38 | G88: 957.98 | I88: =F88/D88 -> 1 | J88: =D88-F88 -> 0
A89: OE.1.1.5.4 | B89: Remoción de Tijerales de madera | C89: und | D89: 157 | E89: 7422.96 | F89: 157 | G89: 7422.96 | I89: =F89/D89 -> 1 | J89: =D89-F89 -> 0
A90: OE.1.1.5.5 | B90: Remoción de Cobertura | C90: m² | D90: 3269.77 | E90: 15466.01 | F90: 3269.77 | G90: 15466.012 | I90: =F90/D90 -> 1 | J90: =D90-F90 -> 0
A91: OE.1.1.5.6 | B91: Remoción de Estructuras Metálicas | C91: m² | D91: 426 | E91: 1431.36 | F91: 426 | G91: 1431.36 | I91: =F91/D91 -> 1 | J91: =D91-F91 -> 0
A92: OE.1.1.6 | B92: DEMOLICIONES | E92: 1036903.8 | G92: 1030685.3 | J92: =D92-F92 -> 0
A93: OE.1.1.6.1 | B93: Demolicion de muros de ladrillo incluye cimentaciones | C93: m³ | D93: 1017.36 | E93: 20337.03 | F93: 1017.36 | G93: 20337.026 | I93: =F93/D93 -> 1 | J93: =D93-F93 -> 0
A94: OE.1.1.6.2 | B94: Demolicion de muros de adobe incluye cimentaciones | C94: m³ | D94: 202.45 | E94: 12883.91 | F94: 202.45 | G94: 12883.918 | I94: =F94/D94 -> 1 | J94: =D94-F94 -> 0
A95: OE.1.1.6.3 | B95: DEMOLICIONES DE MUROS DE CONTENCION DE PIEDRA INC. CIMENTACIONES | C95: m³ | D95: 780 | E95: 135322.2 | F95: 780 | G95: 135322.2 | I95: =F95/D95 -> 1 | J95: =D95-F95 -> 0
A96: OE.1.1.6.4 | B96: Demolicion de Pisos y falso pisos - Manual | C96: m² | D96: 1724.2 | E96: 28914.83 | F96: 1724.2 | G96: 28914.834 | I96: =F96/D96 -> 1 | J96: =D96-F96 -> 0
A97: OE.1.1.6.5 | B97: Eliminación de Demoliciones | C97: m³ | D97: 3776.24 | E97: 358402.94 | F97: 3710.72 | G97: 352184.44 | I97: =F97/D97 -> 0.98264941 | J97: =D97-F97 -> 65.52
A98: OE.1.1.6.6 | B98: Demolición de muros de contención de concreto soterrado | C98: m³ | D98: 538.29 | E98: 192761.65 | F98: 538.29 | G98: 192761.65 | I98: =F98/D98 -> 1 | J98: =D98-F98 -> 0
A99: OE.1.1.6.7 | B99: Demolición manual | C99: m³ | D99: 268.49 | E99: 209255.74 | F99: 268.49 | G99: 209255.74 | I99: =F99/D99 -> 1 | J99: =D99-F99 -> 0
A100: OE.1.1.6.8 | B100: Demolición de estructuras de concreto armado (losas, vigas, columnas) | C100: m³ | D100: 183.73 | E100: 65793.71 | F100: 183.73 | G100: 65793.713 | I100: =F100/D100 -> 1 | J100: =D100-F100 -> 0
A101: OE.1.1.6.9 | B101: Demolición de estructuras de concreto armado existente | C101: m³ | D101: 36.95 | E101: 13231.8 | F101: 36.95 | G101: 13231.795 | I101: =F101/D101 -> 1 | J101: =D101-F101 -> 0
A102: OE.1.1.7 | B102: MOVILIZACIÓN DE CAMPAMENTO, MAQUINARIA Y HERRAMIENTAS | E102: 2400 | G102: 2400 | J102: =D102-F102 -> 0
A103: OE.1.1.7.2 | B103: Movilización y desmovilización de equipos | C103: glb | D103: 1 | E103: 2400 | F103: 1 | G103: 2400 | I103: =F103/D103 -> 1 | J103: =D103-F103 -> 0
A104: OE.1.1.8 | B104: APUNTALAMIENTOS DE CONSTRUCCIONES EXISTENTES | E104: 53.06 | G104: 53.06 | J104: =D104-F104 -> 0
...

Sheet Var. MO-2
B1: |
B5: UNIDAD EJECUTORA | C5: : GERENCIA REGIONAL DE GESTION DE INVERSIONES DE INFRAESTRUCTURA - GOBIERNO REGIONAL CUSCO (SEDE CENTRAL)
B6: OBRA | C6: : MEJORAMIENTO Y AMPLIACION DE LOS SERVICIOS DE SALUD DEL ESTABLECIMIENTO DE SALUD DE BELEMPAMPA - DISTRITO DE SANTIAGO - PROVINCIA DE CUSCO - REGION CUSCO
B7: META | C7: : 0119-2025
B9: VARIACION DE MANO DE OBRA N°5
B11: Item | C11: DESCRIPCION | D11: Und | E11: Metrado Expediente | F11: PN1 | G11: MM1 | H11: DD1 | I11: Metrado Actual | J11: P.U. Expediente | K11: Parcial Expediente | L11: P.U. Actualizado | M11: Parcial Actualizado | N11: Diferencia P.U. | O11: Diferencia Parcial | R11: PN1 | S11: MM1 | T11: DD1
A12: x | C12: COMPONENTE 01: SUFICIENTE Y ADECUADA INFRAESTRUCTURA Y MANTENIMIENTO PARA LA PRESTACIÓN DE SERVICIOS DE SALUD | K12: =+K13+K23+K104+K197+K345+K524+K568 -> 4419206.6 | M12: =+M13+M23+M104+M197+M345+M524+M568 -> 4471604.4 | O12: =+O13+O23+O104+O197+O345+O524+O568 -> 52397.73 | R12: =+R13+R23+R104+R197+R345+R524+R568 -> 0 | S12: =+S13+S23+S104+S197+S345+S524+S568 -> 0 | T12: =+T13+T23+T104+T197+T345+T524+T568 -> 0
A13: X | B13: OE.1 | C13: OBRAS PROVISIONALES, TRABAJOS PRELIMINARES, SEGURIDAD Y SALUD. | K13: =+K14 -> 30972.9 | M13: =+M14 -> 31424.51 | O13: =+O14 -> 451.61
B14: OE.1.1 | C14: OBRAS PROVISIONALES Y TRABAJOS PRELIMINARES | K14: =+K15+K21 -> 30972.9 | M14: =+M15+M21 -> 31424.51 | O14: =+O15+O21 -> 451.61 | P14: =+MAX(N14:N572) -> 238.9
B15: OE.1.1.3 | C15: TRABAJOS PRELIMINARES | K15: =SUM(K16:K20)/2 -> 30356.89 | M15: =SUM(M16:M20)/2 -> 30805.35 | O15: =SUM(O16:O20)/2 -> 448.46
B16: OE.1.1.3.1 | C16: LIMPIEZA DE TERRENO | K16: =SUM(K17:K20) -> 30356.89 | M16: =SUM(M17:M20) -> 30805.35 | O16: =SUM(O17:O20) -> 448.46
B17: OE.1.1.3.1.2 | C17: Traslado de material en desuso d=100 m | D17: m3 | F17: 44 | I17: =SUM(E17:H17) -> 44 | J17: 40.45 | K17: =+ROUND(+IF(I17="",0,I17*J17),2) -> 1779.8 | L17: 42.1 | M17: =+ROUND(+IF(I17="",0,I17*L17),2) -> 1852.4 | N17: =+L17-J17 -> 1.65 | O17: =+M17-K17 -> 72.6
B18: OE.1.1.3.1.3 | C18: Limpieza de terreno | D18: m2 | F18: 23 | I18: =SUM(E18:H18) -> 23 | J18: 2.61 | K18: =+ROUND(+IF(I18="",0,I18*J18),2) -> 60.03 | L18: 2.75 | M18: =+ROUND(+IF(I18="",0,I18*L18),2) -> 63.25 | N18: =+L18-J18 -> 0.14 | O18: =+M18-K18 -> 3.22
B19: OE.1.1.3.1.4 | C19: Acarreo manual de material de desmonte | D19: m3 | F19: 54 | I19: =SUM(E19:H19) -> 54 | J19: 25.21 | K19: =+ROUND(+IF(I19="",0,I19*J19),2) -> 1361.34 | L19: 26.17 | M19: =+ROUND(+IF(I19="",0,I19*L19),2) -> 1413.18 | N19: =+L19-J19 -> 0.96 | O19: =+M19-K19 -> 51.84
B20: OE.1.1.3.1.5 | C20: Eliminacion de desmonte con maquinaria | D20: m3 | F20: 802 | I20: =SUM(E20:H20) -> 802 | J20: 33.86 | K20: =+ROUND(+IF(I20="",0,I20*J20),2) -> 27155.72 | L20: 34.26 | M20: =+ROUND(+IF(I20="",0,I20*L20),2) -> 27476.52 | N20: =+L20-J20 -> 0.4 | O20: =+M20-K20 -> 320.8
B21: OE.1.1.9 | C21: TRAZOS, NIVELES Y REPLANTEO | K21: =SUM(K22) -> 616.01 | M21: =SUM(M22) -> 619.16 | O21: =SUM(O22) -> 3.15
B22: OE.1.1.9.2 | C22: Trazo y Replanteo durante el proceso | D22: m2 | E22: 157.95 | I22: =SUM(E22:H22) -> 157.95 | J22: 3.9 | K22: =+ROUND(+IF(I22="",0,I22*J22),2) -> 616.01 | L22: 3.92 | M22: =+ROUND(+IF(I22="",0,I22*L22),2) -> 619.16 | N22: =+L22-J22 -> 0.02 | O22: =+M22-K22 -> 3.15
A23: X | B23: OE.2 | C23: ESTRUCTURAS. | K23: =+K24+K37+K43+K60+K91 -> 1590221.6 | M23: =+M24+M37+M43+M60+M91 -> 1607750.8 | O23: =+O24+O37+O43+O60+O91 -> 17529.17
B24: OE.2.1 | C24: MOVIMIENTO DE TIERRAS | K24: =+K25+K27+K30+K33+K35 -> 84163.16 | M24: =+M25+M27+M30+M33+M35 -> 84339.37 | O24: =+O25+O27+O30+O33+O35 -> 176.21
B25: OE.2.1.1 | C25: EXCAVACIONES MASIVA | K25: =SUM(K26) -> 5535.71 | M25: =SUM(M26) -> 5594.6 | O25: =SUM(O26) -> 58.89
B26: OE.2.1.1.1 | C26: Excavacion con maquinaria | D26: m3 | E26: 1177.81 | I26: =SUM(E26:H26) -> 1177.81 | J26: 4.7 | K26: =+ROUND(+IF(I26="",0,I26*J26),2) -> 5535.71 | L26: 4.75 | M26: =+ROUND(+IF(I26="",0,I26*L26),2) -> 5594.6 | N26: =+L26-J26 -> 0.05 | O26: =+M26-K26 -> 58.89
B27: OE.2.1.2 | C27: EXCAVACIONES | K27: =SUM(K28:K29)/2 -> 1877.45 | M27: =SUM(M28:M29)/2 -> 1948.94 | O27: =SUM(O28:O29)/2 -> 71.49
B28: OE.2.1.2.1 | C28: EXCAVACIONES SIMPLES | K28: =SUM(K29) -> 1877.45 | M28: =SUM(M29) -> 1948.94 | O28: =SUM(O29) -> 71.49
B29: OE.2.1.2.1.1 | C29: Excavacion manual de zanjas para Zapatas | D29: m3 | E29: 44.68 | I29: =SUM(E29:H29) -> 44.68 | J29: 42.02 | K29: =+ROUND(+IF(I29="",0,I29*J29),2) -> 1877.45 | L29: 43.62 | M29: =+ROUND(+IF(I29="",0,I29*L29),2) -> 1948.94 | N29: =+L29-J29 -> 1.6 | O29: =+M29-K29 -> 71.49
B30: OE.2.1.4 | C30: RELLENOS | K30: =SUM(K31:K32) -> 2989.14 | M30: =SUM(M31:M32) -> 2990.92 | O30: =SUM(O31:O32) -> 1.78
B31: OE.2.1.4.1 | C31: Relleno compactado con material de prestamo | D31: m3 | E31: 7 | I31: =SUM(E31:H31) -> 7 | J31: 65.58 | K31: =+ROUND(+IF(I31="",0,I31*J31),2) -> 459.06 | L31: 65.58 | M31: =+ROUND(+IF(I31="",0,I31*L31),2) -> 459.06 | N31: =+L31-J31 -> 0 | O31: =+M31-K31 -> 0
B32: OE.2.1.4.2 | C32: Relleno compactado c/equipo con material de afirmado e=0.15m | D32: m2 | E32: 178.3 | I32: =SUM(E32:H32) -> 178.3 | J32: 14.19 | K32: =+ROUND(+IF(I32="",0,I32*J32),2) -> 2530.08 | L32: 14.2 | M32: =+ROUND(+IF(I32="",0,I32*L32),2) -> 2531.86 | N32: =+L32-J32 -> 0.01 | O32: =+M32-K32 -> 1.78
B33: OE.2.1.5. | C33: NIVELACION INTERIOR Y APISONADO | K33: =SUM(K34) -> 299.88 | M33: =SUM(M34) -> 310.74 | O33: =SUM(O34) -> 10.86
B34: OE.2.1.5.1 | C34: Nivelacion interior y apisonado para f.piso,patio y veredas | D34: m2 | E34: 68 | I34: =SUM(E34:H34) -> 68 | J34: 4.41 | K34: =+ROUND(+IF(I34="",0,I34*J34),2) -> 299.88 | L34: 4.56968 | M34: =+ROUND(+IF(I34="",0,I34*L34),2) -> 310.74 | N34: =+L34-J34 -> 0.15968 | O34: =+M34-K34 -> 10.86
B35: OE.2.1.6 | C35: ELIMINACION DE MATERIAL EXCEDENTE | K35: =SUM(K36) -> 73460.98 | M35: =SUM(M36) -> 73494.17 | O35: =SUM(O36) -> 33.19
B36: OE.2.1.6.2 | C36: Eliminacion de material excedente con maquinaria | D36: m3 | E36: 1659.76 | I36: =SUM(E36:H36) -> 1659.76 | J36: 44.26 | K36: =+ROUND(+IF(I36="",0,I36*J36),2) -> 73460.98 | L36: 44.28 | M36: =+ROUND(+IF(I36="",0,I36*L36),2) -> 73494.17 | N36: =+L36-J36 -> 0.02 | O36: =+M36-K36 -> 33.19
B37: OE.2.2 | C37: OBRAS DE CONCRETO SIMPLE | K37: =+K38+K40 -> 12830.19 | M37: =+M38+M40 -> 13003.48 | O37: =+O38+O40 -> 173.29
B38: OE.2.2.3 | C38: SOLADOS | K38: =SUM(K39) -> 5048.26 | M38: =SUM(M39) -> 5127.14 | O38: =SUM(O39) -> 78.88
B39: OE.2.2.3.1 | C39: Solado para zapata e=0.10m, f'c=100kg/cm2 | D39: m2 | E39: 117.73 | I39: =SUM(E39:H39) -> 117.73 | J39: 42.88 | K39: =+ROUND(+IF(I39="",0,I39*J39),2) -> 5048.26 | L39: 43.55 | M39: =+ROUND(+IF(I39="",0,I39*L39),2) -> 5127.14 | N39: =+L39-J39 -> 0.67 | O39: =+M39-K39 -> 78.88
B40: OE.2.2.4 | C40: DADOS DE ANCLAJE | K40: =SUM(K41:K42) -> 7781.93 | M40: =SUM(M41:M42) -> 7876.34 | O40: =SUM(O41:O42) -> 94.41
B41: OE.2.2.4.1 | C41: Dado de anclaje f'c= 210 kg/cm2 | D41: und | F41: 64 | I41: =SUM(E41:H41) -> 64 | J41: 72.23 | K41: =+ROUND(+IF(I41="",0,I41*J41),2) -> 4622.72 | L41: 73.4 | M41: =+ROUND(+IF(I41="",0,I41*L41),2) -> 4697.6 | N41: =+L41-J41 -> 1.17 | O41: =+M41-K41 -> 74.88
B42: OE.2.2.4.2 | C42: Acero en dado de anclaje para cimientos de columna | D42: kg | F42: 93 | I42: =SUM(E42:H42) -> 93 | J42: 33.97 | K42: =+ROUND(+IF(I42="",0,I42*J42),2) -> 3159.21 | L42: 34.18 | M42: =+ROUND(+IF(I42="",0,I42*L42),2) -> 3178.74 | N42: =+L42-J42 -> 0.21 | O42: =+M42-K42 -> 19.53
B43: OE.2.3 | C43: OBRAS DE CONCRETO ARMADO | K43: =+K44+K49+K53+K57 -> 108194.24 | M43: =+M44+M49+M53+M57 -> 109731.15 | O43: =+O44+O49+O53+O57 -> 1536.91
B44: OE.2.3.9 | C44: LOSAS | K44: =SUM(K45:K48)/2 -> 38462.36 | M44: =SUM(M45:M48)/2 -> 38731.88 | O44: =SUM(O45:O48)/2 -> 269.52
B45: OE.2.3.9.8 | C45: LOSAS DE CONCRETO | K45: =SUM(K46:K48) -> 38462.36 | M45: =SUM(M46:M48) -> 38731.88 | O45: =SUM(O46:O48) -> 269.52
B46: OE.2.3.9.8.1 | C46: Concreto f'c=210 kg/cm2 en losa | D46: m3 | F46: 72.95 | I46: =SUM(E46:H46) -> 72.95 | J46: 466.32 | K46: =+ROUND(+IF(I46="",0,I46*J46),2) -> 34018.04 | L46: 469.28 | M46: =+ROUND(+IF(I46="",0,I46*L46),2) -> 34233.98 | N46: =+L46-J46 -> 2.96 | O46: =+M46-K46 -> 215.94
B47: OE.2.3.9.8.2 | C47: Encofrado y desencofrado en losa de concreto | D47: m2 | F47: 8.09 | I47: =SUM(E47:H47) -> 8.09 | J47: 65.1 | K47: =+ROUND(+IF(I47="",0,I47*J47),2) -> 526.66 | L47: 66.43 | M47: =+ROUND(+IF(I47="",0,I47*L47),2) -> 537.42 | N47: =+L47-J47 -> 1.33 | O47: =+M47-K47 -> 10.76
B48: OE.2.3.9.8.3 | C48: Acero f'y=4200 kg/cm2 en losa de concreto | D48: kg | F48: 535.2 | I48: =SUM(E48:H48) -> 535.2 | J48: 7.32 | K48: =+ROUND(+IF(I48="",0,I48*J48),2) -> 3917.66 | L48: 7.4 | M48: =+ROUND(+IF(I48="",0,I48*L48),2) -> 3960.48 | N48: =+L48-J48 -> 0.08 | O48: =+M48-K48 -> 42.82
B49: OE.2.3.12 | C49: CISTERNA | K49: =SUM(K50:K52) -> 11598.05 | M49: =SUM(M50:M52) -> 11774.49 | O49: =SUM(O50:O52) -> 176.44
B50: OE.2.3.12.1 | C50: Cisternas -Concreto f´c=280kg/cm2 | D50: m3 | E50: 8.63 | I50: =SUM(E50:H50) -> 8.63 | J50: 661.41 | K50: =+ROUND(+IF(I50="",0,I50*J50),2) -> 5707.97 | L50: 671.64 | M50: =+ROUND(+IF(I50="",0,I50*L50),2) -> 5796.25 | N50: =+L50-J50 -> 10.23 | O50: =+M50-K50 -> 88.28
B51: OE.2.3.12.2 | C51: Cisternas -encofrado y desencofrado | D51: m2 | E51: 11.6 | I51: =SUM(E51:H51) -> 11.6 | J51: 74.31 | K51: =+ROUND(+IF(I51="",0,I51*J51),2) -> 862 | L51: 77.08 | M51: =+ROUND(+IF(I51="",0,I51*L51),2) -> 894.13 | N51: =+L51-J51 -> 2.77 | O51: =+M51-K51 -> 32.13
B52: OE.2.3.12.3 | C52: Cisternas -Acero fy=4200 kg/cm2 | D52: kg | E52: 700.29 | I52: =SUM(E52:H52) -> 700.29 | J52: 7.18 | K52: =+ROUND(+IF(I52="",0,I52*J52),2) -> 5028.08 | L52: 7.26 | M52: =+ROUND(+IF(I52="",0,I52*L52),2) -> 5084.11 | N52: =+L52-J52 -> 0.08 | O52: =+M52-K52 -> 56.03
B53: OE.2.3.13 | C53: SOBRECIMIENTO ARMADO | K53: =SUM(K54:K56) -> 23310.4 | M53: =SUM(M54:M56) -> 23803.77 | O53: =SUM(O54:O56) -> 493.37
B54: OE.2.3.13.1 | C54: Sobrecimiento concreto 1:8+25%PM | D54: m3 | F54: 16.9 | I54: =SUM(E54:H54) -> 16.9 | J54: 328.51 | K54: =+ROUND(+IF(I54="",0,I54*J54),2) -> 5551.82 | L54: 333.86 | M54: =+ROUND(+IF(I54="",0,I54*L54),2) -> 5642.23 | N54: =+L54-J54 -> 5.35 | O54: =+M54-K54 -> 90.41
B55: OE.2.3.13.2 | C55: Encofrado y desencofrado en sobrecimiento | D55: m2 | F55: 242.48 | I55: =SUM(E55:H55) -> 242.48 | J55: 67.61 | K55: =+ROUND(+IF(I55="",0,I55*J55),2) -> 16394.07 | L55: 69.05 | M55: =+ROUND(+IF(I55="",0,I55*L55),2) -> 16743.24 | N55: =+L55-J55 -> 1.44 | O55: =+M55-K55 -> 349.17
B56: OE.2.3.13.3 | C56: Acero f'y=4200 kg/cm2 en sobrecimiento | D56: kg | F56: 489.07 | I56: =SUM(E56:H56) -> 489.07 | J56: 2.79 | K56: =+ROUND(+IF(I56="",0,I56*J56),2) -> 1364.51 | L56: 2.9 | M56: =+ROUND(+IF(I56="",0,I56*L56),2) -> 1418.3 | N56: =+L56-J56 -> 0.11 | O56: =+M56-K56 -> 53.79
B57: OE.2.3.14 | C57: CIMIENTO CORRIDO | K57: =SUM(K58:K59) -> 34823.43 | M57: =SUM(M58:M59) -> 35421.01 | O57: =SUM(O58:O59) -> 597.58
B58: OE.2.3.14.1 | C58: Concreto f'c= 175 kg/cm2 en cimiento | D58: m3 | F58: 39.21 | I58: =SUM(E58:H58) -> 39.21 | J58: 379.99 | K58: =+ROUND(+IF(I58="",0,I58*J58),2) -> 14899.41 | L58: 387.39 | M58: =+ROUND(+IF(I58="",0,I58*L58),2) -> 15189.56 | N58: =+L58-J58 -> 7.4 | O58: =+M58-K58 -> 290.15
B59: OE.2.3.14.2 | C59: Encofrado y desencofrado en cimiento | D59: m2 | F59: 62.36 | I59: =SUM(E59:H59) -> 62.36 | J59: 319.5 | K59: =+ROUND(+IF(I59="",0,I59*J59),2) -> 19924.02 | L59: 324.43 | M59: =+ROUND(+IF(I59="",0,I59*L59),2) -> 20231.45 | N59: =+L59-J59 -> 4.93 | O59: =+M59-K59 -> 307.43
B60: OE.2.4 | C60: ESTRUCTURAS METÁLICAS | K60: =+K61+K65+K70+K89 -> 1134817.5 | M60: =+M61+M65+M70+M89 -> 1148538.9 | O60: =+O61+O65+O70+O89 -> 13721.35
B61: OE.2.4.1 | C61: COLUMNAS METALICAS | K61: =SUM(K62:K64) -> 320358.96 | M61: =SUM(M62:M64) -> 322656.4 | O61: =SUM(O62:O64) -> 2297.44
B62: OE.2.4.1.1.7 | C62: Placa Base Inc. Pernos de anclaje | D62: und | F62: 337 | I62: =SUM(E62:H62) -> 337 | J62: 160.83 | K62: =+ROUND(+IF(I62="",0,I62*J62),2) -> 54199.71 | L62: 161.35 | M62: =+ROUND(+IF(I62="",0,I62*L62),2) -> 54374.95 | N62: =+L62-J62 -> 0.52 | O62: =+M62-K62 -> 175.24
B63: OE.2.4.1.1.8 | C63: Armado Columnas metálicas 3mm (L=6m) | D63: kg | F63: 17685 | I63: =SUM(E63:H63) -> 17685 | J63: 11.46 | K63: =+ROUND(+IF(I63="",0,I63*J63),2) -> 202670.1 | L63: 11.52 | M63: =+ROUND(+IF(I63="",0,I63*L63),2) -> 203731.2 | N63: =+L63-J63 -> 0.06 | O63: =+M63-K63 -> 1061.1
B64: OE.2.4.1.1.9 | C64: Montaje Columnas metálicas 3mm (L=6m) | D64: kg | F64: 17685 | I64: =SUM(E64:H64) -> 17685 | J64: 3.59 | K64: =+ROUND(+IF(I64="",0,I64*J64),2) -> 63489.15 | L64: 3.65 | M64: =+ROUND(+IF(I64="",0,I64*L64),2) -> 64550.25 | N64: =+L64-J64 -> 0.06 | O64: =+M64-K64 -> 1061.1 | P64: X
B65: OE.2.4.2 | C65: VIGAS METALICAS | K65: =SUM(K66:K69)/2 -> 298945.7 | M65: =SUM(M66:M69)/2 -> 305256.37 | O65: =SUM(O66:O69)/2 -> 6310.67
B66: OE.2.4.2.2.2 | C66: PERNOS | K66: =SUM(K67:K69) -> 298945.7 | M66: =SUM(M67:M69) -> 305256.37 | O66: =SUM(O67:O69) -> 6310.67 | Q66: =+O577 -> -1.0186341e-10
B67: OE.2.4.2.2.2.5 | C67: Plancha Metalica Inc.Pernos de sujeción | D67: und | F67: 337 | I67: =SUM(E67:H67) -> 337 | J67: 136.23 | K67: =+ROUND(+IF(I67="",0,I67*J67),2) -> 45909.51 | L67: 137.04 | M67: =+ROUND(+IF(I67="",0,I67*L67),2) -> 46182.48 | N67: =+L67-J67 -> 0.81 | O67: =+M67-K67 -> 272.97
B68: OE.2.4.2.2.2.6 | C68: Armado vigas metálicas 150x100mm e= 3mm | D68: m | F68: 927.45 | I68: =SUM(E68:H68) -> 927.45 | J68: 201.95 | K68: =+ROUND(+IF(I68="",0,I68*J68),2) -> 187298.53 | L68: =207.41-0.04 -> 207.37 | M68: =+ROUND(+IF(I68="",0,I68*L68),2) -> 192325.31 | N68: =+L68-J68 -> 5.42 | O68: =+M68-K68 -> 5026.78 | P68: X
B69: OE.2.4.2.2.2.7 | C69: Montaje vigas metálicas 150x100 mm e=3mm | D69: m | F69: 927.45 | I69: =SUM(E69:H69) -> 927.45 | J69: 70.88 | K69: =+ROUND(+IF(I69="",0,I69*J69),2) -> 65737.66 | L69: 71.97 | M69: =+ROUND(+IF(I69="",0,I69*L69),2) -> 66748.58 | N69: =+L69-J69 -> 1.09 | O69: =+M69-K69 -> 1010.92
B70: OE.2.4.3 | C70: TIJERALES METALICO | K70: =SUM(K71:K88)/2 -> 347321.55 | M70: =SUM(M71:M88)/2 -> 350312.71 | O70: =SUM(O71:O88)/2 -> 2991.16
B71: OE.2.4.3.2 | C71: Armado de Tijeral Metalico | K71: =SUM(K72:K79) -> 285585.65 | M71: =SUM(M72:M79) -> 287056.59 | O71: =SUM(O72:O79) -> 1470.94
B72: OE.2.4.3.2.1 | C72: Armado de Tijeral metalico Tipo 01 L=7.00 m | D72: und | F72: 28 | I72: =SUM(E72:H72) -> 28 | J72: 2166.84 | K72: =+ROUND(+IF(I72="",0,I72*J72),2) -> 60671.52 | L72: 2178.38 | M72: =+ROUND(+IF(I72="",0,I72*L72),2) -> 60994.64 | N72: =+L72-J72 -> 11.54 | O72: =+M72-K72 -> 323.12
B73: OE.2.4.3.2.2 | C73: Armado de Tijeral metalico Tipo 02 L=6.00 m | D73: und | F73: 72 | I73: =SUM(E73:H73) -> 72 | J73: 2101.64 | K73: =+ROUND(+IF(I73="",0,I73*J73),2) -> 151318.08 | L73: 2113.18 | M73: =+ROUND(+IF(I73="",0,I73*L73),2) -> 152148.96 | N73: =+L73-J73 -> 11.54 | O73: =+M73-K73 -> 830.88
B74: OE.2.4.3.2.3 | C74: Armado de Tijeral metalico Tipo 03 L=3.50 m | D74: und | F74: 1 | I74: =SUM(E74:H74) -> 1 | J74: 1309.99 | K74: =+ROUND(+IF(I74="",0,I74*J74),2) -> 1309.99 | L74: 1314.52 | M74: =+ROUND(+IF(I74="",0,I74*L74),2) -> 1314.52 | N74: =+L74-J74 -> 4.53 | O74: =+M74-K74 -> 4.53
B75: OE.2.4.3.2.4 | C75: Armado de Tijeral metalico Tipo 04 L=3.10 m | D75: und | F75: 13 | I75: =SUM(E75:H75) -> 13 | J75: 1280.92 | K75: =+ROUND(+IF(I75="",0,I75*J75),2) -> 16651.96 | L75: 1286.25 | M75: =+ROUND(+IF(I75="",0,I75*L75),2) -> 16721.25 | N75: =+L75-J75 -> 5.33 | O75: =+M75-K75 -> 69.29
B76: OE.2.4.3.2.5 | C76: Armado de Tijeral metalico Tipo 05 L=3.00 m | D76: und | F76: 2 | I76: =SUM(E76:H76) -> 2 | J76: 1316.4 | K76: =+ROUND(+IF(I76="",0,I76*J76),2) -> 2632.8 | L76: 1323.06 | M76: =+ROUND(+IF(I76="",0,I76*L76),2) -> 2646.12 | N76: =+L76-J76 -> 6.66 | O76: =+M76-K76 -> 13.32
B77: OE.2.4.3.2.6 | C77: Armado de Tijeral metalico Tipo 06 L=2.60 m | D77: und | F77: 15 | I77: =SUM(E77:H77) -> 15 | J77: 1238.4 | K77: =+ROUND(+IF(I77="",0,I77*J77),2) -> 18576 | L77: 1245.06 | M77: =+ROUND(+IF(I77="",0,I77*L77),2) -> 18675.9 | N77: =+L77-J77 -> 6.66 | O77: =+M77-K77 -> 99.9
B78: OE.2.4.3.2.7 | C78: Armado de Tijeral metalico Tipo 07 L=1.90 m | D78: und | F78: 15 | I78: =SUM(E78:H78) -> 15 | J78: 1202.92 | K78: =+ROUND(+IF(I78="",0,I78*J78),2) -> 18043.8 | L78: 1208.25 | M78: =+ROUND(+IF(I78="",0,I78*L78),2) -> 18123.75 | N78: =+L78-J78 -> 5.33 | O78: =+M78-K78 -> 79.95
B79: OE.2.4.3.2.8 | C79: Armado de Tijeral metalico Tipo 08 L=1.30 m | D79: und | F79: 15 | I79: =SUM(E79:H79) -> 15 | J79: 1092.1 | K79: =+ROUND(+IF(I79="",0,I79*J79),2) -> 16381.5 | L79: 1095.43 | M79: =+ROUND(+IF(I79="",0,I79*L79),2) -> 16431.45 | N79: =+L79-J79 -> 3.33 | O79: =+M79-K79 -> 49.95
B80: OE.2.4.3.3 | C80: Montaje de Tijeral Metalico | K80: =SUM(K81:K88) -> 61735.9 | M80: =SUM(M81:M88) -> 63256.12 | O80: =SUM(O81:O88) -> 1520.22
B81: OE.2.4.3.3.1 | C81: Montaje de Tijeral metalico Tipo 01 L=7.00 m | D81: und | F81: 28 | I81: =SUM(E81:H81) -> 28 | J81: 473.12 | K81: =+ROUND(+IF(I81="",0,I81*J81),2) -> 13247.36 | L81: 485 | M81: =+ROUND(+IF(I81="",0,I81*L81),2) -> 13580 | N81: =+L81-J81 -> 11.88 | O81: =+M81-K81 -> 332.64
B82: OE.2.4.3.3.2 | C82: Montaje de Tijeral metalico Tipo 02 L=6.00 m | D82: und | F82: 72 | I82: =SUM(E82:H82) -> 72 | J82: 469.92 | K82: =+ROUND(+IF(I82="",0,I82*J82),2) -> 33834.24 | L82: 481.8 | M82: =+ROUND(+IF(I82="",0,I82*L82),2) -> 34689.6 | N82: =+L82-J82 -> 11.88 | O82: =+M82-K82 -> 855.36
B83: OE.2.4.3.3.3 | C83: Montaje de Tijeral metalico Tipo 03 L=3.50 m | D83: und | F83: 2 | I83: =SUM(E83:H83) -> 2 | J83: 292.6 | K83: =+ROUND(+IF(I83="",0,I83*J83),2) -> 585.2 | L83: 299.26 | M83: =+ROUND(+IF(I83="",0,I83*L83),2) -> 598.52 | N83: =+L83-J83 -> 6.66 | O83: =+M83-K83 -> 13.32
B84: OE.2.4.3.3.4 | C84: Montaje de Tijeral metalico Tipo 04 L=3.10 m | D84: und | F84: 13 | I84: =SUM(E84:H84) -> 13 | J84: 326.39 | K84: =+ROUND(+IF(I84="",0,I84*J84),2) -> 4243.07 | L84: 335.31 | M84: =+ROUND(+IF(I84="",0,I84*L84),2) -> 4359.03 | N84: =+L84-J84 -> 8.92 | O84: =+M84-K84 -> 115.96
B85: OE.2.4.3.3.5 | C85: Montaje de Tijeral metalico Tipo 05 L=3.00 m | D85: und | F85: 2 | I85: =SUM(E85:H85) -> 2 | J85: 326.39 | K85: =+ROUND(+IF(I85="",0,I85*J85),2) -> 652.78 | L85: 335.31 | M85: =+ROUND(+IF(I85="",0,I85*L85),2) -> 670.62 | N85: =+L85-J85 -> 8.92 | O85: =+M85-K85 -> 17.84
B86: OE.2.4.3.3.6 | C86: Montaje de Tijeral metalico Tipo 06 L=2.60 m | D86: und | F86: 15 | I86: =SUM(E86:H86) -> 15 | J86: 213.71 | K86: =+ROUND(+IF(I86="",0,I86*J86),2) -> 3205.65 | L86: 218.07 | M86: =+ROUND(+IF(I86="",0,I86*L86),2) -> 3271.05 | N86: =+L86-J86 -> 4.36 | O86: =+M86-K86 -> 65.4
B87: OE.2.4.3.3.7 | C87: Montaje de Tijeral metalico Tipo 07 L=1.90 m | D87: und | F87: 15 | I87: =SUM(E87:H87) -> 15 | J87: 213.71 | K87: =+ROUND(+IF(I87="",0,I87*J87),2) -> 3205.65 | L87: 218.07 | M87: =+ROUND(+IF(I87="",0,I87*L87),2) -> 3271.05 | N87: =+L87-J87 -> 4.36 | O87: =+M87-K87 -> 65.4
B88: OE.2.4.3.3.8 | C88: Montaje de Tijeral metalico Tipo 08 L=1.30 m | D88: und | F88: 15 | I88: =SUM(E88:H88) -> 15 | J88: 184.13 | K88: =+ROUND(+IF(I88="",0,I88*J88),2) -> 2761.95 | L88: 187.75 | M88: =+ROUND(+IF(I88="",0,I88*L88),2) -> 2816.25 | N88: =+L88-J88 -> 3.62 | O88: =+M88-K88 -> 54.3
B89: OE.2.4.4 | C89: CORREAS METALICAS | K89: =SUM(K90) -> 168191.3 | M89: =SUM(M90) -> 170313.38 | O89: =SUM(O90) -> 2122.08
B90: OE.2.4.4.2 | C90: Correas metalicas de 50x50x3mm | D90: m | F90: 3215.28 | I90: =SUM(E90:H90) -> 3215.28 | J90: 52.31 | K90: =+ROUND(+IF(I90="",0,I90*J90),2) -> 168191.3 | L90: 52.97 | M90: =+ROUND(+IF(I90="",0,I90*L90),2) -> 170313.38 | N90: =+L90-J90 -> 0.66 | O90: =+M90-K90 -> 2122.08
B91: OE.2.6 | C91: VARIOS | K91: =+K92+K94+K98+K100+K102 -> 250216.49 | M91: =+M92+M94+M98+M100+M102 -> 252137.9 | O91: =+O92+O94+O98+O100+O102 -> 1921.41
B92: OE.2.6.1 | C92: ARRIOSTRAMIENTO METALICO | K92: =SUM(K93) -> 60421.41 | M92: =SUM(M93) -> 61309.96 | O92: =SUM(O93) -> 888.55
B93: OE.2.6.1.1 | C93: Arriostramiento metalico | D93: kg | E93: 4936.39 | I93: =SUM(E93:H93) -> 4936.39 | J93: 12.24 | K93: =+ROUND(+IF(I93="",0,I93*J93),2) -> 60421.41 | L93: 12.42 | M93: =+ROUND(+IF(I93="",0,I93*L93),2) -> 61309.96 | N93: =+L93-J93 -> 0.18 | O93: =+M93-K93 -> 888.55
B94: OE.2.6.3 | C94: ARRIOSTRES DEL TECHO | K94: =SUM(K95:K97) -> 6542.39 | M94: =SUM(M95:M97) -> 6637.66 | O94: =SUM(O95:O97) -> 95.27
B95: OE.2.6.3.1 | C95: Acero Ø 1/2" LISO | D95: m | E95: 492.2 | I95: =SUM(E95:H95) -> 492.2 | J95: 9.3 | K95: =+ROUND(+IF(I95="",0,I95*J95),2) -> 4577.46 | L95: 9.44 | M95: =+ROUND(+IF(I95="",0,I95*L95),2) -> 4646.37 | N95: =+L95-J95 -> 0.14 | O95: =+M95-K95 -> 68.91
B96: OE.2.6.3.2 | C96: Conexión de tirantes L64x64x7.9 | D96: m | E96: 8.67 | I96: =SUM(E96:H96) -> 8.67 | J96: 53.06 | K96: =+ROUND(+IF(I96="",0,I96*J96),2) -> 460.03 | L96: 53.74 | M96: =+ROUND(+IF(I96="",0,I96*L96),2) -> 465.93 | N96: =+L96-J96 -> 0.68 | O96: =+M96-K96 -> 5.9
B97: OE.2.6.3.3 | C97: Angulo 2.5X2.5X3/16" | D97: m | E97: 30.08 | I97: =SUM(E97:H97) -> 30.08 | J97: 50.03 | K97: =+ROUND(+IF(I97="",0,I97*J97),2) -> 1504.9 | L97: 50.71 | M97: =+ROUND(+IF(I97="",0,I97*L97),2) -> 1525.36 | N97: =+L97-J97 -> 0.68 | O97: =+M97-K97 -> 20.46
B98: OE.2.6.4 | C98: PINTURA DE PROTECCION ANTICORROSIVA | K98: =SUM(K99) -> 95182.77 | M98: =SUM(M99) -> 96039.06 | O98: =SUM(O99) -> 856.29
B99: OE.2.6.4.1 | C99: Pintura a base de resinas epoxi para protección anticorrosión | D99: m2 | E99: 4506.76 | I99: =SUM(E99:H99) -> 4506.76 | J99: 21.12 | K99: =+ROUND(+IF(I99="",0,I99*J99),2) -> 95182.77 | L99: 21.31 | M99: =+ROUND(+IF(I99="",0,I99*L99),2) -> 96039.06 | N99: =+L99-J99 -> 0.19 | O99: =+M99-K99 -> 856.29
B100: OE.2.6.6 | C100: CURADO Y PROTECCION DEL CONCRETO | K100: =SUM(K101) -> 9543.58 | M100: =SUM(M101) -> 9596.75 | O100: =SUM(O101) -> 53.17
B101: OE.2.6.6.2 | C101: Curado y Proteccion de Concreto | D101: m2 | F101: 2658.38 | I101: =SUM(E101:H101) -> 2658.38 | J101: 3.59 | K101: =+ROUND(+IF(I101="",0,I101*J101),2) -> 9543.58 | L101: 3.61 | M101: =+ROUND(+IF(I101="",0,I101*L101),2) -> 9596.75 | N101: =+L101-J101 -> 0.02 | O101: =+M101-K101 -> 53.17
B102: OE.2.6.7 | C102: CERCO METÁLICO | K102: =SUM(K103) -> 78526.34 | M102: =SUM(M103) -> 78554.47 | O102: =SUM(O103) -> 28.13
B103: OE.2.6.7.1 | C103: Cerco perimetrico de rejas metalicas | D103: m | F103: 140.64 | I103: =SUM(E103:H103) -> 140.64 | J103: 558.35 | K103: =+ROUND(+IF(I103="",0,I103*J103),2) -> 78526.34 | L103: 558.55 | M103: =+ROUND(+IF(I103="",0,I103*L103),2) -> 78554.47 | N103: =+L103-J103 -> 0.2 | O103: =+M103-K103 -> 28.13
A104: X | B104: OE.3 | C104: ARQUITECTURA | K104: =+K105+K110+K114+K136+K145+K152+K158+K169+K172+K178+K184 -> 2041336.4 | M104: =+M105+M110+M114+M136+M145+M152+M158+M169+M172+M178+M184 -> 2066485.6 | O104: =+O105+O110+O114+O136+O145+O152+O158+O169+O172+O178+O184 -> 25149.11
B105: OE.3.1 | C105: MUROS Y TABIQUES DE ALBAÑILERIA | K105: =+K106 -> 658610.88 | M105: =+M106 -> 664416.05 | O105: =+O106 -> 5805.17
...

Sheet Var. MO-2 (2)
B1: |
B5: UNIDAD EJECUTORA | C5: : GERENCIA REGIONAL DE GESTION DE INVERSIONES DE INFRAESTRUCTURA - GOBIERNO REGIONAL CUSCO (SEDE CENTRAL)
B6: OBRA | C6: : MEJORAMIENTO Y AMPLIACION DE LOS SERVICIOS DE SALUD DEL ESTABLECIMIENTO DE SALUD DE BELEMPAMPA - DISTRITO DE SANTIAGO - PROVINCIA DE CUSCO - REGION CUSCO
B7: META | C7: : 0119-2025
B9: VARIACION DE MANO DE OBRA N°5
B11: Item | C11: DESCRIPCION | D11: Und | E11: Metrado Expediente | F11: PN1 | G11: MM1 | H11: DD1 | I11: Metrado Actual | J11: P.U. Expediente | K11: Parcial Expediente | L11: P.U. Actualizado | M11: Parcial Actualizado | N11: Diferencia P.U. | O11: Diferencia Parcial | Q11: MM4 | R11: DD4 | S11: MM5 | T11: DD5
A12: x | C12: COMPONENTE 01: SUFICIENTE Y ADECUADA INFRAESTRUCTURA Y MANTENIMIENTO PARA LA PRESTACIÓN DE SERVICIOS DE SALUD | K12: =+K13+K26+K113+K247+K424+K621+K712+K759 -> 5393725.7 | M12: =+M13+M26+M113+M247+M424+M621+M712+M759 -> 5446984 | O12: =+O13+O26+O113+O247+O424+O621+O712+O759 -> 53258.29 | Q12: =+#REF!+Q45+Q309+Q619+#REF!+#REF!+#REF!+#REF! -> #REF! | R12: =+#REF!+R45+R309+R619+#REF!+#REF!+#REF!+#REF! -> #REF! | S12: =+#REF!+S45+S309+S619+#REF!+#REF!+#REF!+#REF! -> #REF! | T12: =+#REF!+T45+T309+T619+#REF!+#REF!+#REF!+#REF! -> #REF!
A13: X | B13: OE.1 | C13: OBRAS PROVISIONALES, TRABAJOS PRELIMINARES, SEGURIDAD Y SALUD. | K13: =+K14+K23 -> 41472.9 | M13: =+M14+M23 -> 41924.51 | O13: =+O14+O23 -> 451.61
B14: OE.1.1 | C14: OBRAS PROVISIONALES Y TRABAJOS PRELIMINARES | K14: =+K15+K21 -> 30972.9 | M14: =+M15+M21 -> 31424.51 | O14: =+O15+O21 -> 451.61
B15: OE.1.1.3 | C15: TRABAJOS PRELIMINARES | K15: =SUM(K16:K20)/2 -> 30356.89 | M15: =SUM(M16:M20)/2 -> 30805.35 | O15: =SUM(O16:O20)/2 -> 448.46
B16: OE.1.1.3.1 | C16: LIMPIEZA DE TERRENO | K16: =SUM(K17:K20) -> 30356.89 | M16: =SUM(M17:M20) -> 30805.35 | O16: =SUM(O17:O20) -> 448.46
B17: OE.1.1.3.1.2 | C17: Traslado de material en desuso d=100 m | D17: m3 | F17: 44 | I17: =SUM(E17:H17) -> 44 | J17: 40.45 | K17: =+ROUND(+IF(I17="",0,I17*J17),2) -> 1779.8 | L17: 42.1 | M17: =+ROUND(+IF(I17="",0,I17*L17),2) -> 1852.4 | N17: =+L17-J17 -> 1.65 | O17: =+M17-K17 -> 72.6
B18: OE.1.1.3.1.3 | C18: Limpieza de terreno | D18: m2 | F18: 23 | I18: =SUM(E18:H18) -> 23 | J18: 2.61 | K18: =+ROUND(+IF(I18="",0,I18*J18),2) -> 60.03 | L18: 2.75 | M18: =+ROUND(+IF(I18="",0,I18*L18),2) -> 63.25 | N18: =+L18-J18 -> 0.14 | O18: =+M18-K18 -> 3.22
B19: OE.1.1.3.1.4 | C19: Acarreo manual de material de desmonte | D19: m3 | F19: 54 | I19: =SUM(E19:H19) -> 54 | J19: 25.21 | K19: =+ROUND(+IF(I19="",0,I19*J19),2) -> 1361.34 | L19: 26.17 | M19: =+ROUND(+IF(I19="",0,I19*L19),2) -> 1413.18 | N19: =+L19-J19 -> 0.96 | O19: =+M19-K19 -> 51.84
B20: OE.1.1.3.1.5 | C20: Eliminacion de desmonte con maquinaria | D20: m3 | F20: 802 | I20: =SUM(E20:H20) -> 802 | J20: 33.86 | K20: =+ROUND(+IF(I20="",0,I20*J20),2) -> 27155.72 | L20: 34.26 | M20: =+ROUND(+IF(I20="",0,I20*L20),2) -> 27476.52 | N20: =+L20-J20 -> 0.4 | O20: =+M20-K20 -> 320.8
B21: OE.1.1.9 | C21: TRAZOS, NIVELES Y REPLANTEO | K21: =SUM(K22) -> 616.01 | M21: =SUM(M22) -> 619.16 | O21: =SUM(O22) -> 3.15
B22: OE.1.1.9.2 | C22: Trazo y Replanteo durante el proceso | D22: m2 | E22: 157.95 | I22: =SUM(E22:H22) -> 157.95 | J22: 3.9 | K22: =+ROUND(+IF(I22="",0,I22*J22),2) -> 616.01 | L22: 3.92 | M22: =+ROUND(+IF(I22="",0,I22*L22),2) -> 619.16 | N22: =+L22-J22 -> 0.02 | O22: =+M22-K22 -> 3.15
B23: OE.1.2 | C23: SEGURIDAD Y SALUD | K23: =+K24 -> 10500 | M23: =+M24 -> 10500 | O23: =+O24 -> 0
B24: OE.1.2.3 | C24: PLAN PARA LA VIGILANCIA PREVENCION Y CONTROL DE COVID EN EL TRABAJO | K24: =SUM(K25) -> 10500 | M24: =SUM(M25) -> 10500 | O24: =SUM(O25) -> 0
B25: OE.1.2.3.5 | C25: Servicio de Pruebas COVID - 19 | D25: und | E25: 60 | I25: =SUM(E25:H25) -> 60 | J25: 175 | K25: =+ROUND(+IF(I25="",0,I25*J25),2) -> 10500 | L25: 175 | M25: =+ROUND(+IF(I25="",0,I25*L25),2) -> 10500 | N25: =+L25-J25 -> 0 | O25: =+M25-K25 -> 0
A26: X | B26: OE.2 | C26: ESTRUCTURAS. | K26: =+K27+K40+K46+K63+K94 -> 1595735.2 | M26: =+M27+M40+M46+M63+M94 -> 1613832 | O26: =+O27+O40+O46+O63+O94 -> 18096.81
B27: OE.2.1 | C27: MOVIMIENTO DE TIERRAS | K27: =+K28+K30+K33+K36+K38 -> 84163.16 | M27: =+M28+M30+M33+M36+M38 -> 84339.37 | O27: =+O28+O30+O33+O36+O38 -> 176.21
B28: OE.2.1.1 | C28: EXCAVACIONES MASIVA | K28: =SUM(K29) -> 5535.71 | M28: =SUM(M29) -> 5594.6 | O28: =SUM(O29) -> 58.89
B29: OE.2.1.1.1 | C29: Excavacion con maquinaria | D29: m3 | E29: 1177.81 | I29: =SUM(E29:H29) -> 1177.81 | J29: 4.7 | K29: =+ROUND(+IF(I29="",0,I29*J29),2) -> 5535.71 | L29: 4.75 | M29: =+ROUND(+IF(I29="",0,I29*L29),2) -> 5594.6 | N29: =+L29-J29 -> 0.05 | O29: =+M29-K29 -> 58.89
B30: OE.2.1.2 | C30: EXCAVACIONES | K30: =SUM(K31:K32)/2 -> 1877.45 | M30: =SUM(M31:M32)/2 -> 1948.94 | O30: =SUM(O31:O32)/2 -> 71.49
B31: OE.2.1.2.1 | C31: EXCAVACIONES SIMPLES | K31: =SUM(K32) -> 1877.45 | M31: =SUM(M32) -> 1948.94 | O31: =SUM(O32) -> 71.49
B32: OE.2.1.2.1.1 | C32: Excavacion manual de zanjas para Zapatas | D32: m3 | E32: 44.68 | I32: =SUM(E32:H32) -> 44.68 | J32: 42.02 | K32: =+ROUND(+IF(I32="",0,I32*J32),2) -> 1877.45 | L32: 43.62 | M32: =+ROUND(+IF(I32="",0,I32*L32),2) -> 1948.94 | N32: =+L32-J32 -> 1.6 | O32: =+M32-K32 -> 71.49
B33: OE.2.1.4 | C33: RELLENOS | K33: =SUM(K34:K35) -> 2989.14 | M33: =SUM(M34:M35) -> 2990.92 | O33: =SUM(O34:O35) -> 1.78
B34: OE.2.1.4.1 | C34: Relleno compactado con material de prestamo | D34: m3 | E34: 7 | I34: =SUM(E34:H34) -> 7 | J34: 65.58 | K34: =+ROUND(+IF(I34="",0,I34*J34),2) -> 459.06 | L34: 65.58 | M34: =+ROUND(+IF(I34="",0,I34*L34),2) -> 459.06 | N34: =+L34-J34 -> 0 | O34: =+M34-K34 -> 0
B35: OE.2.1.4.2 | C35: Relleno compactado c/equipo con material de afirmado e=0.15m | D35: m2 | E35: 178.3 | I35: =SUM(E35:H35) -> 178.3 | J35: 14.19 | K35: =+ROUND(+IF(I35="",0,I35*J35),2) -> 2530.08 | L35: 14.2 | M35: =+ROUND(+IF(I35="",0,I35*L35),2) -> 2531.86 | N35: =+L35-J35 -> 0.01 | O35: =+M35-K35 -> 1.78
B36: OE.2.1.5. | C36: NIVELACION INTERIOR Y APISONADO | K36: =SUM(K37) -> 299.88 | M36: =SUM(M37) -> 310.74 | O36: =SUM(O37) -> 10.86
B37: OE.2.1.5.1 | C37: Nivelacion interior y apisonado para f.piso,patio y veredas | D37: m2 | E37: 68 | I37: =SUM(E37:H37) -> 68 | J37: 4.41 | K37: =+ROUND(+IF(I37="",0,I37*J37),2) -> 299.88 | L37: 4.56968 | M37: =+ROUND(+IF(I37="",0,I37*L37),2) -> 310.74 | N37: =+L37-J37 -> 0.15968 | O37: =+M37-K37 -> 10.86
B38: OE.2.1.6 | C38: ELIMINACION DE MATERIAL EXCEDENTE | K38: =SUM(K39) -> 73460.98 | M38: =SUM(M39) -> 73494.17 | O38: =SUM(O39) -> 33.19
B39: OE.2.1.6.2 | C39: Eliminacion de material excedente con maquinaria | D39: m3 | E39: 1659.76 | I39: =SUM(E39:H39) -> 1659.76 | J39: 44.26 | K39: =+ROUND(+IF(I39="",0,I39*J39),2) -> 73460.98 | L39: 44.28 | M39: =+ROUND(+IF(I39="",0,I39*L39),2) -> 73494.17 | N39: =+L39-J39 -> 0.02 | O39: =+M39-K39 -> 33.19
B40: OE.2.2 | C40: OBRAS DE CONCRETO SIMPLE | K40: =+K41+K43 -> 12830.19 | M40: =+M41+M43 -> 13003.48 | O40: =+O41+O43 -> 173.29
B41: OE.2.2.3 | C41: SOLADOS | K41: =SUM(K42) -> 5048.26 | M41: =SUM(M42) -> 5127.14 | O41: =SUM(O42) -> 78.88
B42: OE.2.2.3.1 | C42: Solado para zapata e=0.10m, f'c=100kg/cm2 | D42: m2 | E42: 117.73 | I42: =SUM(E42:H42) -> 117.73 | J42: 42.88 | K42: =+ROUND(+IF(I42="",0,I42*J42),2) -> 5048.26 | L42: 43.55 | M42: =+ROUND(+IF(I42="",0,I42*L42),2) -> 5127.14 | N42: =+L42-J42 -> 0.67 | O42: =+M42-K42 -> 78.88
B43: OE.2.2.4 | C43: DADOS DE ANCLAJE | K43: =SUM(K44:K45) -> 7781.93 | M43: =SUM(M44:M45) -> 7876.34 | O43: =SUM(O44:O45) -> 94.41
B44: OE.2.2.4.1 | C44: Dado de anclaje f'c= 210 kg/cm2 | D44: und | F44: 64 | I44: =SUM(E44:H44) -> 64 | J44: 72.23 | K44: =+ROUND(+IF(I44="",0,I44*J44),2) -> 4622.72 | L44: 73.4 | M44: =+ROUND(+IF(I44="",0,I44*L44),2) -> 4697.6 | N44: =+L44-J44 -> 1.17 | O44: =+M44-K44 -> 74.88
B45: OE.2.2.4.2 | C45: Acero en dado de anclaje para cimientos de columna | D45: kg | F45: 93 | I45: =SUM(E45:H45) -> 93 | J45: 33.97 | K45: =+ROUND(+IF(I45="",0,I45*J45),2) -> 3159.21 | L45: 34.18 | M45: =+ROUND(+IF(I45="",0,I45*L45),2) -> 3178.74 | N45: =+L45-J45 -> 0.21 | O45: =+M45-K45 -> 19.53
B46: OE.2.3 | C46: OBRAS DE CONCRETO ARMADO | K46: =+K47+K52+K56+K60 -> 108194.24 | M46: =+M47+M52+M56+M60 -> 109731.15 | O46: =+O47+O52+O56+O60 -> 1536.91
B47: OE.2.3.9 | C47: LOSAS | K47: =SUM(K48:K51)/2 -> 38462.36 | M47: =SUM(M48:M51)/2 -> 38731.88 | O47: =SUM(O48:O51)/2 -> 269.52
B48: OE.2.3.9.8 | C48: LOSAS DE CONCRETO | K48: =SUM(K49:K51) -> 38462.36 | M48: =SUM(M49:M51) -> 38731.88 | O48: =SUM(O49:O51) -> 269.52
B49: OE.2.3.9.8.1 | C49: Concreto f'c=210 kg/cm2 en losa | D49: m3 | F49: 72.95 | I49: =SUM(E49:H49) -> 72.95 | J49: 466.32 | K49: =+ROUND(+IF(I49="",0,I49*J49),2) -> 34018.04 | L49: 469.28 | M49: =+ROUND(+IF(I49="",0,I49*L49),2) -> 34233.98 | N49: =+L49-J49 -> 2.96 | O49: =+M49-K49 -> 215.94
B50: OE.2.3.9.8.2 | C50: Encofrado y desencofrado en losa de concreto | D50: m2 | F50: 8.09 | I50: =SUM(E50:H50) -> 8.09 | J50: 65.1 | K50: =+ROUND(+IF(I50="",0,I50*J50),2) -> 526.66 | L50: 66.43 | M50: =+ROUND(+IF(I50="",0,I50*L50),2) -> 537.42 | N50: =+L50-J50 -> 1.33 | O50: =+M50-K50 -> 10.76
B51: OE.2.3.9.8.3 | C51: Acero f'y=4200 kg/cm2 en losa de concreto | D51: kg | F51: 535.2 | I51: =SUM(E51:H51) -> 535.2 | J51: 7.32 | K51: =+ROUND(+IF(I51="",0,I51*J51),2) -> 3917.66 | L51: 7.4 | M51: =+ROUND(+IF(I51="",0,I51*L51),2) -> 3960.48 | N51: =+L51-J51 -> 0.08 | O51: =+M51-K51 -> 42.82
B52: OE.2.3.12 | C52: CISTERNA | K52: =SUM(K53:K55) -> 11598.05 | M52: =SUM(M53:M55) -> 11774.49 | O52: =SUM(O53:O55) -> 176.44
B53: OE.2.3.12.1 | C53: Cisternas -Concreto f´c=280kg/cm2 | D53: m3 | E53: 8.63 | I53: =SUM(E53:H53) -> 8.63 | J53: 661.41 | K53: =+ROUND(+IF(I53="",0,I53*J53),2) -> 5707.97 | L53: 671.64 | M53: =+ROUND(+IF(I53="",0,I53*L53),2) -> 5796.25 | N53: =+L53-J53 -> 10.23 | O53: =+M53-K53 -> 88.28
B54: OE.2.3.12.2 | C54: Cisternas -encofrado y desencofrado | D54: m2 | E54: 11.6 | I54: =SUM(E54:H54) -> 11.6 | J54: 74.31 | K54: =+ROUND(+IF(I54="",0,I54*J54),2) -> 862 | L54: 77.08 | M54: =+ROUND(+IF(I54="",0,I54*L54),2) -> 894.13 | N54: =+L54-J54 -> 2.77 | O54: =+M54-K54 -> 32.13
B55: OE.2.3.12.3 | C55: Cisternas -Acero fy=4200 kg/cm2 | D55: kg | E55: 700.29 | I55: =SUM(E55:H55) -> 700.29 | J55: 7.18 | K55: =+ROUND(+IF(I55="",0,I55*J55),2) -> 5028.08 | L55: 7.26 | M55: =+ROUND(+IF(I55="",0,I55*L55),2) -> 5084.11 | N55: =+L55-J55 -> 0.08 | O55: =+M55-K55 -> 56.03
B56: OE.2.3.13 | C56: SOBRECIMIENTO ARMADO | K56: =SUM(K57:K59) -> 23310.4 | M56: =SUM(M57:M59) -> 23803.77 | O56: =SUM(O57:O59) -> 493.37
B57: OE.2.3.13.1 | C57: Sobrecimiento concreto 1:8+25%PM | D57: m3 | F57: 16.9 | I57: =SUM(E57:H57) -> 16.9 | J57: 328.51 | K57: =+ROUND(+IF(I57="",0,I57*J57),2) -> 5551.82 | L57: 333.86 | M57: =+ROUND(+IF(I57="",0,I57*L57),2) -> 5642.23 | N57: =+L57-J57 -> 5.35 | O57: =+M57-K57 -> 90.41
B58: OE.2.3.13.2 | C58: Encofrado y desencofrado en sobrecimiento | D58: m2 | F58: 242.48 | I58: =SUM(E58:H58) -> 242.48 | J58: 67.61 | K58: =+ROUND(+IF(I58="",0,I58*J58),2) -> 16394.07 | L58: 69.05 | M58: =+ROUND(+IF(I58="",0,I58*L58),2) -> 16743.24 | N58: =+L58-J58 -> 1.44 | O58: =+M58-K58 -> 349.17
B59: OE.2.3.13.3 | C59: Acero f'y=4200 kg/cm2 en sobrecimiento | D59: kg | F59: 489.07 | I59: =SUM(E59:H59) -> 489.07 | J59: 2.79 | K59: =+ROUND(+IF(I59="",0,I59*J59),2) -> 1364.51 | L59: 2.9 | M59: =+ROUND(+IF(I59="",0,I59*L59),2) -> 1418.3 | N59: =+L59-J59 -> 0.11 | O59: =+M59-K59 -> 53.79
B60: OE.2.3.14 | C60: CIMIENTO CORRIDO | K60: =SUM(K61:K62) -> 34823.43 | M60: =SUM(M61:M62) -> 35421.01 | O60: =SUM(O61:O62) -> 597.58
B61: OE.2.3.14.1 | C61: Concreto f'c= 175 kg/cm2 en cimiento | D61: m3 | F61: 39.21 | I61: =SUM(E61:H61) -> 39.21 | J61: 379.99 | K61: =+ROUND(+IF(I61="",0,I61*J61),2) -> 14899.41 | L61: 387.39 | M61: =+ROUND(+IF(I61="",0,I61*L61),2) -> 15189.56 | N61: =+L61-J61 -> 7.4 | O61: =+M61-K61 -> 290.15
B62: OE.2.3.14.2 | C62: Encofrado y desencofrado en cimiento | D62: m2 | F62: 62.36 | I62: =SUM(E62:H62) -> 62.36 | J62: 319.5 | K62: =+ROUND(+IF(I62="",0,I62*J62),2) -> 19924.02 | L62: 324.43 | M62: =+ROUND(+IF(I62="",0,I62*L62),2) -> 20231.45 | N62: =+L62-J62 -> 4.93 | O62: =+M62-K62 -> 307.43
B63: OE.2.4 | C63: ESTRUCTURAS METÁLICAS | K63: =+K64+K68+K73+K92 -> 1134817.5 | M63: =+M64+M68+M73+M92 -> 1149106.5 | O63: =+O64+O68+O73+O92 -> 14288.99
B64: OE.2.4.1 | C64: COLUMNAS METALICAS | K64: =SUM(K65:K67) -> 320358.96 | M64: =SUM(M65:M67) -> 323186.95 | O64: =SUM(O65:O67) -> 2827.99
B65: OE.2.4.1.1.7 | C65: Placa Base Inc. Pernos de anclaje | D65: und | F65: 337 | I65: =SUM(E65:H65) -> 337 | J65: 160.83 | K65: =+ROUND(+IF(I65="",0,I65*J65),2) -> 54199.71 | L65: 161.35 | M65: =+ROUND(+IF(I65="",0,I65*L65),2) -> 54374.95 | N65: =+L65-J65 -> 0.52 | O65: =+M65-K65 -> 175.24
B66: OE.2.4.1.1.8 | C66: Armado Columnas metálicas 3mm (L=6m) | D66: kg | F66: 17685 | I66: =SUM(E66:H66) -> 17685 | J66: 11.46 | K66: =+ROUND(+IF(I66="",0,I66*J66),2) -> 202670.1 | L66: 11.52 | M66: =+ROUND(+IF(I66="",0,I66*L66),2) -> 203731.2 | N66: =+L66-J66 -> 0.06 | O66: =+M66-K66 -> 1061.1
B67: OE.2.4.1.1.9 | C67: Montaje Columnas metálicas 3mm (L=6m) | D67: kg | F67: 17685 | I67: =SUM(E67:H67) -> 17685 | J67: 3.59 | K67: =+ROUND(+IF(I67="",0,I67*J67),2) -> 63489.15 | L67: 3.68 | M67: =+ROUND(+IF(I67="",0,I67*L67),2) -> 65080.8 | N67: =+L67-J67 -> 0.09 | O67: =+M67-K67 -> 1591.65
B68: OE.2.4.2 | C68: VIGAS METALICAS | K68: =SUM(K69:K72)/2 -> 298945.7 | M68: =SUM(M69:M72)/2 -> 305293.46 | O68: =SUM(O69:O72)/2 -> 6347.76
B69: OE.2.4.2.2.2 | C69: PERNOS | K69: =SUM(K70:K72) -> 298945.7 | M69: =SUM(M70:M72) -> 305293.46 | O69: =SUM(O70:O72) -> 6347.76
B70: OE.2.4.2.2.2.5 | C70: Plancha Metalica Inc.Pernos de sujeción | D70: und | F70: 337 | I70: =SUM(E70:H70) -> 337 | J70: 136.23 | K70: =+ROUND(+IF(I70="",0,I70*J70),2) -> 45909.51 | L70: 137.04 | M70: =+ROUND(+IF(I70="",0,I70*L70),2) -> 46182.48 | N70: =+L70-J70 -> 0.81 | O70: =+M70-K70 -> 272.97
B71: OE.2.4.2.2.2.6 | C71: Armado vigas metálicas 150x100mm e= 3mm | D71: m | F71: 927.45 | I71: =SUM(E71:H71) -> 927.45 | J71: 201.95 | K71: =+ROUND(+IF(I71="",0,I71*J71),2) -> 187298.53 | L71: 207.41 | M71: =+ROUND(+IF(I71="",0,I71*L71),2) -> 192362.4 | N71: =+L71-J71 -> 5.46 | O71: =+M71-K71 -> 5063.87
B72: OE.2.4.2.2.2.7 | C72: Montaje vigas metálicas 150x100 mm e=3mm | D72: m | F72: 927.45 | I72: =SUM(E72:H72) -> 927.45 | J72: 70.88 | K72: =+ROUND(+IF(I72="",0,I72*J72),2) -> 65737.66 | L72: 71.97 | M72: =+ROUND(+IF(I72="",0,I72*L72),2) -> 66748.58 | N72: =+L72-J72 -> 1.09 | O72: =+M72-K72 -> 1010.92
B73: OE.2.4.3 | C73: TIJERALES METALICO | K73: =SUM(K74:K91)/2 -> 347321.55 | M73: =SUM(M74:M91)/2 -> 350312.71 | O73: =SUM(O74:O91)/2 -> 2991.16
B74: OE.2.4.3.2 | C74: Armado de Tijeral Metalico | K74: =SUM(K75:K82) -> 285585.65 | M74: =SUM(M75:M82) -> 287056.59 | O74: =SUM(O75:O82) -> 1470.94
B75: OE.2.4.3.2.1 | C75: Armado de Tijeral metalico Tipo 01 L=7.00 m | D75: und | F75: 28 | I75: =SUM(E75:H75) -> 28 | J75: 2166.84 | K75: =+ROUND(+IF(I75="",0,I75*J75),2) -> 60671.52 | L75: 2178.38 | M75: =+ROUND(+IF(I75="",0,I75*L75),2) -> 60994.64 | N75: =+L75-J75 -> 11.54 | O75: =+M75-K75 -> 323.12
B76: OE.2.4.3.2.2 | C76: Armado de Tijeral metalico Tipo 02 L=6.00 m | D76: und | F76: 72 | I76: =SUM(E76:H76) -> 72 | J76: 2101.64 | K76: =+ROUND(+IF(I76="",0,I76*J76),2) -> 151318.08 | L76: 2113.18 | M76: =+ROUND(+IF(I76="",0,I76*L76),2) -> 152148.96 | N76: =+L76-J76 -> 11.54 | O76: =+M76-K76 -> 830.88
B77: OE.2.4.3.2.3 | C77: Armado de Tijeral metalico Tipo 03 L=3.50 m | D77: und | F77: 1 | I77: =SUM(E77:H77) -> 1 | J77: 1309.99 | K77: =+ROUND(+IF(I77="",0,I77*J77),2) -> 1309.99 | L77: 1314.52 | M77: =+ROUND(+IF(I77="",0,I77*L77),2) -> 1314.52 | N77: =+L77-J77 -> 4.53 | O77: =+M77-K77 -> 4.53
B78: OE.2.4.3.2.4 | C78: Armado de Tijeral metalico Tipo 04 L=3.10 m | D78: und | F78: 13 | I78: =SUM(E78:H78) -> 13 | J78: 1280.92 | K78: =+ROUND(+IF(I78="",0,I78*J78),2) -> 16651.96 | L78: 1286.25 | M78: =+ROUND(+IF(I78="",0,I78*L78),2) -> 16721.25 | N78: =+L78-J78 -> 5.33 | O78: =+M78-K78 -> 69.29
B79: OE.2.4.3.2.5 | C79: Armado de Tijeral metalico Tipo 05 L=3.00 m | D79: und | F79: 2 | I79: =SUM(E79:H79) -> 2 | J79: 1316.4 | K79: =+ROUND(+IF(I79="",0,I79*J79),2) -> 2632.8 | L79: 1323.06 | M79: =+ROUND(+IF(I79="",0,I79*L79),2) -> 2646.12 | N79: =+L79-J79 -> 6.66 | O79: =+M79-K79 -> 13.32
B80: OE.2.4.3.2.6 | C80: Armado de Tijeral metalico Tipo 06 L=2.60 m | D80: und | F80: 15 | I80: =SUM(E80:H80) -> 15 | J80: 1238.4 | K80: =+ROUND(+IF(I80="",0,I80*J80),2) -> 18576 | L80: 1245.06 | M80: =+ROUND(+IF(I80="",0,I80*L80),2) -> 18675.9 | N80: =+L80-J80 -> 6.66 | O80: =+M80-K80 -> 99.9
B81: OE.2.4.3.2.7 | C81: Armado de Tijeral metalico Tipo 07 L=1.90 m | D81: und | F81: 15 | I81: =SUM(E81:H81) -> 15 | J81: 1202.92 | K81: =+ROUND(+IF(I81="",0,I81*J81),2) -> 18043.8 | L81: 1208.25 | M81: =+ROUND(+IF(I81="",0,I81*L81),2) -> 18123.75 | N81: =+L81-J81 -> 5.33 | O81: =+M81-K81 -> 79.95
B82: OE.2.4.3.2.8 | C82: Armado de Tijeral metalico Tipo 08 L=1.30 m | D82: und | F82: 15 | I82: =SUM(E82:H82) -> 15 | J82: 1092.1 | K82: =+ROUND(+IF(I82="",0,I82*J82),2) -> 16381.5 | L82: 1095.43 | M82: =+ROUND(+IF(I82="",0,I82*L82),2) -> 16431.45 | N82: =+L82-J82 -> 3.33 | O82: =+M82-K82 -> 49.95
B83: OE.2.4.3.3 | C83: Montaje de Tijeral Metalico | K83: =SUM(K84:K91) -> 61735.9 | M83: =SUM(M84:M91) -> 63256.12 | O83: =SUM(O84:O91) -> 1520.22
B84: OE.2.4.3.3.1 | C84: Montaje de Tijeral metalico Tipo 01 L=7.00 m | D84: und | F84: 28 | I84: =SUM(E84:H84) -> 28 | J84: 473.12 | K84: =+ROUND(+IF(I84="",0,I84*J84),2) -> 13247.36 | L84: 485 | M84: =+ROUND(+IF(I84="",0,I84*L84),2) -> 13580 | N84: =+L84-J84 -> 11.88 | O84: =+M84-K84 -> 332.64
B85: OE.2.4.3.3.2 | C85: Montaje de Tijeral metalico Tipo 02 L=6.00 m | D85: und | F85: 72 | I85: =SUM(E85:H85) -> 72 | J85: 469.92 | K85: =+ROUND(+IF(I85="",0,I85*J85),2) -> 33834.24 | L85: 481.8 | M85: =+ROUND(+IF(I85="",0,I85*L85),2) -> 34689.6 | N85: =+L85-J85 -> 11.88 | O85: =+M85-K85 -> 855.36
B86: OE.2.4.3.3.3 | C86: Montaje de Tijeral metalico Tipo 03 L=3.50 m | D86: und | F86: 2 | I86: =SUM(E86:H86) -> 2 | J86: 292.6 | K86: =+ROUND(+IF(I86="",0,I86*J86),2) -> 585.2 | L86: 299.26 | M86: =+ROUND(+IF(I86="",0,I86*L86),2) -> 598.52 | N86: =+L86-J86 -> 6.66 | O86: =+M86-K86 -> 13.32
B87: OE.2.4.3.3.4 | C87: Montaje de Tijeral metalico Tipo 04 L=3.10 m | D87: und | F87: 13 | I87: =SUM(E87:H87) -> 13 | J87: 326.39 | K87: =+ROUND(+IF(I87="",0,I87*J87),2) -> 4243.07 | L87: 335.31 | M87: =+ROUND(+IF(I87="",0,I87*L87),2) -> 4359.03 | N87: =+L87-J87 -> 8.92 | O87: =+M87-K87 -> 115.96
B88: OE.2.4.3.3.5 | C88: Montaje de Tijeral metalico Tipo 05 L=3.00 m | D88: und | F88: 2 | I88: =SUM(E88:H88) -> 2 | J88: 326.39 | K88: =+ROUND(+IF(I88="",0,I88*J88),2) -> 652.78 | L88: 335.31 | M88: =+ROUND(+IF(I88="",0,I88*L88),2) -> 670.62 | N88: =+L88-J88 -> 8.92 | O88: =+M88-K88 -> 17.84
B89: OE.2.4.3.3.6 | C89: Montaje de Tijeral metalico Tipo 06 L=2.60 m | D89: und | F89: 15 | I89: =SUM(E89:H89) -> 15 | J89: 213.71 | K89: =+ROUND(+IF(I89="",0,I89*J89),2) -> 3205.65 | L89: 218.07 | M89: =+ROUND(+IF(I89="",0,I89*L89),2) -> 3271.05 | N89: =+L89-J89 -> 4.36 | O89: =+M89-K89 -> 65.4
B90: OE.2.4.3.3.7 | C90: Montaje de Tijeral metalico Tipo 07 L=1.90 m | D90: und | F90: 15 | I90: =SUM(E90:H90) -> 15 | J90: 213.71 | K90: =+ROUND(+IF(I90="",0,I90*J90),2) -> 3205.65 | L90: 218.07 | M90: =+ROUND(+IF(I90="",0,I90*L90),2) -> 3271.05 | N90: =+L90-J90 -> 4.36 | O90: =+M90-K90 -> 65.4
B91: OE.2.4.3.3.8 | C91: Montaje de Tijeral metalico Tipo 08 L=1.30 m | D91: und | F91: 15 | I91: =SUM(E91:H91) -> 15 | J91: 184.13 | K91: =+ROUND(+IF(I91="",0,I91*J91),2) -> 2761.95 | L91: 187.75 | M91: =+ROUND(+IF(I91="",0,I91*L91),2) -> 2816.25 | N91: =+L91-J91 -> 3.62 | O91: =+M91-K91 -> 54.3
B92: OE.2.4.4 | C92: CORREAS METALICAS | K92: =SUM(K93) -> 168191.3 | M92: =SUM(M93) -> 170313.38 | O92: =SUM(O93) -> 2122.08
B93: OE.2.4.4.2 | C93: Correas metalicas de 50x50x3mm | D93: m | F93: 3215.28 | I93: =SUM(E93:H93) -> 3215.28 | J93: 52.31 | K93: =+ROUND(+IF(I93="",0,I93*J93),2) -> 168191.3 | L93: 52.97 | M93: =+ROUND(+IF(I93="",0,I93*L93),2) -> 170313.38 | N93: =+L93-J93 -> 0.66 | O93: =+M93-K93 -> 2122.08
B94: OE.2.6 | C94: VARIOS | K94: =+K95+K97+K101+K103+K109+K111 -> 255730.07 | M94: =+M95+M97+M101+M103+M109+M111 -> 257651.48 | O94: =+O95+O97+O101+O103+O109+O111 -> 1921.41
B95: OE.2.6.1 | C95: ARRIOSTRAMIENTO METALICO | K95: =SUM(K96) -> 60421.41 | M95: =SUM(M96) -> 61309.96 | O95: =SUM(O96) -> 888.55
B96: OE.2.6.1.1 | C96: Arriostramiento metalico | D96: kg | E96: 4936.39 | I96: =SUM(E96:H96) -> 4936.39 | J96: 12.24 | K96: =+ROUND(+IF(I96="",0,I96*J96),2) -> 60421.41 | L96: 12.42 | M96: =+ROUND(+IF(I96="",0,I96*L96),2) -> 61309.96 | N96: =+L96-J96 -> 0.18 | O96: =+M96-K96 -> 888.55
B97: OE.2.6.3 | C97: ARRIOSTRES DEL TECHO | K97: =SUM(K98:K100) -> 6542.39 | M97: =SUM(M98:M100) -> 6637.66 | O97: =SUM(O98:O100) -> 95.27
B98: OE.2.6.3.1 | C98: Acero Ø 1/2" LISO | D98: m | E98: 492.2 | I98: =SUM(E98:H98) -> 492.2 | J98: 9.3 | K98: =+ROUND(+IF(I98="",0,I98*J98),2) -> 4577.46 | L98: 9.44 | M98: =+ROUND(+IF(I98="",0,I98*L98),2) -> 4646.37 | N98: =+L98-J98 -> 0.14 | O98: =+M98-K98 -> 68.91
B99: OE.2.6.3.2 | C99: Conexión de tirantes L64x64x7.9 | D99: m | E99: 8.67 | I99: =SUM(E99:H99) -> 8.67 | J99: 53.06 | K99: =+ROUND(+IF(I99="",0,I99*J99),2) -> 460.03 | L99: 53.74 | M99: =+ROUND(+IF(I99="",0,I99*L99),2) -> 465.93 | N99: =+L99-J99 -> 0.68 | O99: =+M99-K99 -> 5.9
B100: OE.2.6.3.3 | C100: Angulo 2.5X2.5X3/16" | D100: m | E100: 30.08 | I100: =SUM(E100:H100) -> 30.08 | J100: 50.03 | K100: =+ROUND(+IF(I100="",0,I100*J100),2) -> 1504.9 | L100: 50.71 | M100: =+ROUND(+IF(I100="",0,I100*L100),2) -> 1525.36 | N100: =+L100-J100 -> 0.68 | O100: =+M100-K100 -> 20.46
B101: OE.2.6.4 | C101: PINTURA DE PROTECCION ANTICORROSIVA | K101: =SUM(K102) -> 95182.77 | M101: =SUM(M102) -> 96039.06 | O101: =SUM(O102) -> 856.29
B102: OE.2.6.4.1 | C102: Pintura a base de resinas epoxi para protección anticorrosión | D102: m2 | E102: 4506.76 | I102: =SUM(E102:H102) -> 4506.76 | J102: 21.12 | K102: =+ROUND(+IF(I102="",0,I102*J102),2) -> 95182.77 | L102: 21.31 | M102: =+ROUND(+IF(I102="",0,I102*L102),2) -> 96039.06 | N102: =+L102-J102 -> 0.19 | O102: =+M102-K102 -> 856.29
B103: OE.2.6.5 | C103: CONTROL DE CALIDAD | K103: =SUM(K104:K108) -> 5513.58 | M103: =SUM(M104:M108) -> 5513.58 | O103: =SUM(O104:O108) -> 0
B104: OE.2.6.5.1 | C104: Verificación de Capacidad Portante | D104: und | E104: 2 | I104: =SUM(E104:H104) -> 2 | J104: 737.77 | K104: =+ROUND(+IF(I104="",0,I104*J104),2) -> 1475.54 | L104: 737.77 | M104: =+ROUND(+IF(I104="",0,I104*L104),2) -> 1475.54 | N104: =+L104-J104 -> 0 | O104: =+M104-K104 -> 0
B105: OE.2.6.5.2 | C105: Diseño de Mezclas | D105: und | E105: 2 | I105: =SUM(E105:H105) -> 2 | J105: 450 | K105: =+ROUND(+IF(I105="",0,I105*J105),2) -> 900 | L105: 450 | M105: =+ROUND(+IF(I105="",0,I105*L105),2) -> 900 | N105: =+L105-J105 -> 0 | O105: =+M105-K105 -> 0
...

Sheet DD-2
B1: |
B5: UNIDAD EJECUTORA | C5: : GERENCIA REGIONAL DE GESTION DE INVERSIONES DE INFRAESTRUCTURA - GOBIERNO REGIONAL CUSCO (SEDE CENTRAL)
B6: OBRA | C6: : MEJORAMIENTO Y AMPLIACION DE LOS SERVICIOS DE SALUD DEL ESTABLECIMIENTO DE SALUD DE BELEMPAMPA - DISTRITO DE SANTIAGO - PROVINCIA DE CUSCO - REGION CUSCO
B7: META | C7: : 0119-2025
B9: PARTIDAS DEDUCTIVOS N°04
B11: Item | C11: DESCRIPCION | D11: Und | E11: Metrado | F11: PU | G11: Parcial
B13: OE.3 | C13: ARQUITECTURA | G13: =+G14+G16+G20 -> 238275.81 | H13: X
B14: OE.3.3 | C14: CIELORRASOS | G14: =SUM(G15) -> 182063.62
B15: OE.3.3.6.4 | C15: Falso Cielorraso (Baldosa Translucida 0.61 x 0.61m) | D15: m2 | E15: 477.92 | F15: 380.95 | G15: =+ROUND(+IF(E15="",0,E15*F15),2) -> 182063.62
B16: OE.3.5 | C16: ZOCALOS Y CONTRAZOCALOS | G16: =+G17 -> 36219.35
B17: OE.3.5.2 | C17: CONTRAZOCALOS | G17: =SUM(G18:G19) -> 36219.35
B18: OE.3.5.2.11 | C18: OTROS
B19: OE.3.5.2.11.1 | C19: CONTRAZOCALO SANITARIO COVER FORMER H=0.10 M. | D19: m | E19: 1234.47 | F19: 29.34 | G19: =+ROUND(+IF(E19="",0,E19*F19),2) -> 36219.35
B20: OE.3.8 | C20: CARPINTERÍA METÁLICA Y HERRERÍA | G20: =+G21 -> 19992.84
B21: OE.3.8.14 | C21: BARANDA METALICA | G21: =SUM(G22:G22) -> 19992.84
B22: OE.3.8.14.1 | C22: BARANDAS METALICA EN ESCALERA PRINCIPAL H=1.17 m | D22: m | E22: 75.13 | F22: 266.11 | G22: =+ROUND(+IF(E22="",0,E22*F22),2) -> 19992.84
B23: TOTAL COSTO DIRECTO PARTIDAS DEDUCTIVOS N°04 | G23: =+G13 -> 238275.81

Sheet MM-3
B1: |
B5: UNIDAD EJECUTORA | C5: : GERENCIA REGIONAL DE GESTION DE INVERSIONES DE INFRAESTRUCTURA - GOBIERNO REGIONAL CUSCO (SEDE CENTRAL)
B6: OBRA | C6: : MEJORAMIENTO Y AMPLIACION DE LOS SERVICIOS DE SALUD DEL ESTABLECIMIENTO DE SALUD DE BELEMPAMPA - DISTRITO DE SANTIAGO - PROVINCIA DE CUSCO - REGION CUSCO
B7: META | C7: : 0119-2025
B9: MAYORES METRADOS N°03
B11: Item | C11: DESCRIPCION | D11: Und | E11: Metrado | F11: PU | G11: Parcial
B13: OE.1 | C13: OBRAS PROVISIONALES, TRABAJOS PRELIMINARES, SEGURIDAD Y SALUD. | G13: =+G14 -> 37042.77
B14: OE.1.1 | C14: OBRAS PROVISIONALES Y TRABAJOS PRELIMINARES | G14: =+G15+G18+G24 -> 37042.77
B15: OE.1.1.2 | C15: INSTALACIONES PROVISIONALES | G15: =SUM(G16:G17) -> 4304.87
B16: OE.1.1.2.3 | C16: Energia Electrica Provisional | D16: glb | E16: 1 | F16: 2837.67 | G16: =+ROUND(E16*F16,2) -> 2837.67
B17: OE.1.1.2.4 | C17: Abastecimiento Provisional de agua | D17: glb | E17: 1 | F17: 1467.2 | G17: =+ROUND(E17*F17,2) -> 1467.2
B18: OE.1.1.3 | C18: TRABAJOS PRELIMINARES | G18: =SUM(G19:G23)/2 -> 21565.9
B19: OE.1.1.3.1 | C19: LIMPIEZA DE TERRENO | G19: =SUM(G20:G23) -> 21565.9
B20: OE.1.1.3.1.1 | C20: Eliminación de maleza y arbustos de fácil extracción | D20: m2 | E20: 294 | F20: 13.45 | G20: =+ROUND(E20*F20,2) -> 3954.3
B21: OE.1.1.3.1.2 | C21: Traslado de materiales en desuso d=100 m | D21: m3 | E21: 248 | F21: 42.1 | G21: =+ROUND(E21*F21,2) -> 10440.8
B22: OE.1.1.3.1.3 | C22: Limpieza de terrreno | D22: m2 | E22: 1989 | F22: 2.75 | G22: =+ROUND(E22*F22,2) -> 5469.75
B23: OE.1.1.3.1.4 | C23: Acarreo manual de material de desmonte | D23: m3 | E23: 65 | F23: 26.17 | G23: =+ROUND(E23*F23,2) -> 1701.05
B24: OE.1.1.9 | C24: TRAZOS, NIVELES Y REPLANTEO | G24: =SUM(G25) -> 11172
B25: OE.1.1.9.2 | C25: Trazo y Replanteo durante el proceso | D25: m2 | E25: 2850 | F25: 3.92 | G25: =+ROUND(E25*F25,2) -> 11172
B26: OE.2 | C26: ESTRUCTURAS. | G26: =+G27 -> 283626.56
B27: OE.2.4 | C27: ESTRUCTURAS METÁLICAS | G27: =+G28+G32+G38 -> 283626.56
B28: OE.2.4.1 | C28: COLUMNAS METALICAS | G28: =SUM(G29:G31) -> 8034.17
B29: OE.2.4.1.1.7 | C29: Placa base Inc. Pernos de anclaje | D29: und | E29: 30 | F29: 161.35 | G29: =+ROUND(E29*F29,2) -> 4840.5
B30: OE.2.4.1.1.8 | C30: Armado Columnas metálicas | D30: kg | E30: 210.11 | F30: 11.52 | G30: =+ROUND(E30*F30,2) -> 2420.47
B31: OE.2.4.1.1.9 | C31: Montaje Columnas metálicas | D31: kg | E31: 210.11 | F31: 3.68 | G31: =+ROUND(E31*F31,2) -> 773.2
B32: OE.2.4.2 | C32: VIGAS METALICAS | G32: =SUM(G33:G37)/2 -> 144494.26
B33: OE.2.4.2.1 | C33: PARA ARMADO | G33: =SUM(G34) -> 103862.63
B34: OE.2.4.2.2.2.6 | C34: Armado de vigas metalicas | D34: m | E34: 500.76 | F34: 207.41 | G34: =+ROUND(E34*F34,2) -> 103862.63
B35: OE.2.4.2.3 | C35: PARA MONTAJE | G35: =SUM(G36:G37) -> 40631.63
B36: OE.2.4.2.2.2.5 | C36: Plancha Metálica Inc. Pernos de sujeción | D36: und | E36: 30 | F36: 137.04 | G36: =+ROUND(E36*F36,2) -> 4111.2
B37: OE.2.4.2.2.2.7 | C37: Montaje vigas metálicas | D37: m | E37: 500.76 | F37: 72.93 | G37: =+ROUND(E37*F37,2) -> 36520.43
B38: OE.2.4.3 | C38: TIJERALES METALICO | G38: =SUM(G39:G48)/2 -> 131098.13
B39: OE.2.4.3.2 | C39: Armado de Tijeral Metalico | G39: =SUM(G40:G43) -> 107158.43
B40: OE.2.4.3.2.2 | C40: Armado de Tijeral metálico Tipo 02 L=6.00 m | D40: und | E40: 35 | F40: 2113.18 | G40: =+ROUND(E40*F40,2) -> 73961.3
B41: OE.2.4.3.2.5 | C41: Armado de Tijeral metálico Tipo 05 L=3.00 m | D41: und | E41: 12 | F41: 1323.06 | G41: =+ROUND(E41*F41,2) -> 15876.72
B42: OE.2.4.3.2.6 | C42: Armado de Tijeral metálico Tipo 06 L=2.60 m | D42: und | E42: 11 | F42: 1245.06 | G42: =+ROUND(E42*F42,2) -> 13695.66
B43: OE.2.4.3.2.7 | C43: Armado de Tijeral metálico Tipo 07 L=1.90 m | D43: und | E43: 3 | F43: 1208.25 | G43: =+ROUND(E43*F43,2) -> 3624.75
B44: OE.2.4.3.3 | C44: Montaje de Tijeral Metalico | G44: =SUM(G45:G48) -> 23939.7
B45: OE.2.4.3.3.2 | C45: Montaje de Tijeral metálico Tipo 02 L=6.00 m | D45: und | E45: 35 | F45: 481.8 | G45: =+ROUND(E45*F45,2) -> 16863
B46: OE.2.4.3.3.5 | C46: Montaje de Tijeral metálico Tipo 05 L=3.00 m | D46: und | E46: 12 | F46: 335.31 | G46: =+ROUND(E46*F46,2) -> 4023.72
B47: OE.2.4.3.3.6 | C47: Montaje de Tijeral metálico Tipo 06 L=2.60 m | D47: und | E47: 11 | F47: 218.07 | G47: =+ROUND(E47*F47,2) -> 2398.77
B48: OE.2.4.3.3.7 | C48: Montaje de Tijeral metálico Tipo 07 L=1.90 m | D48: und | E48: 3 | F48: 218.07 | G48: =+ROUND(E48*F48,2) -> 654.21
B49: OE.3 | C49: ARQUITECTURA | G49: =+G50+G53+G62+G68+G71+G74+G77+G81 -> 231956.11
B50: OE.3.3 | C50: CIELORRASOS | G50: =+G51 -> 29113.4
B51: OE.3.3.6 | C51: FALSO CIELO RASO | G51: =SUM(G52) -> 29113.4
B52: OE.3.3.6.1 | C52: FALSO CIELORRASO (BALDOSA DE FIBRA MINERAL BIOSOLUBLE 0.61 x 0.61m, E=14mm.) | D52: m2 | E52: 399.58 | F52: 72.86 | G52: =+ROUND(E52*F52,2) -> 29113.4
B53: OE.3.4 | C53: PISOS Y PAVIMENTOS | G53: =+G54+G59 -> 54770.64
B54: OE.3.4.2 | C54: PISOS | G54: =SUM(G55:G58) -> 53995.76
B55: OE.3.4.2.20 | C55: Piso Porcelanato de 60x60 antideslizante de alto transito | D55: m2 | E55: 303.16 | F55: 46.85 | G55: =+ROUND(E55*F55,2) -> 14203.05
B56: OE.3.4.2.25 | C56: Piso de Cemento Pulido | D56: m2 | E56: 41.61 | F56: 40.65 | G56: =+ROUND(E56*F56,2) -> 1691.45
B57: OE.3.4.2.26 | C57: Piso Vinilico Conductivo | D57: m2 | E57: 17.26 | F57: 192.01 | G57: =+ROUND(E57*F57,2) -> 3314.09
B58: OE.3.4.2.27 | C58: Piso de terrazo | D58: m2 | E58: 304.19 | F58: 114.36 | G58: =+ROUND(E58*F58,2) -> 34787.17
B59: OE.3.4.3 | C59: PISOS DE CONCRETO | G59: =SUM(G60:G61)/2 -> 774.88
B60: OE.3.4.3.3 | C60: CIRCULACIÓN EN PATIO DE MANIOBRAS | G60: =SUM(G61) -> 774.88
B61: OE.3.4.3.3.1 | C61: Empedrado e=10 cm | D61: m2 | E61: 29.12 | F61: 26.61 | G61: =+ROUND(E61*F61,2) -> 774.88
B62: OE.3.5 | C62: ZOCALOS Y CONTRAZOCALOS | G62: =+G63+G65 -> 79983.06
B63: OE.3.5.1 | C63: ZOCALOS | G63: =SUM(G64) -> 47255.99
B64: OE.3.5.1.12 | C64: Zocalo de porcelanato de 60X 60 cm | D64: m2 | E64: 768.64 | F64: 61.48 | G64: =+ROUND(E64*F64,2) -> 47255.99
B65: OE.3.5.2 | C65: CONTRAZOCALOS | G65: =SUM(G66:G67)/2 -> 32727.07
B66: OE.3.5.2.3 | C66: CONTRAZOCALOS DE CERAMICO | G66: =SUM(G67) -> 32727.07
B67: OE.3.5.2.3.4 | C67: Contrazocalo de Terrazo (H=10cm) | D67: m | E67: 334.53 | F67: 97.83 | G67: =+ROUND(E67*F67,2) -> 32727.07
B68: OE.3.6 | C68: COBERTURAS | G68: =+G69 -> 932.14
B69: OE.3.6.7 | C69: RECUBRIMIENTOS SOBRE ESTRUCTURAS DE MADERA, METAL, ETC. | G69: =SUM(G70) -> 932.14
B70: OE.3.6.7.5 | C70: Cumbrera para panel termoacustico | D70: m | E70: 29.62 | F70: 31.47 | G70: =+ROUND(E70*F70,2) -> 932.14
B71: OE.3.7 | C71: CARPINTERÍA METÁLICA Y HERRERÍA | G71: =+G72 -> 226.65
B72: OE.3.8.18 | C72: ELEMENTOS METALICOS ESPECIALES | G72: =SUM(G73) -> 226.65
B73: OE.3.8.18.1 | C73: TOPE DE ACERO CROMADO PARA PUERTAS. | D73: und | E73: 15 | F73: 15.11 | G73: =+ROUND(E73*F73,2) -> 226.65
B74: OE.3.9 | C74: CERRAJERIA | G74: =+G75 -> 9548.28
B75: OE.3.9.1 | C75: BISAGRAS | G75: =SUM(G76) -> 9548.28
B76: OE.3.9.1.2 | C76: BISAGRA ALUMINIZADA CAPUCHINA PESADA 4"x4" | D76: und | E76: 378 | F76: 25.26 | G76: =+ROUND(E76*F76,2) -> 9548.28
B77: OE.3.11 | C77: PINTURA | G77: =+G78 -> 32435.3
B78: OE.3.11.1 | C78: PINTURA DE CIELOS RASOS, VIGAS, COLUMNAS Y PAREDES | G78: =SUM(G79:G80) -> 32435.3
B79: OE.3.11.1.4 | C79: Pintura muros interiores c/ latex antibacterial (2 MANOS). C/ IMPRIMANTE | D79: m2 | E79: 475.87 | F79: 34.66 | G79: =+ROUND(E79*F79,2) -> 16493.65
B80: OE.3.11.1.6 | C80: Empastado y lijado de muros interiores | D80: m2 | E80: 475.87 | F80: 33.5 | G80: =+ROUND(E80*F80,2) -> 15941.65
B81: OE.3.12 | C81: VARIOS, LIMPIEZA, JARDINERIA | G81: =SUM(G82:G86)-G84 -> 24946.64
B82: OE.3.12.1 | C82: LIMPIEZA PERMANENTE DE OBRA | D82: glb | E82: 1 | F82: 6542.56 | G82: =+ROUND(E82*F82,2) -> 6542.56
B83: OE.3.12.2 | C83: LIMPIEZA FINAL DE OBRA | D83: glb | E83: 1 | F83: 3653.73 | G83: =+ROUND(E83*F83,2) -> 3653.73
B84: OE.3.12.5 | C84: SEMBRIO DE GRASS | G84: =SUM(G85:G86) -> 14750.35
B85: OE.3.12.5.1 | C85: SEMBRIO DE GRASS | D85: m2 | E85: 923.16 | F85: 14.39 | G85: =+ROUND(E85*F85,2) -> 13284.27
B86: OE.3.12.5.2 | C86: PLANTACION DE ARBUSTOS | D86: und | E86: 136 | F86: 10.78 | G86: =+ROUND(E86*F86,2) -> 1466.08
B87: OE.4 | C87: INSTALACIONES SANITARIAS | G87: =+G88+G105+G125+G128+G150 -> 75568.32
B88: OE.4.1 | C88: APARATOS SANITARIOS Y ACCESORIOS | G88: =+G89+G94+G97+G102 -> 6349.82
B89: OE.4.1.1 | C89: SUMINISTRO DE APARATOS SANITARIOS Y ACCESORIOS | G89: =SUM(G90:G93)/2 -> 5393.35
B90: OE.4.1.1.1 | C90: SUMINISTRO DE URINARIOS | G90: =SUM(G91) -> 220
B91: OE.4.1.1.1.1 | C91: Urinario de loza tipo C-9 | D91: und | E91: 1 | F91: 220 | G91: =+ROUND(E91*F91,2) -> 220 | H91: x
B92: OE.4.1.1.3 | C92: SUMINISTRO DE LAVATORIOS | G92: =SUM(G93) -> 5173.35
B93: OE.4.1.1.3.1 | C93: Lavatorio de Loza Tipo Ovalin 60x50 | D93: und | E93: 35 | F93: 147.81 | G93: =+ROUND(E93*F93,2) -> 5173.35 | H93: x
B94: OE.4.1.2 | C94: SUMINISTRO DE ACCESORIOS | G94: =SUM(G95:G96)/2 -> 95.14
B95: OE.4.1.2.1 | C95: SUMINISTRO DE ACCESORIOS PARA URINARIOS | G95: =SUM(G96) -> 95.14
B96: OE.4.1.2.1.1 | C96: Accesorios para urinario de loza | D96: und | E96: 1 | F96: 95.14 | G96: =+ROUND(E96*F96,2) -> 95.14 | H96: x
B97: OE.4.1.3 | C97: INSTALACIÓN DE APARATOS SANITARIOS | G97: =SUM(G98:G101)/2 -> 840.04
B98: OE.4.1.3.1 | C98: INSTALACIÓN DE URINARIOS | G98: =SUM(G99) -> 14.74
B99: OE.4.1.3.1.1 | C99: Instalación de Urinario de loza | D99: und | E99: 1 | F99: 14.74 | G99: =+ROUND(E99*F99,2) -> 14.74 | H99: x
B100: OE.4.1.3.3 | C100: INSTALACIÓN DE LAVATORIOS | G100: =SUM(G101) -> 825.3
B101: OE.4.1.3.3.1 | C101: Instalacion de lavatorio de loza tipo ovalin 60x50 | D101: und | E101: 35 | F101: 23.58 | G101: =+ROUND(E101*F101,2) -> 825.3 | H101: x
B102: OE.4.1.4 | C102: INSTALACIÓN DE ACCESORIOS | G102: =SUM(G103:G104)/2 -> 21.29
B103: OE.4.1.4.1 | C103: INSTALACIÓN DE ACCESORIOS PARA URINARIOS | G103: =SUM(G104) -> 21.29
B104: OE.4.1.4.1.1 | C104: Instalacion de accesorios para urinario de loza | D104: und | E104: 1 | F104: 21.29 | G104: =+ROUND(E104*F104,2) -> 21.29
B105: OE.4.2 | C105: SISTEMA DE AGUA FRIA | G105: =+G106+G114+G119+G122 -> 21743.45
B106: OE.4.2.3 | C106: REDES DE ALIMENTACIÓN EXTERIORES | G106: =SUM(G107:G113)/2 -> 10857.61
...

Sheet PN-3
B1: |
B5: UNIDAD EJECUTORA | C5: : GERENCIA REGIONAL DE GESTION DE INVERSIONES DE INFRAESTRUCTURA - GOBIERNO REGIONAL CUSCO (SEDE CENTRAL)
B6: OBRA | C6: : MEJORAMIENTO Y AMPLIACION DE LOS SERVICIOS DE SALUD DEL ESTABLECIMIENTO DE SALUD DE BELEMPAMPA - DISTRITO DE SANTIAGO - PROVINCIA DE CUSCO - REGION CUSCO
B7: META | C7: : 0119-2025
B9: PARTIDAS NUEVAS N°03
B11: Item | C11: DESCRIPCION | D11: Und | E11: Metrado | F11: PU | G11: Parcial
B13: OE.2 | C13: ESTRUCTURAS. | G13: =+G14+G20 -> 47896.24
B14: OE.2.4 | C14: ESTRUCTURAS METÁLICAS | G14: =+G15 -> 9997.84
B15: OE.2.4.4 | C15: TIJERALES METALICO | G15: =SUM(G16:G19)/2 -> 9997.84
B16: OE.2.4.4.1 | C16: ARMADO DE TIJERAL METALICO | G16: =SUM(G17) -> 7901.44
B17: OE.2.4.3.2.9 | C17: Armado de Tijeral metálico Tipo 09 L=3.70 m | D17: und | E17: 8 | F17: 987.68 | G17: =+ROUND(E17*F17,2) -> 7901.44
B18: OE.2.4.4.2 | C18: MONTAJE DE TIJERAL METALICO | G18: =SUM(G19) -> 2096.4
B19: OE.2.4.3.3.9 | C19: Montaje de Tijeral metálico Tipo 09 L=3.70 m | D19: und | E19: 8 | F19: 262.05 | G19: =+ROUND(E19*F19,2) -> 2096.4
B20: OE.2.6 | C20: VARIOS | G20: =+G21 -> 37898.4
B21: OE.2.6.1 | C21: ARRIOSTRAMIENTO METALICO | G21: =SUM(G22:G23) -> 37898.4
B22: OE.2.6.1.2 | C22: Plancha estriada de 1.20x2.40, e=1/8" | D22: und | E22: 18 | F22: 1093.5 | G22: =+ROUND(E22*F22,2) -> 19683
B23: OE.2.6.1.3 | C23: Parantes metalicos para contramarcos perfil 50x50x3.00mm | D23: und | E23: 140 | F23: 130.11 | G23: =+ROUND(E23*F23,2) -> 18215.4
B24: OE.3 | C24: ARQUITECTURA | G24: =+G25+G29+G32+G35+G39+G42+G62+G95+G102+G107+G111 -> 1041552.4
B25: OE.3.1 | C25: MUROS Y TABIQUES DE ALBAÑILERIA | G25: =+G26 -> 65076.12
B26: OE.3.1.10 | C26: MUROS CON EL SISTEMA DE CONSTRUCCIÓN EN SECO (SISTEMA DRY WALL O SIMILAR) | G26: =SUM(G27:G28) -> 65076.12
B27: OE.3.1.10.7 | C27: Recubrimiento de elementos estructurales con fibrocemento de 6mm | D27: m2 | E27: 163.24 | F27: 48.64 | G27: =+ROUND(E27*F27,2) -> 7939.99
B28: OE.3.1.10.8 | C28: Muro sistema de fibrocemento con lamina de plomo e=3mm | D28: m2 | E28: 44.8 | F28: 1275.36 | G28: =+ROUND(E28*F28,2) -> 57136.13
B29: OE.3.3 | C29: CIELORRASOS | G29: =+G30 -> 6334.46
B30: OE.3.3.6 | C30: FALSO CIELO RASO | G30: =SUM(G31) -> 6334.46
B31: OE.3.3.6.5 | C31: Falso cielo raso con placa superboard 6mm incluye estructuras | D31: m2 | E31: 32.01 | F31: 197.89 | G31: =+ROUND(E31*F31,2) -> 6334.46
B32: OE.3.4 | C32: PISOS Y PAVIMENTOS | G32: =+G33 -> 4551.13
B33: OE.3.4.2 | C33: PISOS | G33: =SUM(G34) -> 4551.13
B34: OE.3.4.2.28 | C34: Base de concreto para muebles fijos H=10cm | D34: m2 | E34: 21.93 | F34: 207.53 | G34: =+ROUND(E34*F34,2) -> 4551.13
B35: OE.3.5 | C35: ZOCALOS Y CONTRAZOCALOS | G35: =+G36 -> 23196.65
B36: OE.3.5.2 | C36: CONTRAZOCALOS | G36: =SUM(G37:G38)/2 -> 23196.65
B37: OE.3.5.2.3 | C37: CONTRAZOCALOS DE CERAMICO | G37: =SUM(G38) -> 23196.65
B38: OE.3.5.2.3.6 | C38: Contrazocalo de porcelanato H=10cm | D38: m | E38: 1001.15 | F38: 23.17 | G38: =+ROUND(E38*F38,2) -> 23196.65
B39: OE.3.6 | C39: COBERTURAS | G39: =+G40 -> 517674.47
B40: OE.3.6.7 | C40: RECUBRIMIENTOS SOBRE ESTRUCTURAS DE MADERA, METAL, ETC. | G40: =SUM(G41) -> 517674.47
B41: OE.3.6.7.7 | C41: Cobertura con termopaneles acusticos | D41: m2 | E41: 2538.74 | F41: 203.91 | G41: =+ROUND(E41*F41,2) -> 517674.47
B42: OE.3.7 | C42: CARPINTERIA DE MADERA | G42: =+G43+G60 -> 175630.01
B43: OE.3.7.1 | C43: PUERTAS | G43: =SUM(G44:G59) -> 145106.03
B44: OE.3.7.1.7 | C44: Puerta de 2 hojas vaiven contraplacada con plancha de acero (P-02) 1.40X2.70 m | D44: und | E44: 1 | F44: 1840.92 | G44: =+ROUND(E44*F44,2) -> 1840.92
B45: OE.3.7.1.8 | C45: Puerta de 2 hojas contraplacada (P-03) 1.80X2.70 m, según detalle | D45: und | E45: 1 | F45: 2325.92 | G45: =+ROUND(E45*F45,2) -> 2325.92
B46: OE.3.7.1.9 | C46: Puerta de 1 hoja contraplacada (P-05) 1.20X2.70 m, según detalle | D46: und | E46: 1 | F46: 1123.61 | G46: =+ROUND(E46*F46,2) -> 1123.61
B47: OE.3.7.1.10 | C47: Puerta de 1 hoja contraplacada (P-06) 1.20X2.70 m, según detalle | D47: und | E47: 7 | F47: 1123.61 | G47: =+ROUND(E47*F47,2) -> 7865.27
B48: OE.3.7.1.11 | C48: Puerta de 2 hojas vaiven contraplacada con plancha de acero (P-07) 1.80X2.70 m | D48: und | E48: 3 | F48: 2325.92 | G48: =+ROUND(E48*F48,2) -> 6977.76
B49: OE.3.7.1.12 | C49: Puerta de 1 hoja contraplacada (P-08) 0.90X2.70 m, según detalle | D49: und | E49: 7 | F49: 866.61 | G49: =+ROUND(E49*F49,2) -> 6066.27
B50: OE.3.7.1.13 | C50: Puerta de 1 hoja contraplacada (P-09) 0.90X2.70 m, según detalle | D50: und | E50: 4 | F50: 866.61 | G50: =+ROUND(E50*F50,2) -> 3466.44
B51: OE.3.7.1.14 | C51: Puerta de 1 hoja contraplacada con plancha de acero (P-10) 1.20X2.70 m, según detalle | D51: und | E51: 11 | F51: 1323.61 | G51: =+ROUND(E51*F51,2) -> 14559.71
B52: OE.3.7.1.15 | C52: Puerta de 1 hoja contraplacada (P-11) 0.80X2.70 m, según detalle | D52: und | E52: 20 | F52: 773.61 | G52: =+ROUND(E52*F52,2) -> 15472.2
B53: OE.3.7.1.16 | C53: Puerta de 1 hoja contraplacada (P-12) 1.00X2.70 m, según detalle | D53: und | E53: 24 | F53: 1030.61 | G53: =+ROUND(E53*F53,2) -> 24734.64
B54: OE.3.7.1.17 | C54: Puerta de 1 hoja contraplacada (P-13) 1.00X2.70 m, según detalle | D54: und | E54: 37 | F54: 1030.61 | G54: =+ROUND(E54*F54,2) -> 38132.57
B55: OE.3.7.1.18 | C55: Puerta de 1 hoja contraplacada (P-14) 0.90X2.70 m, según detalle | D55: und | E55: 5 | F55: 966.61 | G55: =+ROUND(E55*F55,2) -> 4833.05
... B59: OE.3.7.1.22 | C59: Puerta de 1 hoja contraplacada con alma de plomo (P-04) 1.00X2.15m, según detalle | D59: und | E59: 2 | F59: 3613.85 | G59: =+ROUND(E59*F59,2) -> 7227.7
B60: OE.3.7.2 | C60: MUEBLES DE LABORATORIO Y SIMILARES | G60: =SUM(G61) -> 30523.98
B61: OE.3.7.2.12 | C61: Muebles Bajos de Melamina de 18mm inc. Accesorios | D61: m | E61: 48.47 | F61: 629.75 | G61: =+ROUND(E61*F61,2) -> 30523.98
B62: OE.3.8 | C62: CARPINTERÍA METÁLICA Y HERRERÍA | G62: =+G63+G68+G78+G88+G90 -> 160313.67
B63: OE.3.8.1 | C63: VENTANAS DE FIERRO | G63: =SUM(G64:G67) -> 3361.04
B64: OE. 3.8.1.4 | C64: VENTANA METALICA DE Fe CON MALLA DE ACERO GALVANIZADO. VM-1 (2.84 X 1.00) | D64: und | E64: 1 | F64: 845.26 | G64: =+ROUND(E64*F64,2) -> 845.26
B65: OE. 3.8.1.5 | C65: VENTANA METALICA DE Fe CON MALLA DE ACERO GALVANIZADO. VM-2 (3.09 X 1.00) | D65: und | E65: 1 | F65: 885.26 | G65: =+ROUND(E65*F65,2) -> 885.26
B66: OE. 3.8.1.6 | C66: VENTANA METALICA DE Fe CON MALLA DE ACERO GALVANIZADO. VM-3 (2.50 X 1.00) | D66: und | E66: 1 | F66: 805.26 | G66: =+ROUND(E66*F66,2) -> 805.26
B67: OE. 3.8.1.7 | C67: VENTANA METALICA DE Fe CON MALLA DE ACERO GALVANIZADO. VM-4 (2.60 X 1.00) | D67: und | E67: 1 | F67: 825.26 | G67: =+ROUND(E67*F67,2) -> 825.26
B68: OE.3.8.2 | C68: PUERTA DE FIERRO | G68: =SUM(G69:G77) -> 27164.43
B69: OE. 3.8.2.5 | C69: PUERTA METALICA DE Fe CON PLANCHA METALICA Y MALLA ELECTROSOLDADA PJ-01 ( 1.00 X 2.70) | D69: und | E69: 1 | F69: 2166.87 | G69: =+ROUND(E69*F69,2) -> 2166.87
B70: OE. 3.8.2.6 | C70: PUERTA METALICA DE TUBO CUADRADO DE 2" CON PLANCHA METALICA PJ-02 ( 1.45 X 2.70) | D70: und | E70: 1 | F70: 2436.87 | G70: =+ROUND(E70*F70,2) -> 2436.87
B71: OE. 3.8.2.7 | C71: PUERTA METALICA CON PLANCHA METALICA PJ-03 ( 2.85 X 2.70) | D71: und | E71: 1 | F71: 3227.08 | G71: =+ROUND(E71*F71,2) -> 3227.08
B72: OE. 3.8.2.8 | C72: PUERTA METALICA CON PLANCHA METALICA PJ-04 ( 3.06 X 2.90) | D72: und | E72: 1 | F72: 3847.89 | G72: =+ROUND(E72*F72,2) -> 3847.89
B73: OE. 3.8.2.9 | C73: PUERTA METALICA CON PLANCHA METALICA PJ-05 ( 4.90 X 3.30) | D73: und | E73: 1 | F73: 4151.37 | G73: =+ROUND(E73*F73,2) -> 4151.37
B74: OE. 3.8.2.10 | C74: PUERTA METALICA CORREDIZA CON MALLA ELECTROSOLDADA PJ-06 ( 1.25 X 2.70) | D74: und | E74: 1 | F74: 2166.87 | G74: =+ROUND(E74*F74,2) -> 2166.87
B75: OE. 3.8.2.11 | C75: PUERTA METALICA CON MALLA ELECTROSOLDADA Y PLANCHA METALICA PJ-07 ( 1.00 X 1.80) | D75: und | E75: 2 | F75: 2036.87 | G75: =+ROUND(E75*F75,2) -> 4073.74
B76: OE. 3.8.2.12 | C76: PUERTA METALICA PJ-08 ( 1.40 X 2.90) | D76: und | E76: 1 | F76: 2426.87 | G76: =+ROUND(E76*F76,2) -> 2426.87
B77: OE. 3.8.2.13 | C77: PUERTA METALICA PJ-09 ( 1.94 X 2.90) | D77: und | E77: 1 | F77: 2666.87 | G77: =+ROUND(E77*F77,2) -> 2666.87
B78: OE.3.8.4 | C78: VENTANA DE ALUMINIO | G78: =SUM(G79:G87) -> 70444.17
B79: OE.3.8.4.2 | C79: VENTANA DE ALUMINIO SISTEMA PROYECTANTE CON VIDRIO LAMINADO DE 6MM. V-1 (0.50 X 0.70) SUMINISTRO E INSTALACION | D79: und | E79: 7 | F79: 206.96 | G79: =+ROUND(E79*F79,2) -> 1448.72
B80: OE.3.8.4.3 | C80: VENTANA DE ALUMINIO SISTEMA PROYECTANTE CON VIDRIO LAMINADO DE 6MM. V-2 (0.45 X 0.70) SUMINISTRO E INSTALACION | D80: und | E80: 1 | F80: 186.56 | G80: =+ROUND(E80*F80,2) -> 186.56
B81: OE.3.8.4.4 | C81: VENTANA DE ALUMINIO SISTEMA PROYECTANTE CON VIDRIO LAMINADO DE 6MM. V-3 (0.70 X 0.70) SUMINISTRO E INSTALACION | D81: und | E81: 45 | F81: 241.31 | G81: =+ROUND(E81*F81,2) -> 10858.95
B82: OE.3.8.4.5 | C82: VENTANA DE ALUMINIO SISTEMA PROYECTANTE CON VIDRIO LAMINADO DE 6MM PAVONADO. V-3b (0.70 X 0.70) SUMINISTRO E INSTALACION | D82: und | E82: 6 | F82: 251.31 | G82: =+ROUND(E82*F82,2) -> 1507.86
B83: OE.3.8.4.6 | C83: VENTANA DE ALUMINIO SISTEMA CORREDERAS CON VIDRIO LAMINADO DE 6MM. V-4 (0.60 X 1.80) SUMINISTRO E INSTALACION | D83: und | E83: 1 | F83: 364.96 | G83: =+ROUND(E83*F83,2) -> 364.96
B84: OE.3.8.4.7 | C84: VENTANA DE ALUMINIO SISTEMA CORREDERAS CON VIDRIO LAMINADO DE 6MM. V-5 (1.00 X 1.80) SUMINISTRO E INSTALACION | D84: und | E84: 65 | F84: 556.96 | G84: =+ROUND(E84*F84,2) -> 36202.4
B85: OE.3.8.4.8 | C85: VENTANA DE ALUMINIO SISTEMA CORREDERAS CON VIDRIO LAMINADO DE 6MM. V-6 (1.20 X 1.80) SUMINISTRO E INSTALACION | D85: und | E85: 22 | F85: 652.96 | G85: =+ROUND(E85*F85,2) -> 14365.12
B86: OE.3.8.4.9 | C86: VENTANA DE ALUMINIO SISTEMA CORREDERAS CON VIDRIO LAMINADO DE 6MM. V-8 (0.70 X 1.80) SUMINISTRO E INSTALACION | D86: und | E86: 2 | F86: 526.96 | G86: =+ROUND(E86*F86,2) -> 1053.92
B87: OE.3.8.4.10 | C87: VENTANA DE ALUMINIO SISTEMA CORREDERAS CON VIDRIO LAMINADO DE 6MM. V-9 (1.00 X 1.80) SUMINISTRO E INSTALACION | D87: und | E87: 8 | F87: 556.96 | G87: =+ROUND(E87*F87,2) -> 4455.68
B88: OE.3.8.14 | C88: BARANDA METALICA | G88: =SUM(G89) -> 45657.6
B89: OE.3.8.14.2 | C89: Baranda metalica, H=1.00m. según diseño | D89: m | E89: 84.25 | F89: 541.93 | G89: =+ROUND(E89*F89,2) -> 45657.6
B90: OE.3.8.18 | C90: ELEMENTOS METALICOS ESPECIALES | G90: =SUM(G91:G94) -> 13686.43
B91: OE.3.8.18.2 | C91: Protector de camillas | D91: m | E91: 33 | F91: 111.54 | G91: =+ROUND(E91*F91,2) -> 3680.82
B92: OE.3.8.18.3 | C92: Burlete adhesivo para puertas | D92: m | E92: 130 | F92: 49.79 | G92: =+ROUND(E92*F92,2) -> 6472.7
B93: OE.3.8.18.4 | C93: Escalera de gato de fierro, según diseño | D93: und | E93: 2 | F93: 712.16 | G93: =+ROUND(E93*F93,2) -> 1424.32
B94: OE.3.8.18.5 | C94: Tapajunta de acero galvanizado en pisos y muros | D94: m | E94: 35.6 | F94: 59.23 | G94: =+ROUND(E94*F94,2) -> 2108.59
B95: OE.3.9 | C95: CERRAJERIA | G95: =+G96+G98 -> 26194.78
B96: OE.3.9.1 | C96: BISAGRAS | G96: =SUM(G97) -> 8192.88
B97: OE.3.9.1.3 | C97: Bisagra vaiven de acero grado 2 satinadas | D97: und | E97: 36 | F97: 227.58 | G97: =+ROUND(E97*F97,2) -> 8192.88
B98: OE.3.9.2 | C98: CERRADURAS | G98: =SUM(G99:G101) -> 18001.9
B99: OE.3.9.2.6 | C99: Cerradura embutida tipo palanca | D99: und | E99: 38 | F99: 123.94 | G99: =+ROUND(E99*F99,2) -> 4709.72
B100: OE.3.9.2.7 | C100: Cerradura embutida tipo pomo | D100: und | E100: 87 | F100: 133.94 | G100: =+ROUND(E100*F100,2) -> 11652.78
B101: OE.3.9.2.8 | C101: Cerradura de tres golpes | D101: und | E101: 10 | F101: 163.94 | G101: =+ROUND(E101*F101,2) -> 1639.4
B102: OE.3.11 | C102: PINTURA | G102: =+G103 -> 41484.8
B103: OE.3.11.1 | C103: PINTURA DE CIELOS RASOS, VIGAS, COLUMNAS Y PAREDES | G103: =SUM(G104:G106) -> 41484.8
B104: OE.3.11.1.8 | C104: Pintura en marcos de madera, 02 manos | D104: m2 | E104: 336.76 | F104: 35.98 | G104: =+ROUND(E104*F104,2) -> 12116.62
B105: OE.3.11.1.9 | C105: Pintura en puertas de madera, 02 manos | D105: m2 | E105: 702.64 | F105: 32.04 | G105: =+ROUND(E105*F105,2) -> 22512.59
B106: OE.3.11.1.10 | C106: Pintura en sardineles 02 manos | D106: m2 | E106: 266.34 | F106: 25.74 | G106: =+ROUND(E106*F106,2) -> 6855.59
B107: OE.3.13 | C107: OTROS | G107: =+G108 -> 15046.09
B108: OE.3.13.6 | C108: MESAS DE CONCRETO | G108: =SUM(G109:G110) -> 15046.09
B109: OE.3.13.6.1 | C109: Mesa de concreto e=0.10 | D109: m2 | E109: 39.43 | F109: 310.43 | G109: =+ROUND(E109*F109,2) -> 12240.25
...

Sheet DD-3
B1: |
B5: UNIDAD EJECUTORA | C5: : GERENCIA REGIONAL DE GESTION DE INVERSIONES DE INFRAESTRUCTURA - GOBIERNO REGIONAL CUSCO (SEDE CENTRAL)
B6: OBRA | C6: : MEJORAMIENTO Y AMPLIACION DE LOS SERVICIOS DE SALUD DEL ESTABLECIMIENTO DE SALUD DE BELEMPAMPA - DISTRITO DE SANTIAGO - PROVINCIA DE CUSCO - REGION CUSCO
B7: META | C7: : 0119-2025
B9: PARTIDAS DEDUCTIVOS N°3
B11: Item | C11: DESCRIPCION | D11: Und | E11: Metrado | F11: PU | G11: Parcial
B13: OE.1 | C13: OBRAS PROVISIONALES, TRABAJOS PRELIMINARES, SEGURIDAD Y SALUD. | G13: =+G14 -> 10500
B14: OE.1.1 | C14: OBRAS PROVISIONALES Y TRABAJOS PRELIMINARES | G14: =SUM(G15:G16) -> 10500
B15: OE.1.2.3 | C15: PLAN PARA LA VIGILANCIA PREVENCION Y CONTROL DE COVID EN EL TRABAJO
B16: OE.1.2.3.5 | C16: Servicio de Pruebas COVID - 19 | D16: und | E16: 60 | F16: 175 | G16: =+ROUND(+IF(E16="",0,E16*F16),2) -> 10500
B17: OE.2 | C17: ESTRUCTURAS. | G17: =+G18+G21+G25 -> 68180.18
B18: OE.2.1 | C18: MOVIMIENTO DE TIERRAS | G18: =SUM(G19:G20) -> 5535.71
B19: OE.2.1.1 | C19: EXCAVACIONES MASIVA
B20: OE.2.1.1.1 | C20: Excavacion con maquinaria | D20: m3 | E20: 1177.81 | F20: 4.7 | G20: =+ROUND(+IF(E20="",0,E20*F20),2) -> 5535.71
B21: OE.2.3 | C21: OBRAS DE CONCRETO ARMADO | G21: =SUM(G22:G24) -> 7759.7
B22: OE.2.3.12 | C22: CISTERNA
B23: OE.2.3.12.1 | C23: Cisternas -Concreto f´c=280kg/cm2 | D23: m3 | E23: 4.13 | F23: 661.41 | G23: =+ROUND(+IF(E23="",0,E23*F23),2) -> 2731.62
B24: OE.2.3.12.3 | C24: Cisternas -Acero fy=4200 kg/cm2 | D24: kg | E24: 700.29 | F24: 7.18 | G24: =+ROUND(+IF(E24="",0,E24*F24),2) -> 5028.08
B25: OE.2.6 | C25: VARIOS | G25: =SUM(G26:G33) -> 54884.77
B26: OE.2.6.1 | C26: ARRIOSTRAMIENTO METALICO
B27: OE.2.6.1.1 | C27: Arriostramiento metalico | D27: kg | E27: 3828.99 | F27: 12.24 | G27: =+ROUND(+IF(E27="",0,E27*F27),2) -> 46866.84
B28: OE.2.6.3 | C28: ARRIOSTRES DEL TECHO
B29: OE.2.6.3.1 | C29: Acero Ø 1/2" LISO | D29: m | E29: 492.2 | F29: 9.3 | G29: =+ROUND(+IF(E29="",0,E29*F29),2) -> 4577.46
B30: OE.2.6.3.2 | C30: Conexión de tirantes L64x64x7.9 | D30: m | E30: 8.67 | F30: 53.06 | G30: =+ROUND(+IF(E30="",0,E30*F30),2) -> 460.03
B31: OE.2.6.3.3 | C31: Angulo 2.5X2.5X3/16" | D31: m | E31: 30.08 | F31: 50.03 | G31: =+ROUND(+IF(E31="",0,E31*F31),2) -> 1504.9
B32: OE.2.6.5 | C32: CONTROL DE CALIDAD
B33: OE.2.6.5.1 | C33: Verificación de Capacidad Portante | D33: und | E33: 2 | F33: 737.77 | G33: =+ROUND(+IF(E33="",0,E33*F33),2) -> 1475.54
B34: OE.3 | C34: ARQUITECTURA | G34: =+G35+G38+G41+G49+G55+G75+G92+G101 -> 748266.79
B35: OE.3.1 | C35: MUROS Y TABIQUES DE ALBAÑILERIA | G35: =SUM(G36:G37) -> 33732.16
B36: OE.3.1.10 | C36: MUROS CON EL SISTEMA DE CONSTRUCCIÓN EN SECO (SISTEMA DRY WALL O SIMILAR)
B37: OE.3.1.10.3 | C37: MURO SISTEMA DRYWALL CON LAMINA DE PLOMO e=2mm | D37: m2 | E37: 44.8 | F37: 752.95 | G37: =+ROUND(+IF(E37="",0,E37*F37),2) -> 33732.16
B38: OE.3.3 | C38: CIELORRASOS | G38: =SUM(G39:G40) -> 13206.2
B39: OE.3.3.6 | C39: FALSO CIELO RASO
B40: OE.3.3.6.3 | C40: FALSO CIELO RASO CON PLACA DE SUPERBOARD CON LAMINA DE PLOMO e=2mm | D40: m2 | E40: 18.3 | F40: 721.65 | G40: =+ROUND(+IF(E40="",0,E40*F40),2) -> 13206.2
B41: OE.3.5 | C41: ZOCALOS Y CONTRAZOCALOS | G41: =SUM(G42:G48) -> 73769.41
B42: OE.3.5.1 | C42: ZOCALOS
A43: PN1 | B43: OE.3.5.1.13 | C43: Revestimiento Vinilico Conductivo | D43: m2 | E43: 37.4 | F43: 248.03 | G43: =+ROUND(+IF(E43="",0,E43*F43),2) -> 9276.32
B44: OE.3.5.2 | C44: CONTRAZOCALOS
B45: OE.3.5.2.3 | C45: CONTRAZOCALOS DE CERAMICO
A46: PN1 | B46: OE.3.5.2.3.3 | C46: Contrazocalo de ceramico (H=10cm) | D46: m | E46: 928.53 | F46: 30.45 | G46: =+ROUND(+IF(E46="",0,E46*F46),2) -> 28273.74
B47: OE.3.5.2.11 | C47: OTROS
B48: OE.3.5.2.11.1 | C48: CONTRAZOCALO SANITARIO COVER FORMER H=0.10 M. | D48: m | E48: 1234.47 | F48: 29.34 | G48: =+ROUND(+IF(E48="",0,E48*F48),2) -> 36219.35
B49: OE.3.6 | C49: COBERTURAS | G49: =SUM(G50:G54) -> 545413.86
B50: OE.3.6.7 | C50: RECUBRIMIENTOS SOBRE ESTRUCTURAS DE MADERA, METAL, ETC.
B51: OE.3.6.7.4 | C51: Cobertura con panel termoacústico relleno de poliuretano | D51: m2 | E51: 1789.7 | F51: 278.26 | G51: =+ROUND(+IF(E51="",0,E51*F51),2) -> 498001.92
B52: OE.3.6.7.6 | C52: Cobertura con policarbonato e=10 mm | D52: m2 | E52: 326.98 | F52: 77.06 | G52: =+ROUND(+IF(E52="",0,E52*F52),2) -> 25197.08
B53: OE.3.6.9 | C53: OTROS
B54: OE.3.6.9.2 | C54: Cerramiento con policarbonato e=10 mm | D54: m2 | E54: 361.57 | F54: 61.44 | G54: =+ROUND(+IF(E54="",0,E54*F54),2) -> 22214.86
B55: OE.3.7 | C55: CARPINTERIA DE MADERA | G55: =SUM(G56:G74) -> 58022.3
B56: OE.3.7.1 | C56: PUERTAS
B57: OE.3.7.1.1 | C57: PUERTA DE MDF CONTRAPLACADA DE 6 mm. DE 01 HOJA RECUBIERTA CON | D57: und | E57: 1 | F57: 2278.11 | G57: =+ROUND(+IF(E57="",0,E57*F57),2) -> 2278.11
B58: OE.3.7.1.2 | C58: FORMICA BLANCA, MARCOS CON BARNIZ INCOLORO; PLANCHAS DE METAL Y REJILLA DE VENTILACION EN LA PARTE INFERIOR. TIPO P-7 (1.00 x 2.20) CORREDIZAPUERTA DE MDF CONTRAPLACADA DE 6 mm. DE 01 HOJA RECUBIERTA CON FORMICA BLANCA, MARCOS CON BARNIZ INCOLORO; PLANCHAS DE METAL Y REJILLA DE VENTILACION EN LA PARTE INFERIORA TIPO P-8 (1.05 x 2.20) DOBLE CORREDIZA | D58: und | E58: 3 | F58: 2392 | G58: =+ROUND(+IF(E58="",0,E58*F58),2) -> 7176
B59: OE.3.7.1.3 | C59: PUERTA DE MDF CONTRAPLACADA DE 6 mm. DE 01 HOJA RECUBIERTA CONFORMICA BLANCA, MARCOS CON BARNIZ INCOLORO. TIPO P-11 (1.05 x 2.20) | D59: und | E59: 7 | F59: 2358.17 | G59: =+ROUND(+IF(E59="",0,E59*F59),2) -> 16507.19
B60: OE.3.7.1.4 | C60: PUERTA DE MDF CONTRAPLACADA DE 6 mm. DE 01 HOJA RECUBIERTA CON FORMICA BLANCA, MARCOS CON BARNIZ INCOLORO. TIPO P-12 (0.85 x 2.20) | D60: und | E60: 2 | F60: 1988.94 | G60: =+ROUND(+IF(E60="",0,E60*F60),2) -> 3977.88
B61: OE.3.7.1.5 | C61: PUERTA DE MADERA CONTRAPLACADA CON PROTECCION DE LAMINAS DE PLOMO DE 01 HOJA RECUBIERTA CON FORMICA BLANCA. TIPO P-14 (1.05 x 2.20) | D61: und | E61: 2 | F61: 1980 | G61: =+ROUND(+IF(E61="",0,E61*F61),2) -> 3960
B62: OE.3.7.1.6 | C62: PUERTA DE MADERA CONTRAPLACADA CON PROTECCION DE LAMINAS DE PLOMO DE 01 HOJA RECUBIERTA CON FORMICA BLANCA. TIPO P-15 (0.85 x 2.20) | D62: und | E62: 1 | F62: 1700 | G62: =+ROUND(+IF(E62="",0,E62*F62),2) -> 1700
B63: OE.3.7.2 | C63: MUEBLES DE LABORATORIO Y SIMILARES
B64: OE.3.7.2.1 | C64: MUEBLE TIPO 01 ADMISION - CITAS - INFORMES | D64: und | E64: 3 | F64: 740 | G64: =+ROUND(+IF(E64="",0,E64*F64),2) -> 2220
B65: OE.3.7.2.2 | C65: MUEBLE TIPO 02 ENTREGA Y RECEPCION | D65: und | E65: 3 | F65: 59 | G65: =+ROUND(+IF(E65="",0,E65*F65),2) -> 177
B66: OE.3.7.2.3 | C66: MUEBLE TIPO 03 ESTACION DE ENFERMERAS | D66: und | E66: 2 | F66: 663.5 | G66: =+ROUND(+IF(E66="",0,E66*F66),2) -> 1327
B67: OE.3.7.2.4 | C67: MUEBLE TIPO 04 TOMA DE MUESTRAS | D67: und | E67: 1 | F67: 560 | G67: =+ROUND(+IF(E67="",0,E67*F67),2) -> 560
B68: OE.3.7.2.5 | C68: MUEBLE TIPO 05 TRABAJOS LIMPIO - SUCIO | D68: und | E68: 2 | F68: 540 | G68: =+ROUND(+IF(E68="",0,E68*F68),2) -> 1080
B69: OE.3.7.2.6 | C69: MUEBLE TIPO 06 ESTAR DE PERSONAL | D69: und | E69: 2 | F69: 525.01 | G69: =+ROUND(+IF(E69="",0,E69*F69),2) -> 1050.02
B70: OE.3.7.2.7 | C70: MUEBLE TIPO 07 ESTERILIZACION | D70: und | E70: 1 | F70: 3575 | G70: =+ROUND(+IF(E70="",0,E70*F70),2) -> 3575
B71: OE.3.7.2.8 | C71: MUEBLE TIPO 08 LIMPIEZA | D71: und | E71: 1 | F71: 438 | G71: =+ROUND(+IF(E71="",0,E71*F71),2) -> 438
B72: OE.3.7.2.9 | C72: MUEBLE TIPO 09 LABORATORIO | D72: und | E72: 3 | F72: 1922 | G72: =+ROUND(+IF(E72="",0,E72*F72),2) -> 5766
B73: OE.3.7.2.10 | C73: MUEBLE TIPO 10 CONSULTORIOS Y TOPICO ATENCION RECIEN NACIDO | D73: und | E73: 10 | F73: 570.01 | G73: =+ROUND(+IF(E73="",0,E73*F73),2) -> 5700.1
B74: OE.3.7.2.11 | C74: MUEBLE TIPO 11 LAVADO DE PERSONAL ASISTENCIAL | D74: und | E74: 1 | F74: 530 | G74: =+ROUND(+IF(E74="",0,E74*F74),2) -> 530
B75: OE.3.8 | C75: CARPINTERÍA METÁLICA Y HERRERÍA | G75: =SUM(G76:G91) -> 19564.47
B76: OE.3.8.1 | C76: VENTANAS DE FIERRO
B77: OE. 3.8.1.1 | C77: VENTANA ALTA FIJA PERFILES DE Fe 2" x 1 1/2 y/o MALLA DE ACERO GALVANIZADO. V-2 (2.45 X 1.23) | D77: und | E77: 1 | F77: 615.79 | G77: =+ROUND(+IF(E77="",0,E77*F77),2) -> 615.79
B78: OE. 3.8.1.2 | C78: VENTANA ALTA FIJA PERFILES DE Fe 2" x 1 1/2 y/o MALLA DE ACERO GALVANIZADO. V-3 (2.15 X 1.23) | D78: und | E78: 1 | F78: 500 | G78: =+ROUND(+IF(E78="",0,E78*F78),2) -> 500
B79: OE. 3.8.1.3 | C79: VENTANA ALTA FIJA PERFILES DE Fe 2" x 1 1/2 y/o MALLA DE ACERO GALVANIZADO. V-4 (5.40 X 1.23) | D79: und | E79: 1 | F79: 1000 | G79: =+ROUND(+IF(E79="",0,E79*F79),2) -> 1000
B80: OE.3.8.2 | C80: PUERTA DE FIERRO
B81: OE. 3.8.2.1 | C81: PUERTA METALICA TIPO PJ-01 (3.20 X 2.80M) DOBLE HOJA | D81: und | E81: 1 | F81: 2920 | G81: =+ROUND(+IF(E81="",0,E81*F81),2) -> 2920
B82: OE. 3.8.2.2 | C82: PUERTA METALICA TIPO PJ-02 (1.30 X 2.80M) UNA HOJA | D82: und | E82: 3 | F82: 998 | G82: =+ROUND(+IF(E82="",0,E82*F82),2) -> 2994
B83: OE. 3.8.2.3 | C83: PUERTA METALICA TIPO REJA DE DOBLE HOJA CON TUBO CUADRADO DE 2" x 2" e= 1 mm. P-9 ( 2.40 X 2.80) | D83: und | E83: 2 | F83: 1120 | G83: =+ROUND(+IF(E83="",0,E83*F83),2) -> 2240
B84: OE. 3.8.2.4 | C84: PUERTA METALICA TIPO REJA DE DOBLE HOJA CON TUBO CUADRADO DE 2" x 2" e= 1 mm. P-10 ( 1.40 X 2.80) | D84: und | E84: 1 | F84: 1120 | G84: =+ROUND(+IF(E84="",0,E84*F84),2) -> 1120
B85: OE.3.8.4 | C85: VENTANA DE ALUMINIO
B86: OE.3.8.4.1 | C86: VENTANA DE ALUMINIO SISTEMA CORREDERAS CON VIDRIO TEMPLADO DE 6MM. INCOLORO V-5 (1.00 X 1.00) | D86: und | E86: 12 | F86: 100.61 | G86: =+ROUND(+IF(E86="",0,E86*F86),2) -> 1207.32
B87: OE.3.8.5 | C87: PUERTAS DE ALUMINIO
B88: OE.3.8.5.1 | C88: PUERTA DE MELAMINE CON MARCOS DE ALUMINIO DE 01 HOJA,COLOR CLARO.P-6 (0.65 x 2.00) | D88: und | E88: 10 | F88: 235 | G88: =+ROUND(+IF(E88="",0,E88*F88),2) -> 2350
B89: OE.3.8.15 | C89: PASAMANOS AISLADOS | H89: X
B90: OE.3.8.15.1 | C90: AGARRADERA PARA MINUSVALIDOS EN SSHH; Ø 2" L=0.60M. | D90: und | E90: 18 | F90: 103.24 | G90: =+ROUND(+IF(E90="",0,E90*F90),2) -> 1858.32
B91: OE.3.8.15.2 | C91: AGARRADERA PARA MINUSVALIDOS EN SSHH; Ø 2" L=0.90M. | D91: und | E91: 18 | F91: 153.28 | G91: =+ROUND(+IF(E91="",0,E91*F91),2) -> 2759.04
B92: OE.3.9 | C92: CERRAJERIA | G92: =SUM(G93:G100) -> 3273.39
B93: OE.3.9.2 | C93: CERRADURAS
B94: OE.3.9.2.1 | C94: CERRADURA TIPO A | D94: und | E94: 10 | F94: 135.43 | G94: =+ROUND(+IF(E94="",0,E94*F94),2) -> 1354.3
B95: OE.3.9.2.2 | C95: CERRADURA TIPO G | D95: und | E95: 7 | F95: 100.48 | G95: =+ROUND(+IF(E95="",0,E95*F95),2) -> 703.36
B96: OE.3.9.2.3 | C96: CERRADURA TIPO H | D96: und | E96: 10 | F96: 54.55 | G96: =+ROUND(+IF(E96="",0,E96*F96),2) -> 545.5
B97: OE.3.9.2.4 | C97: CERRADURA TIPO I | D97: und | E97: 4 | F97: 130.45 | G97: =+ROUND(+IF(E97="",0,E97*F97),2) -> 521.8
B98: OE.3.9.2.5 | C98: CERRADURA TIPO J | D98: und | E98: 1 | F98: 93.95 | G98: =+ROUND(+IF(E98="",0,E98*F98),2) -> 93.95
B99: OE.3.9.4 | C99: ACCESORIOS DE CIERRE
B100: OE.3.9.4.1 | C100: TIRADOR DE ACERO INOX. PARA PUERTA DE VIDRIO | D100: und | E100: 2 | F100: 27.24 | G100: =+ROUND(+IF(E100="",0,E100*F100),2) -> 54.48
B101: OE.3.10 | C101: VIDRIOS, CRISTALES Y SIMILARES | G101: =SUM(G102:G103) -> 1285
B102: OE.3.7.1 | C102: PUERTAS
B103: OE.3.10.4.1 | C103: (P-13) PUERTA AUTOPORTANTE DE CRISTAL TEMPLADO 10mm, PUERTA BATIENTE CON CINTA DE SEGURIDAD DE 10 cm DE ANCHO A 1.00 m DE ALTURA (1.95 X 2.20) | D103: und | E103: 1 | F103: 1285 | G103: =+ROUND(+IF(E103="",0,E103*F103),2) -> 1285
B104: OE.4 | C104: INSTALACIONES SANITARIAS | G104: =+G105+G148+G178+G182 -> 60241.45
B105: OE4.1 | C105: APARATOS SANITARIOS Y ACCESORIOS | G105: =SUM(G106:G147) -> 23486.05
B106: OE.4.1.1 | C106: SUMINISTRO DE APARATOS SANITARIOS Y ACCESORIOS
...

Sheet MM-4
B1: |
B5: UNIDAD EJECUTORA | C5: : GERENCIA REGIONAL DE GESTION DE INVERSIONES DE INFRAESTRUCTURA - GOBIERNO REGIONAL CUSCO (SEDE CENTRAL)
B6: OBRA | C6: : MEJORAMIENTO Y AMPLIACION DE LOS SERVICIOS DE SALUD DEL ESTABLECIMIENTO DE SALUD DE BELEMPAMPA - DISTRITO DE SANTIAGO - PROVINCIA DE CUSCO - REGION CUSCO
B7: META | C7: : 0119-2025
B9: PARTIDAS MAYORES METRADOS N°04
B11: Item | C11: DESCRIPCION | D11: Und | E11: Metrado | F11: PU | G11: Parcial
B12: OE.1 | C12: OBRAS PROVISIONALES, TRABAJOS PRELIMINARES, SEGURIDAD Y SALUD. | G12: =+G13 -> 1047034.9
B13: OE.1.1 | C13: OBRAS PROVISIONALES Y TRABAJOS PRELIMINARES | G13: =+G14+G21+G24+G31 -> 1047034.9
B14: OE.1.1.1 | C14: CONSTRUCCIONES PROVISIONALES | G14: =SUM(G15:G20) -> 755277.07
B15: OE.1.1.1.1 | C15: Oficinas | D15: m² | E15: 800 | F15: 157.37 | G15: =+ROUND(E15*F15,2) -> 125896
B16: OE.1.1.1.2 | C16: Almacenes | D16: m² | E16: 4148.09 | F16: 109.44 | G16: =+ROUND(E16*F16,2) -> 453966.97
B17: OE.1.1.1.3 | C17: Casetas de guardianÍa | D17: m² | E17: =28.79+12.27 -> 41.06 | F17: 147.84 | G17: =+ROUND(E17*F17,2) -> 6070.31
B18: OE.1.1.1.5 | C18: Vestuarios | D18: m² | E18: 680 | F18: 130.85 | G18: =+ROUND(E18*F18,2) -> 88978
B19: OE.1.1.1.6 | C19: Servicios higienicos | D19: m² | E19: 96 | F19: 282.01 | G19: =+ROUND(E19*F19,2) -> 27072.96
B20: OE.1.1.1.7 | C20: Cercos Provisional de calamina | D20: m | E20: =924.78+73.4 -> 998.18 | F20: 53.39 | G20: =+ROUND(E20*F20,2) -> 53292.83
B21: OE.1.1.4 | C21: ELIMINACION DE OBSTRUCCIONES | G21: =SUM(G22:G23) -> 1109.09
B22: OE.1.1.4.1 | C22: Tala de Arboles | D22: und | E22: 5 | F22: 17.72 | G22: =+ROUND(E22*F22,2) -> 88.6
B23: OE.1.1.4.2 | C23: Eliminación de Raices | D23: und | E23: 41 | F23: 24.89 | G23: =+ROUND(E23*F23,2) -> 1020.49
B24: OE.1.1.5 | C24: REMOCIONES | G24: =SUM(G25:G30) -> 10412.53
B25: OE.1.1.5.1 | C25: Remoción de Puertas | D25: und | E25: 39 | F25: 23.64 | G25: =+ROUND(E25*F25,2) -> 921.96
B26: OE.1.1.5.2 | C26: Remoción de Ventanas | D26: und | E26: 39 | F26: 23.64 | G26: =+ROUND(E26*F26,2) -> 921.96
B27: OE.1.1.5.3 | C27: Remoción de Aparatos Sanitarios | D27: und | E27: 3 | F27: 25.21 | G27: =+ROUND(E27*F27,2) -> 75.63
B28: OE.1.1.5.4 | C28: Remoción de Tijerales de madera | D28: und | E28: 80 | F28: 47.28 | G28: =+ROUND(E28*F28,2) -> 3782.4
B29: OE.1.1.5.5 | C29: Remoción de Cobertura | D29: m² | E29: 728.8 | F29: 4.73 | G29: =+ROUND(E29*F29,2) -> 3447.22
B30: OE.1.1.5.6 | C30: Remoción de Estructuras Metálicas | D30: m² | E30: 376 | F30: 3.36 | G30: =+ROUND(E30*F30,2) -> 1263.36
B31: OE.1.1.6 | C31: DEMOLICIONES | G31: =SUM(G32:G36) -> 280236.21
B32: OE.1.1.6.1 | C32: Demolicion de muros de ladrillo incluye cimentaciones | D32: m³ | E32: 403 | F32: 19.99 | G32: =+ROUND(E32*F32,2) -> 8055.97
B33: OE.1.1.6.2 | C33: Demolicion de muros de adobe incluye cimentaciones | D33: m³ | E33: 75.07 | F33: 63.64 | G33: =+ROUND(E33*F33,2) -> 4777.45
B34: OE.1.1.6.3 | C34: Demolicion de Pisos y falso pisos - Manual | D34: m³ | E34: 345.65 | F34: 173.49 | G34: =+ROUND(E34*F34,2) -> 59966.82
B35: OE.1.1.6.4 | C35: DEMOLICIONES DE MUROS DE CONTENCION DE PIEDRA INC. CIMENTACIONES | D35: m² | E35: 1250 | F35: 16.77 | G35: =+ROUND(E35*F35,2) -> 20962.5
B36: OE.1.1.6.5 | C36: Eliminación de Demoliciones | D36: m³ | E36: 1964.74 | F36: 94.91 | G36: =+ROUND(E36*F36,2) -> 186473.47
B37: OE.2 | C37: ESTRUCTURAS. | G37: =+G38 -> 12460
B38: OE.2.6 | C38: VARIOS | G38: =+G39 -> 12460
B39: OE.2.6.2 | C39: PRUEBAS DE CONTROL DE CALIDAD | G39: =SUM(G40) -> 12460
B40: OE.2.6.2.3 | C40: Ensayos de Compactación de Suelos | D40: und | E40: 178 | F40: 70 | G40: =+ROUND(E40*F40,2) -> 12460
B41: OE.4 | C41: INSTALACIONES SANITARIAS | G41: =+G42 -> 47901.19
B42: OE.4.9 | C42: SISTEMA DE SUBDRENAJE | G42: =SUM(G43:G46) -> 47901.19
B43: OE.4.9.1 | C43: TRAZO Y REPLANTEO | D43: m | E43: 477.22 | F43: 2.59 | G43: =+ROUND(E43*F43,2) -> 1236
B44: OE.4.9.5 | C44: RELLENO CON GRAVA DE 3/4" | D44: m³ | E44: =257.7+7.84 -> 265.54 | F44: 88.21 | G44: =+ROUND(E44*F44,2) -> 23423.28
B45: OE.4.9.9 | C45: GEOTEXTIL NO TEJIDO PARA SUBDREN | D45: m² | E45: =1813.44+67.48 -> 1880.92 | F45: 6.3 | G45: =+ROUND(E45*F45,2) -> 11849.8
B46: OE.4.9.10 | C46: TUBERÍA PVC C-10 Ø6" (CON 02 PERFORACIONES DE 8MM@0.10M) | D46: m | E46: =403.15+21.77 -> 424.92 | F46: 26.81 | G46: =+ROUND(E46*F46,2) -> 11392.11
B47: TOTAL COSTO DIRECTO PARTIDAS MAYORES METRADOS N°4 | G47: =G37+G12+G41 -> 1107396.1

Sheet PN-4
B1: |
B5: UNIDAD EJECUTORA | C5: : GERENCIA REGIONAL DE GESTION DE INVERSIONES DE INFRAESTRUCTURA - GOBIERNO REGIONAL CUSCO (SEDE CENTRAL)
B6: OBRA | C6: : MEJORAMIENTO Y AMPLIACION DE LOS SERVICIOS DE SALUD DEL ESTABLECIMIENTO DE SALUD DE BELEMPAMPA - DISTRITO DE SANTIAGO - PROVINCIA DE CUSCO - REGION CUSCO
B7: META | C7: : 0119-2025
B9: PARTIDAS NUEVAS N°04
B11: Item | C11: DESCRIPCION | D11: Und | E11: Metrado | F11: PU | G11: Parcial
B12: OE.1 | C12: OBRAS PROVISIONALES, TRABAJOS PRELIMINARES, SEGURIDAD Y SALUD. | G12: =+G13+G45+G61+G96 -> 5505231.7
B13: OE.1.1 | C13: OBRAS PROVISIONALES Y TRABAJOS PRELIMINARES | G13: =+G14+G32+G38+G42 -> 5085167.6
B14: OE.1.1.1 | C14: CONSTRUCCIONES PROVISIONALES | G14: =SUM(G15:G31) -> 2951134.7
B15: OE.1.1.1.10 | C15: Traslado de material en desuso de Belempampa a Coripata y Antonio Lorena (D=750m) | D15: kg | E15: 110000 | F15: 0.13 | G15: =+ROUND(+IF(E15="",0,E15*F15),2) -> 14300
B16: OE.1.1.1.11 | C16: Traslado de materiales de Belempampa a almacén Huancaro (D=1800m) | D16: kg | E16: 2026138.6 | F16: 0.3 | G16: =+ROUND(+IF(E16="",0,E16*F16),2) -> 607841.59
B17: OE.1.1.1.12 | C17: Desmontaje y traslado de módulos prefabricados | D17: und | E17: 7 | F17: 1723.87 | G17: =+ROUND(+IF(E17="",0,E17*F17),2) -> 12067.09
B18: OE.1.1.1.13 | C18: Reubicación manual de material en obra D=300 m-Kilogramos | D18: kg | E18: 1384372.7 | F18: 0.74 | G18: =+ROUND(+IF(E18="",0,E18*F18),2) -> 1024435.8
B19: OE.1.1.1.14 | C19: Reubicación de material en obra manual D=300 m-metros cúbicos | D19: m³ | E19: 1810 | F19: 66.7 | G19: =+ROUND(+IF(E19="",0,E19*F19),2) -> 120727
B20: OE.1.1.1.15 | C20: Traslado de material con maquinaria de almacén Huancaro a Belempampa- en Kilogramos (D=1800m) | D20: kg | E20: 1592658.6 | F20: 0.17 | G20: =+ROUND(+IF(E20="",0,E20*F20),2) -> 270751.97
B21: OE.1.1.1.16 | C21: Traslado de material con maquinaria de almacén Huancaro a Belempampa-15M3 por viaje (D=1800m) | D21: vje | E21: 153 | F21: 681.84 | G21: =+ROUND(+IF(E21="",0,E21*F21),2) -> 104321.52
B22: OE.1.1.1.17 | C22: Reposición y mantenimiento de áreas colindantes | D22: m | E22: 30 | F22: 174.3 | G22: =+ROUND(+IF(E22="",0,E22*F22),2) -> 5229
B23: OE.1.1.1.18 | C23: Orden y limpieza permanente en obra | D23: mes | E23: 24 | F23: 13422.3 | G23: =+ROUND(+IF(E23="",0,E23*F23),2) -> 322135.2
B24: OE.1.1.1.19 | C24: Desmontaje de oficinas y almacenes | D24: m² | E24: 480 | F24: 54.74 | G24: =+ROUND(+IF(E24="",0,E24*F24),2) -> 26275.2
B25: OE.1.1.1.20 | C25: Almacén de estructura metálica | D25: m² | E25: 540 | F25: 486.01 | G25: =+ROUND(+IF(E25="",0,E25*F25),2) -> 262445.4
B26: OE.1.1.1.21 | C26: Embalado de materiales de almacén para traslado | D26: kg | E26: 282088.64 | F26: 0.34 | G26: =+ROUND(+IF(E26="",0,E26*F26),2) -> 95910.14
... B31: OE.1.1.1.26 | C31: Mantenimiento de andamios y estructuras metálicas | D31: und | E31: 30 | F31: 242.96 | G31: =+ROUND(+IF(E31="",0,E31*F31),2) -> 7288.8
B32: OE.1.1.2 | C32: INSTALACIONES PROVISIONALES | G32: =SUM(G33:G37) -> 213375.8
B33: OE.1.1.2.1 | C33: AGUA PARA LA CONSTRUCCIÓN
B34: OE.1.1.2.1.2 | C34: Restauración y mantenimiento de instalaciones sanitarias provisionales | D34: mes | E34: 24 | F34: 4945.23 | G34: =+ROUND(+IF(E34="",0,E34*F34),2) -> 118685.52
B35: OE.1.1.2.3 | C35: ENERGÍA ELÉCTRICA PROVISIONAL
B36: OE.1.1.2.3.4 | C36: Desmontaje y reubicación de instalaciones eléctricas provisionales | D36: mes | E36: 24 | F36: 3215.21 | G36: =+ROUND(+IF(E36="",0,E36*F36),2) -> 77165.04
B37: OE.1.1.2.3.5 | C37: Suministro de artefactos de iluminación nocturna en obra | D37: glb | E37: 1 | F37: 17525.24 | G37: =+ROUND(+IF(E37="",0,E37*F37),2) -> 17525.24
B38: OE.1.1.6 | C38: DEMOLICIONES | G38: =SUM(G39:G41) -> 428587.61
B39: OE.1.1.6.6 | C39: Demolición de muros de contención de concreto soterrado | D39: m³ | E39: 500 | F39: 358.1 | G39: =+ROUND(+IF(E39="",0,E39*F39),2) -> 179050
B40: OE.1.1.6.7 | C40: Demolición manual | D40: m³ | E40: 250 | F40: 779.38 | G40: =+ROUND(+IF(E40="",0,E40*F40),2) -> 194845
B41: OE.1.1.6.8 | C41: Demolición de estructuras de concreto armado (losas, vigas, columnas) | D41: m³ | E41: 152.73 | F41: 358.1 | G41: =+ROUND(+IF(E41="",0,E41*F41),2) -> 54692.61
B42: OE.1.1.9 | C42: TRAZOS, NIVELES Y REPLANTEO | G42: =SUM(G43:G44) -> 1492069.4
B43: OE.1.1.9.3 | C43: Establecimiento de punto geodésico Orden C con certificación | D43: und | E43: 2 | F43: 4500 | G43: =+ROUND(+IF(E43="",0,E43*F43),2) -> 9000
B44: OE.1.1.9.4 | C44: Control, trazo y replanteo en Obra | D44: mes | E44: 24 | F44: 61794.56 | G44: =+ROUND(+IF(E44="",0,E44*F44),2) -> 1483069.4
B45: OE.1.3 | C45: PLAN DE MONITOREO ARQUEOLOGICO | G45: =+G46+G49+G51+G55 -> 307557.3
B46: OE.1.3.1 | C46: IMPLEMENTACION PARA TRABAJOS DE MOVIMIENTO DE TIERRA AL NIVEL DE SEGUIMIENTO DEL PEA 2022 | G46: =SUM(G47:G48) -> 18907
B47: OE.1.3.1.1 | C47: Cubiertas para zanjas/movimiento de tierra a nivel de seguimiento | D47: m² | E47: 300 | F47: 50.49 | G47: =+ROUND(+IF(E47="",0,E47*F47),2) -> 15147
B48: OE.1.3.1.2 | C48: Trazado de zanjas para movimiento de tierra a nivel de seguimiento del PEA - 2022 | D48: m² | E48: 250 | F48: 15.04 | G48: =+ROUND(+IF(E48="",0,E48*F48),2) -> 3760
B49: OE.1.3.2 | C49: MOVIMIENTO DE TIERRA A NIVEL DE SEGUIMIENTO DE LAS ESTRUCTURAS DEL PEA 2022 | G49: =SUM(G50) -> 205467.9
B50: OE.1.3.2.1 | C50: Movimiento de tierra a nivel de seguimiento de las estructuras del PEA 2022 | D50: m³ | E50: 290 | F50: 708.51 | G50: =+ROUND(+IF(E50="",0,E50*F50),2) -> 205467.9
B51: OE.1.3.3 | C51: REGISTRO DE ZANJAS/MOVIMIENTO DE TIERRA A NIVEL DE SEGUIMIENTO DE LAS ESTRUCTURAS DEL PEA - 2022 | G51: =SUM(G52:G54) -> 37993.2
B52: OE.1.3.3.1 | C52: Registro grafico de zanjas (ficha de hallazgo, de excavación, arquitectura, diario de campo, ficha de monitoreo) | D52: und | E52: 180 | F52: 51.17 | G52: =+ROUND(+IF(E52="",0,E52*F52),2) -> 9210.6
B53: OE.1.3.3.2 | C53: Dibujo en papel milimétrico | D53: und | E53: 70 | F53: 307.02 | G53: =+ROUND(+IF(E53="",0,E53*F53),2) -> 21491.4
B54: OE.1.3.3.3 | C54: Digitalización en gabinete de fichas levantadas | D54: und | E54: 210 | F54: 34.72 | G54: =+ROUND(+IF(E54="",0,E54*F54),2) -> 7291.2
B55: OE.1.3.4 | C55: PROCESO DE CONSERVACION DE MATERIAL CULTURAL (TRABAJO DE GABINETE) | G55: =SUM(G56:G60) -> 45189.2
B56: OE.1.3.4.1 | C56: Lavado de material cultural | D56: bol | E56: 140 | F56: 63.9 | G56: =+ROUND(+IF(E56="",0,E56*F56),2) -> 8946
B57: OE.1.3.4.2 | C57: Clasificado y análisis de material cultural | D57: bol | E57: 140 | F57: 122.81 | G57: =+ROUND(+IF(E57="",0,E57*F57),2) -> 17193.4
B58: OE.1.3.4.3 | C58: Codificado de material cultural | D58: bol | E58: 140 | F58: 69.45 | G58: =+ROUND(+IF(E58="",0,E58*F58),2) -> 9723
B59: OE.1.3.4.4 | C59: Inventario de material cultural | D59: bol | E59: 140 | F59: 34.72 | G59: =+ROUND(+IF(E59="",0,E59*F59),2) -> 4860.8
B60: OE.1.3.4.5 | C60: Embalado de material cultural | D60: bol | E60: 140 | F60: 31.9 | G60: =+ROUND(+IF(E60="",0,E60*F60),2) -> 4466
B61: OE.1.4 | C61: CONSERVACION PREVENTIVA Y DEFINITIVA DE HALLAZGOS ARQUEOLOGICOS Y REPUBLICANOS (CANALES Y MUROS | G61: =+G62+G93 -> 104865.84
B62: OE.1.4.1 | C62: RECOMPOSICION ANASTILOSIS - RESCATE DE MUROS PREHISPANICOS/REPUBLICANO | G62: =SUM(G63:G92) -> 78665.84
B63: OE.1.4.1.1 | C63: PREPARACION DE MORTERO
B64: OE.1.4.1.1.1 | C64: Preparación de mortero para canal prehispánico | D64: m³ | E64: 22 | F64: 148.64 | G64: =+ROUND(+IF(E64="",0,E64*F64),2) -> 3270.08
B65: OE.1.4.1.1.2 | C65: Preparación de mortero para canal republicano | D65: m³ | E65: 10 | F65: 151.36 | G65: =+ROUND(+IF(E65="",0,E65*F65),2) -> 1513.6
B66: OE.1.4.1.2 | C66: CUBERTINAS DE PROTECCION DE CABECERA DE MUROS
B67: OE.1.4.1.2.1 | C67: Cubertinas de protección con mortero de tierra, arcilla, arena, cal y piedra chancada | D67: m² | E67: 2 | F67: 369.75 | G67: =+ROUND(+IF(E67="",0,E67*F67),2) -> 739.5
B68: OE.1.4.1.3 | C68: ARMADO EN ANASTILOSIS MUROS Y CANALES PREHISPANICO/REPUBLICANO
B69: OE.1.4.1.3.1 | C69: Desmontado, Anastilosis de estructura de canal Prehispánico | D69: m³ | E69: 36 | F69: 320.2 | G69: =+ROUND(+IF(E69="",0,E69*F69),2) -> 11527.2
B70: OE.1.4.1.3.2 | C70: Desmontado, Anastilosis de estructura de canal Republicano | D70: m³ | E70: 36 | F70: 320.2 | G70: =+ROUND(+IF(E70="",0,E70*F70),2) -> 11527.2
B71: OE.1.4.1.3.3 | C71: Reticulado y codificado de estructura Canal Prehispánico | D71: m² | E71: 60 | F71: 85.16 | G71: =+ROUND(+IF(E71="",0,E71*F71),2) -> 5109.6
B72: OE.1.4.1.3.4 | C72: Reticulado y codificado de estructura Canal Republicano | D72: m² | E72: 40 | F72: 85.16 | G72: =+ROUND(+IF(E72="",0,E72*F72),2) -> 3406.4
B73: OE.1.4.1.4 | C73: EMBOQUILLADO CON MORTERO PREPARADO
B74: OE.1.4.1.4.1 | C74: Emboquillado de muros Prehispánico | D74: m² | E74: 150 | F74: 89.05 | G74: =+ROUND(+IF(E74="",0,E74*F74),2) -> 13357.5
B75: OE.1.4.1.4.2 | C75: Emboquillado de muros Republicano | D75: m² | E75: 71 | F75: 89.05 | G75: =+ROUND(+IF(E75="",0,E75*F75),2) -> 6322.55
B76: OE.1.4.1.5 | C76: CONSOLIDACION
B77: OE.1.4.1.5.1 | C77: Consolidación de canales Pre Hispánicos | D77: m² | E77: 15 | F77: 71.73 | G77: =+ROUND(+IF(E77="",0,E77*F77),2) -> 1075.95
B78: OE.1.4.1.5.2 | C78: Consolidación de canales Republicanos | D78: m² | E78: 20 | F78: 71.73 | G78: =+ROUND(+IF(E78="",0,E78*F78),2) -> 1434.6
B79: OE.1.4.1.5.3 | C79: Consolidación de muros rustico | D79: m² | E79: 1 | F79: 440.41 | G79: =+ROUND(+IF(E79="",0,E79*F79),2) -> 440.41
B80: OE.1.4.1.6 | C80: RECOMPOSICION
B81: OE.1.4.1.6.1 | C81: Recomposición de muros rustico | D81: m³ | E81: 1 | F81: 440.41 | G81: =+ROUND(+IF(E81="",0,E81*F81),2) -> 440.41
B82: OE.1.4.1.6.2 | C82: Recomposición de canal Pre Hispánicos | D82: m³ | E82: 8 | F82: 146.8 | G82: =+ROUND(+IF(E82="",0,E82*F82),2) -> 1174.4
B83: OE.1.4.1.6.3 | C83: Recomposición de canal Republicano | D83: m³ | E83: 10 | F83: 146.8 | G83: =+ROUND(+IF(E83="",0,E83*F83),2) -> 1468
B84: OE.1.4.1.7 | C84: RESTITUCION CON MATERIAL PROPIO
B85: OE.1.4.1.7.1 | C85: Restitución de muros rustico con material propio | D85: m³ | E85: 3 | F85: 102.34 | G85: =+ROUND(+IF(E85="",0,E85*F85),2) -> 307.02
B86: OE.1.4.1.7.2 | C86: Restitución de canales Pre Hispánicos rustico (con material propio) | D86: m³ | E86: 5 | F86: 102.34 | G86: =+ROUND(+IF(E86="",0,E86*F86),2) -> 511.7
B87: OE.1.4.1.7.3 | C87: Restitución de canal Republicano (con material propio) | D87: m³ | E87: 4 | F87: 102.34 | G87: =+ROUND(+IF(E87="",0,E87*F87),2) -> 409.36
B88: OE.1.4.1.7.4 | C88: Tratamiento de pisos: tierra: arcilla, gravilla | D88: m² | E88: 75 | F88: 22.02 | G88: =+ROUND(+IF(E88="",0,E88*F88),2) -> 1651.5
B89: OE.1.4.1.8 | C89: MANTENIMIENTO POST INVERSION
B90: OE.1.4.1.8.1 | C90: Mantenimiento Post Inversión | D90: mes | E90: 12 | F90: 248.78 | G90: =+ROUND(+IF(E90="",0,E90*F90),2) -> 2985.36
B91: OE.1.4.1.9 | C91: VARIOS, LIMPIEZA Y JARDINERIA
B92: OE.1.4.1.9.1 | C92: Limpieza de retículas y codificado | D92: m² | E92: 50 | F92: 199.87 | G92: =+ROUND(+IF(E92="",0,E92*F92),2) -> 9993.5
B93: OE.1.4.2 | C93: VARIOS | G93: =SUM(G94:G95) -> 26200
B94: OE.1.4.2.1 | C94: Señalética para Arqueología inc instalación | D94: glb | E94: 1 | F94: 1200 | G94: =+ROUND(+IF(E94="",0,E94*F94),2) -> 1200
B95: OE.1.4.2.2 | C95: Señalética para arqueología - en concreto y mayólica grabada en alto relieve | D95: und | E95: 5 | F95: 5000 | G95: =+ROUND(+IF(E95="",0,E95*F95),2) -> 25000
B96: OE.1.5 | C96: TRAMITES EN LA DDC CUSCO | G96: =+G97+G99+G101 -> 7641.02
B97: OE.1.5.1 | C97: PAGO DE APROBACION DEL INFORME FINAL AL PMAR | G97: =SUM(G98) -> 1071.02
B98: OE.1.5.1.1 | C98: Servicio de aprobación del informe final al PMAR | D98: ser | E98: 1 | F98: 1071.02 | G98: =+ROUND(+IF(E98="",0,E98*F98),2) -> 1071.02
B99: OE.1.5.2 | C99: PAGO AL MINISTERIO DE CULTURA - PRA | G99: =SUM(G100) -> 1807.6
B100: OE.1.5.2.1 | C100: Pago al Ministerio De Cultura - PRA | D100: ser | E100: 1 | F100: 1807.6 | G100: =+ROUND(+IF(E100="",0,E100*F100),2) -> 1807.6
B101: OE.1.5.3 | C101: PAGO AL MINISTERIO DE CULTURA - PRA - INSPECCION | G101: =SUM(G102) -> 4762.4
B102: OE.1.5.3.1 | C102: Pago al Ministerio De Cultura - PRA- Inspección | D102: ser | E102: 1 | F102: 4762.4 | G102: =+ROUND(+IF(E102="",0,E102*F102),2) -> 4762.4
B103: OE.2 | C103: ESTRUCTURAS. | G103: =+G104+G115+G124+G207 -> 18455900
B104: OE.2.1 | C104: MOVIMIENTO DE TIERRAS | G104: =G105+G107+G109+G113 -> 2354617.9
B105: OE.2.1.1 | C105: NIVELACIÓN DE TERRENO | G105: =SUM(G106) -> 81762.69
B106: OE.2.1.1.2 | C106: Nivelacion manual de terreno a nivel de desplante | D106: m² | E106: 6387.71 | F106: 12.8 | G106: =+ROUND(+IF(E106="",0,E106*F106),2) -> 81762.69
B107: OE.2.1.3 | C107: CORTE DE PLATAFORMA | G107: =SUM(G108) -> 1330597.5
B108: OE.2.1.3.2 | C108: Corte de terreno con maquinaria pesada | D108: m³ | E108: 44250 | F108: 30.07 | G108: =+ROUND(+IF(E108="",0,E108*F108),2) -> 1330597.5
B109: OE.2.1.4 | C109: RELLENOS | G109: =SUM(G110:G112) -> 640611.89
...

Sheet DD-4
B1: |
B5: UNIDAD EJECUTORA | C5: : GERENCIA REGIONAL DE GESTION DE INVERSIONES DE INFRAESTRUCTURA - GOBIERNO REGIONAL CUSCO (SEDE CENTRAL)
B6: OBRA | C6: : MEJORAMIENTO Y AMPLIACION DE LOS SERVICIOS DE SALUD DEL ESTABLECIMIENTO DE SALUD DE BELEMPAMPA - DISTRITO DE SANTIAGO - PROVINCIA DE CUSCO - REGION CUSCO
B7: META | C7: : 0119-2025
B9: PARTIDAS DEDUCTIVOS N°04
B11: Item | C11: DESCRIPCION | D11: Und | E11: Metrado | F11: PU | G11: Parcial
B12: OE.2 | C12: ESTRUCTURAS. | G12: =+G13+G23+G32 -> 30117585 | H12: X | I12: 31247535 | J12: =+I12-G12 -> 1129950.7
B13: OE.2.1 | C13: MOVIMIENTO DE TIERRAS | G13: =+G14+G16+G19+G21 -> 2501427.9 | I13: 3521435.1 | J13: =+I13-G13 -> 1020007.2
B14: OE.2.1.1 | C14: NIVELACIÓN DE TERRENO | G14: =SUM(G15) -> 8357.41 | I14: 8357.41 | J14: =+I14-G14 -> 0
B15: OE.2.1.1.1 | C15: Nivelación con maquinaria a nivel de sub razante | D15: m² | E15: 4037.395 | F15: 2.07 | G15: =+ROUND(+IF(E15="",0,E15*F15),2) -> 8357.41 | I15: 8357.41 | J15: =+I15-G15 -> 0
B16: OE.2.1.2 | C16: EXCAVACIONES | G16: =SUM(G17:G18) -> 55594.93 | I16: 302181.11 | J16: =+I16-G16 -> 246586.18
B17: OE.2.1.2.1 | C17: EXCAVACIONES MASIVAS CON MAQUINARIA | J17: =+I17-G17 -> 0
B18: OE.2.1.2.1.1 | C18: Excavaciones masivas para instalación de muros pantalla | D18: m³ | E18: 1810.32 | F18: 30.71 | G18: =+ROUND(+IF(E18="",0,E18*F18),2) -> 55594.93 | I18: 55594.93 | J18: =+I18-G18 -> 0
B19: OE.2.1.3 | C19: CORTE DE PLATAFORMA | G19: =SUM(G20) -> 231795.72 | I19: 231795.72 | J19: =+I19-G19 -> 0
B20: OE.2.1.3.1 | C20: Corte de plataforma con maquinaria en terreno natural | D20: m³ | E20: 23249.32 | F20: 9.97 | G20: =+ROUND(+IF(E20="",0,E20*F20),2) -> 231795.72 | I20: 231795.72 | J20: =+I20-G20 -> 0
B21: OE.2.1.6 | C21: ELIMINACION DE MATERIAL EXCEDENTE | G21: =SUM(G22:G22) -> 2205679.9 | I21: 2396003.6 | J21: =+I21-G21 -> 190323.74
B22: OE.2.1.6.3 | C22: Eliminación de material excedente con maquinaria a DME | D22: m³ | E22: 34345.685 | F22: 64.22 | G22: =+ROUND(+IF(E22="",0,E22*F22),2) -> 2205679.9 | I22: 2205679.9 | J22: =+I22-G22 -> 0
B23: OE.2.2 | C23: OBRAS CONCRETO SIMPLE | G23: =+G24+G27+G29 -> 310463.75 | I23: 420407.23 | J23: =+I23-G23 -> 109943.48
B24: OE.2.2.1 | C24: CIMIENTOS CORRIDOS | G24: =SUM(G25:G26) -> 140292.37 | I24: 140292.37 | J24: =+I24-G24 -> 0
B25: OE.2.2.1.1 | C25: Cimiento corridos - Concreto f'c=175 kg/cm2 | D25: m³ | E25: 195.70575 | F25: 456.34 | G25: =+ROUND(+IF(E25="",0,E25*F25),2) -> 89308.36 | I25: 89308.36 | J25: =+I25-G25 -> 0
B26: OE.2.2.1.2 | C26: Cimiento Corrido - Encofrado y desencofrado | D26: m² | E26: 785.3359 | F26: 64.92 | G26: =+ROUND(+IF(E26="",0,E26*F26),2) -> 50984.01 | I26: 50984.01 | J26: =+I26-G26 -> 0
B27: OE.2.2.2 | C27: SUB ZAPATAS O FALSA ZAPATA | G27: =SUM(G28) -> 131152 | I27: 131168 | J27: =+I27-G27 -> 16
B28: OE.2.2.2.1 | C28: Falsa zapata f´c=100kg/cm2 + 30% P.G 10" max. | D28: m³ | E28: 400 | F28: 327.88 | G28: =+ROUND(+IF(E28="",0,E28*F28),2) -> 131152 | I28: 131168 | J28: =+I28-G28 -> 16
B29: OE.2.2.5 | C29: ESTRUCTURA DE SOSTENIMIENTO DE EXCAVACIONES | G29: =SUM(G30:G31) -> 39019.38 | I29: 39019.38 | J29: =+I29-G29 -> 0
B30: OE.2.2.5.1 | C30: Calzaduras- concreto f'c=140 kg/cm2+30% P.M | D30: m³ | E30: 86.475 | F30: 418.22 | G30: =+ROUND(+IF(E30="",0,E30*F30),2) -> 36165.57 | I30: 36165.57 | J30: =+I30-G30 -> 0
B31: OE.2.2.5.2 | C31: Calzadura - Encofrado y Desencofrado | D31: m² | E31: 68.75 | F31: 41.51 | G31: =+ROUND(+IF(E31="",0,E31*F31),2) -> 2853.81 | I31: 2853.81 | J31: =+I31-G31 -> 0
B32: OE.2.3 | C32: OBRAS DE CONCRETO ARMADO | G32: =+G33+G36+G40+G44+G48+G74+G82+G89+G111+G115+G125 -> 27305693 | I32: 27305693 | J32: =+I32-G32 -> 0
B33: OE.2.3.2 | C33: ZAPATAS | G33: =SUM(G34:G35) -> 617879.96 | I33: 617879.96 | J33: =+I33-G33 -> 0
B34: OE.2.3.2.1 | C34: Zapatas - Concreto pre mezclado F'C=210 KG/CM2 | D34: m³ | E34: 685.4474 | F34: 479.29 | G34: =+ROUND(+IF(E34="",0,E34*F34),2) -> 328528.08 | I34: 328528.08 | J34: =+I34-G34 -> 0
B35: OE.2.3.2.3 | C35: Zapatas - Acero f'y=4200 kg/cm2 | D35: kg | E35: 43577.09 | F35: 6.64 | G35: =+ROUND(+IF(E35="",0,E35*F35),2) -> 289351.88 | I35: 289351.88 | J35: =+I35-G35 -> 0
B36: OE.2.3.3 | C36: VIGAS DE CIMENTACIÓN | G36: =SUM(G37:G39) -> 407294.51 | I36: 407294.51 | J36: =+I36-G36 -> 0
B37: OE.2.3.3.1 | C37: Viga de cimentación - concreto pre mezclado F'C=210 KG/CM2 | D37: m³ | E37: 280.6161 | F37: 478.59 | G37: =+ROUND(+IF(E37="",0,E37*F37),2) -> 134300.06 | I37: 134300.06 | J37: =+I37-G37 -> 0
B38: OE.2.3.3.2 | C38: Vigas de Cimentación - Encofrado y desencofrado | D38: m² | E38: 956.202 | F38: 65.51 | G38: =+ROUND(+IF(E38="",0,E38*F38),2) -> 62640.79 | I38: 62640.79 | J38: =+I38-G38 -> 0
B39: OE.2.3.3.3 | C39: Vigas de Cimentación - Acero f'y=4200 kg/cm2 | D39: kg | E39: 31679.768 | F39: 6.64 | G39: =+ROUND(+IF(E39="",0,E39*F39),2) -> 210353.66 | I39: 210353.66 | J39: =+I39-G39 -> 0
B40: OE.2.3.4 | C40: LOSAS DE CIMENTACIÓN | G40: =SUM(G41:G43) -> 628699.85 | I40: 628699.85 | J40: =+I40-G40 -> 0
B41: OE.2.3.4.1 | C41: Losas de cimentación - concreto pre mezclado F'C=210 KG/CM2 | D41: m³ | E41: 580.67915 | F41: 478.59 | G41: =+ROUND(+IF(E41="",0,E41*F41),2) -> 277907.23 | I41: 277907.23 | J41: =+I41-G41 -> 0
B42: OE.2.3.4.2 | C42: Losa de Cimentación - Encofrado y Desencofrado | D42: m² | E42: 321.961 | F42: 42.24 | G42: =+ROUND(+IF(E42="",0,E42*F42),2) -> 13599.63 | I42: 13599.63 | J42: =+I42-G42 -> 0
B43: OE.2.3.4.3 | C43: Losa de Cimentación - Acero f'y=4200 kg/cm2 | D43: kg | E43: 50782.077 | F43: 6.64 | G43: =+ROUND(+IF(E43="",0,E43*F43),2) -> 337192.99 | I43: 337192.99 | J43: =+I43-G43 -> 0
B44: OE.2.3.5 | C44: SOBRECIMIENTOS REFORZADOS | G44: =SUM(G45:G47) -> 369424 | I44: 369424 | J44: =+I44-G44 -> 0
B45: OE.2.3.5.1 | C45: Sobrecimientos reforzados-concreto f'c=175 kg/cm2 | D45: m³ | E45: 275.24158 | F45: 456.34 | G45: =+ROUND(+IF(E45="",0,E45*F45),2) -> 125603.74 | I45: 125603.74 | J45: =+I45-G45 -> 0
B46: OE.2.3.5.2 | C46: Sobrecimiento reforzado - Encofrado y desencofrado | D46: m² | E46: 3230.1621 | F46: 47.37 | G46: =+ROUND(+IF(E46="",0,E46*F46),2) -> 153012.78 | I46: 153012.78 | J46: =+I46-G46 -> 0
B47: OE.2.3.5.3 | C47: Sobrecimientos reforzados - Acero f'y=4200 kg/cm2 | D47: kg | E47: 13675.826 | F47: 6.64 | G47: =+ROUND(+IF(E47="",0,E47*F47),2) -> 90807.48 | I47: 90807.48 | J47: =+I47-G47 -> 0
B48: OE.2.3.6 | C48: MUROS REFORZADOS | G48: =SUM(G49:G73) -> 16321233 | I48: 16321233 | J48: =+I48-G48 -> 0
B49: OE.2.3.6.1 | C49: MUROS DE CONTENCIÓN | J49: =+I49-G49 -> 0
B50: OE.2.3.6.1.1 | C50: Muros de contención-concreto pre mezclado F'C=210 KG/CM2 | D50: m³ | E50: 445.9798 | F50: 478.59 | G50: =+ROUND(+IF(E50="",0,E50*F50),2) -> 213441.47 | I50: 213441.47 | J50: =+I50-G50 -> 0
B51: OE.2.3.6.1.2 | C51: Muros de contención-encofrado y desencofrado | D51: m² | E51: 569.9557 | F51: 41.31 | G51: =+ROUND(+IF(E51="",0,E51*F51),2) -> 23544.87 | I51: 23544.87 | J51: =+I51-G51 -> 0
B52: OE.2.3.6.1.3 | C52: Muro de contencion - Acero f'y=4200 kg/cm2 | D52: kg | E52: 15145.084 | F52: 6.64 | G52: =+ROUND(+IF(E52="",0,E52*F52),2) -> 100563.36 | I52: 100563.36 | J52: =+I52-G52 -> 0
B53: OE.2.3.6.1.4 | C53: Muro de Contención-Material de Filtro 3/4" | D53: m³ | E53: 163.38 | F53: 130.41 | G53: =+ROUND(+IF(E53="",0,E53*F53),2) -> 21306.39 | I53: 21306.39 | J53: =+I53-G53 -> 0
B54: OE.2.3.6.1.5 | C54: Muro de Contención-Llorones de Drenaje PVC 2" | D54: m | E54: 42 | F54: 26.77 | G54: =+ROUND(+IF(E54="",0,E54*F54),2) -> 1124.34 | I54: 1124.34 | J54: =+I54-G54 -> 0
B55: OE.2.3.6.1.6 | C55: Muro de Contencion.- Membrana Impermeabilizante | D55: m² | E55: 16.873 | F55: 28.02 | G55: =+ROUND(+IF(E55="",0,E55*F55),2) -> 472.78 | I55: 472.78 | J55: =+I55-G55 -> 0
B56: OE.2.3.6.2 | C56: PLACAS | J56: =+I56-G56 -> 0
B57: OE.2.3.6.2.1 | C57: Placas - concreto premezclado f'c=210 kg/cm2 | D57: m³ | E57: 1187.2693 | F57: 478.59 | G57: =+ROUND(+IF(E57="",0,E57*F57),2) -> 568215.21 | I57: 568215.21 | J57: =+I57-G57 -> 0
B58: OE.2.3.6.2.2 | C58: Placas - Encofrado y Desencofrado | D58: m² | E58: 8581.9233 | F58: 41.31 | G58: =+ROUND(+IF(E58="",0,E58*F58),2) -> 354519.25 | I58: 354519.25 | J58: =+I58-G58 -> 0
B59: OE.2.3.6.2.3 | C59: Placas - Acero f'y=4200 kg/cm2 | D59: kg | E59: 104087.25 | F59: 6.64 | G59: =+ROUND(+IF(E59="",0,E59*F59),2) -> 691139.36 | I59: 691139.36 | J59: =+I59-G59 -> 0
B60: OE.2.3.6.3 | C60: PANTALLAS, BARANDAS Y SIMILARES | J60: =+I60-G60 -> 0
B61: OE.2.3.6.3.1 | C61: Pantallas, barandas y similares - concreto premezclado f'c=210 kg/cm2 | D61: m³ | E61: 103.29 | F61: 478.59 | G61: =+ROUND(+IF(E61="",0,E61*F61),2) -> 49433.56 | I61: 49433.56 | J61: =+I61-G61 -> 0
B62: OE.2.3.6.3.2 | C62: Pantallas, barandas y similares - Encofrado y desencofrado | D62: m² | E62: 954.8 | F62: 55.44 | G62: =+ROUND(+IF(E62="",0,E62*F62),2) -> 52934.11 | I62: 52934.11 | J62: =+I62-G62 -> 0
B63: OE.2.3.6.3.3 | C63: Placas-Acero f'y=4200 kg/cm2 | D63: kg | E63: 10135.57 | F63: 6.64 | G63: =+ROUND(+IF(E63="",0,E63*F63),2) -> 67300.18 | I63: 67300.18 | J63: =+I63-G63 -> 0
B64: OE.2.3.6.4 | C64: MUROS PANTALLA CON ANCLAJE | J64: =+I64-G64 -> 0
B65: OE.2.3.6.4.1 | C65: Muros pantalla-concreto pre mezclado F'C=350 KG/CM2 | D65: m³ | E65: 1905.3 | F65: 537.89 | G65: =+ROUND(+IF(E65="",0,E65*F65),2) -> 1024841.8 | I65: 1024841.8 | J65: =+I65-G65 -> 0
B66: OE.2.3.6.4.2 | C66: Muros pantalla-acero fy=4200 kg/cm2 inc. instalación | D66: kg | E66: 315513.85 | F66: 6.64 | G66: =+ROUND(+IF(E66="",0,E66*F66),2) -> 2095011.9 | I66: 2095011.9 | J66: =+I66-G66 -> 0
B67: OE.2.3.6.4.3 | C67: Muros pantalla-instalación de anclajes | D67: m | E67: 36981 | F67: 292.38 | G67: =+ROUND(+IF(E67="",0,E67*F67),2) -> 10812505 | I67: 10812505 | J67: =+I67-G67 -> 0
B68: OE.2.3.6.4.4 | C68: Vigas de confinamiento - concreto pre mezclado F'C=350 KG/CM2 | D68: m³ | E68: 43.2 | F68: 537.89 | G68: =+ROUND(+IF(E68="",0,E68*F68),2) -> 23236.85 | I68: 23236.85 | J68: =+I68-G68 -> 0
B69: OE.2.3.6.4.5 | C69: Vigas de confinamiento - encofrado y desencofrado | D69: m² | E69: 282 | F69: 85.03 | G69: =+ROUND(+IF(E69="",0,E69*F69),2) -> 23978.46 | I69: 23978.46 | J69: =+I69-G69 -> 0
B70: OE.2.3.6.4.6 | C70: Vigas de confinamiento - acero fy=4200 kg/cm2 | D70: kg | E70: 13259.7 | F70: 6.64 | G70: =+ROUND(+IF(E70="",0,E70*F70),2) -> 88044.41 | I70: 88044.41 | J70: =+I70-G70 -> 0
B71: OE.2.3.6.4.7 | C71: Muros guía - concreto pre mezclado F'C=210 KG/CM2 | D71: m³ | E71: 78.96 | F71: 478.59 | G71: =+ROUND(+IF(E71="",0,E71*F71),2) -> 37789.47 | I71: 37789.47 | J71: =+I71-G71 -> 0
B72: OE.2.3.6.4.8 | C72: Muros guía - encofrado y desencofrado | D72: m² | E72: 451.2 | F72: 72.24 | G72: =+ROUND(+IF(E72="",0,E72*F72),2) -> 32594.69 | I72: 32594.69 | J72: =+I72-G72 -> 0
B73: OE.2.3.6.4.9 | C73: Muros guía - acero fy=4200 kg/cm2 | D73: kg | E73: 5908.94 | F73: 6.64 | G73: =+ROUND(+IF(E73="",0,E73*F73),2) -> 39235.36 | I73: 39235.36 | J73: =+I73-G73 -> 0
B74: OE.2.3.7 | C74: COLUMNAS | G74: =SUM(G75:G81) -> 2109143.2 | I74: 2109143.2 | J74: =+I74-G74 -> 0
B75: OE.2.3.7.1 | C75: Columnas - concreto premezclado f'c=210 kg/cm2 | D75: m³ | E75: 655.26875 | F75: 478.59 | G75: =+ROUND(+IF(E75="",0,E75*F75),2) -> 313605.07 | I75: 313605.07 | J75: =+I75-G75 -> 0
B76: OE.2.3.7.2 | C76: Columnas - Encofrado y desencofrado | D76: m² | E76: 4543.6166 | F76: 48.38 | G76: =+ROUND(+IF(E76="",0,E76*F76),2) -> 219820.17 | I76: 219820.17 | J76: =+I76-G76 -> 0
B77: OE.2.3.7.3 | C77: Columnas - acero f'y=4200 Kg/cm2 | D77: kg | E77: 67569.452 | F77: 6.64 | G77: =+ROUND(+IF(E77="",0,E77*F77),2) -> 448661.16 | I77: 448661.16 | J77: =+I77-G77 -> 0
B78: OE.2.3.7.4 | C78: Columnetas - concreto f'c=175 Kg/cm2 | D78: m³ | E78: 414.63836 | F78: 456.34 | G78: =+ROUND(+IF(E78="",0,E78*F78),2) -> 189216.07 | I78: 189216.07 | J78: =+I78-G78 -> 0
B79: OE.2.3.7.5 | C79: Columnetas - Encofrado y desencofrado | D79: m² | E79: 7033.7455 | F79: 74 | G79: =+ROUND(+IF(E79="",0,E79*F79),2) -> 520497.17 | I79: 520497.17 | J79: =+I79-G79 -> 0
B80: OE.2.3.7.6 | C80: Columnetas - Acero f'y=4200 kg/cm2 | D80: kg | E80: 61575.98 | F80: 6.64 | G80: =+ROUND(+IF(E80="",0,E80*F80),2) -> 408864.51 | I80: 408864.51 | J80: =+I80-G80 -> 0
B81: OE.2.3.7.7 | C81: Columnetas - anclaje a muros pantalla | D81: und | E81: 29 | F81: 292.38 | G81: =+ROUND(+IF(E81="",0,E81*F81),2) -> 8479.02 | I81: 8479.02 | J81: =+I81-G81 -> 0
B82: OE.2.3.8 | C82: VIGAS | G82: =SUM(G83:G88) -> 2370073.3 | I82: 2370073.3 | J82: =+I82-G82 -> 0
B83: OE.2.3.8.1 | C83: Vigas -Concreto premezclado f'c=210 kg/cm2 | D83: m³ | E83: 986.49815 | F83: 478.59 | G83: =+ROUND(+IF(E83="",0,E83*F83),2) -> 472128.15 | I83: 472128.15 | J83: =+I83-G83 -> 0
B84: OE.2.3.8.2 | C84: Vigas - Encofrado y desencofrado | D84: m² | E84: 8317.75 | F84: 85.02 | G84: =+ROUND(+IF(E84="",0,E84*F84),2) -> 707175.11 | I84: 707175.11 | J84: =+I84-G84 -> 0
B85: OE.2.3.8.3 | C85: Vigas - Acero f'y=4200 kg/cm2 | D85: kg | E85: 108859.69 | F85: 6.64 | G85: =+ROUND(+IF(E85="",0,E85*F85),2) -> 722828.33 | I85: 722828.33 | J85: =+I85-G85 -> 0
B86: OE.2.3.8.4 | C86: Viguetas. - concreto f'c=175 Kg/cm2 | D86: m³ | E86: 184.13036 | F86: 456.34 | G86: =+ROUND(+IF(E86="",0,E86*F86),2) -> 84026.05 | I86: 84026.05 | J86: =+I86-G86 -> 0
B87: OE.2.3.8.5 | C87: Viguetas - Encofrado y desencofrado | D87: m² | E87: 2338.5436 | F87: 84.58 | G87: =+ROUND(+IF(E87="",0,E87*F87),2) -> 197794.02 | I87: 197794.02 | J87: =+I87-G87 -> 0
B88: OE.2.3.8.6 | C88: Viguetas - Acero f'y=4200 kg/cm2 | D88: kg | E88: 28030.365 | F88: 6.64 | G88: =+ROUND(+IF(E88="",0,E88*F88),2) -> 186121.62 | I88: 186121.62 | J88: =+I88-G88 -> 0
B89: OE.2.3.9 | C89: LOSAS | G89: =SUM(G90:G110) -> 3257272.8 | I89: 3257272.8 | J89: =+I89-G89 -> 0
B90: OE.2.3.9.1 | C90: LOSA MACISA | J90: =+I90-G90 -> 0
B91: OE.2.3.9.1.1 | C91: Losa Maciza - Concreto premezclado f'c=210 Kg/cm2 | D91: m³ | E91: 51.35945 | F91: 478.59 | G91: =+ROUND(+IF(E91="",0,E91*F91),2) -> 24580.12 | I91: 24580.12 | J91: =+I91-G91 -> 0
B92: OE.2.3.9.1.2 | C92: Losa Maciza - Encofrado y desencofrado | D92: m² | E92: 311.2399 | F92: 68.79 | G92: =+ROUND(+IF(E92="",0,E92*F92),2) -> 21410.19 | I92: 21410.19 | J92: =+I92-G92 -> 0
B93: OE.2.3.9.1.3 | C93: Losa maciza - Acero f'y=4200 kg/cm2 | D93: kg | E93: 11619.577 | F93: 6.64 | G93: =+ROUND(+IF(E93="",0,E93*F93),2) -> 77153.99 | I93: 77153.99 | J93: =+I93-G93 -> 0
B94: OE.2.3.9.2 | C94: LOSA ALIGERADA | J94: =+I94-G94 -> 0
B95: OE.2.3.9.2.1 | C95: Losa Aligerada - Concreto premezclado f'c=210 Kg/cm2 | D95: m³ | E95: 1681.412 | F95: 478.59 | G95: =+ROUND(+IF(E95="",0,E95*F95),2) -> 804706.95 | I95: 804706.95 | J95: =+I95-G95 -> 0
B96: OE.2.3.9.2.2 | C96: Losa aligerada - Encofrado y desencofrado | D96: m² | E96: 11934.634 | F96: 68.79 | G96: =+ROUND(+IF(E96="",0,E96*F96),2) -> 820983.47 | I96: 820983.47 | J96: =+I96-G96 -> 0
B97: OE.2.3.9.2.3 | C97: Losa aligerada - Acero f'y=4200 kg/cm2 | D97: kg | E97: 140394.98 | F97: 6.64 | G97: =+ROUND(+IF(E97="",0,E97*F97),2) -> 932222.66 | I97: 932222.66 | J97: =+I97-G97 -> 0
B98: OE.2.3.9.2.4 | C98: Losa Aligerada - Ladrillo hueco de arcilla de 20x30x30 cm | D98: und | E98: 80819 | F98: 4.63 | G98: =+ROUND(+IF(E98="",0,E98*F98),2) -> 374191.97 | I98: 374191.97 | J98: =+I98-G98 -> 0
B99: OE.2.3.9.2.5 | C99: Losa Aligerada - Ladrillo hueco de arcilla de 15x30x30 cm | D99: und | E99: 4679 | F99: 4.28 | G99: =+ROUND(+IF(E99="",0,E99*F99),2) -> 20026.12 | I99: 20026.12 | J99: =+I99-G99 -> 0
B100: OE.2.3.9.8 | C100: FALSO PISO ARMADO | J100: =+I100-G100 -> 0
B101: OE.2.3.9.8.1 | C101: Falso piso armado - concreto f'c=175 kg/cm2 e=10 cm | D101: m² | E101: 771.27 | F101: 28.59 | G101: =+ROUND(+IF(E101="",0,E101*F101),2) -> 22050.61 | I101: 22050.61 | J101: =+I101-G101 -> 0
B102: OE.2.3.9.8.2 | C102: Falso piso armado - acero f'y=4200 Kg/cm2 | D102: kg | E102: 1467.95 | F102: 6.64 | G102: =+ROUND(+IF(E102="",0,E102*F102),2) -> 9747.19 | I102: 9747.19 | J102: =+I102-G102 -> 0
B103: OE.2.3.9.9 | C103: RAMPA DE CONCRETO ARMADO | J103: =+I103-G103 -> 0
B104: OE.2.3.9.9.1 | C104: Rampa - concreto premezclado f'c=210 kg/cm2 | D104: m³ | E104: 23.99249 | F104: 478.59 | G104: =+ROUND(+IF(E104="",0,E104*F104),2) -> 11482.57 | I104: 11482.57 | J104: =+I104-G104 -> 0
B105: OE.2.3.9.9.2 | C105: Rampa - Encofrado y desencofrado | D105: m² | E105: 2.44205 | F105: 68.79 | G105: =+ROUND(+IF(E105="",0,E105*F105),2) -> 167.99 | I105: 167.99 | J105: =+I105-G105 -> 0
...

Sheet MM-5
B1: |
B5: UNIDAD EJECUTORA | C5: : GERENCIA REGIONAL DE GESTION DE INVERSIONES DE INFRAESTRUCTURA - GOBIERNO REGIONAL CUSCO (SEDE CENTRAL)
B6: OBRA | C6: : MEJORAMIENTO Y AMPLIACION DE LOS SERVICIOS DE SALUD DEL ESTABLECIMIENTO DE SALUD DE BELEMPAMPA - DISTRITO DE SANTIAGO - PROVINCIA DE CUSCO - REGION CUSCO
B7: META | C7: : 0119-2025
B9: PARTIDAS MAYORES METRADOS N°5
B11: Item | C11: DESCRIPCION | D11: Und | E11: Metrado | F11: PU | G11: Parcial
C12: COMPONENTE 01: SUFICIENTE Y ADECUADA INFRAESTRUCTURA Y MANTENIMIENTO PARA LA PRESTACIÓN DE SERVICIOS DE SALUD | G12: =+G13+G35+G77+G95+G206+G218 -> 6873197.4
B13: OE.1 | C13: OBRAS PROVISIONALES, TRABAJOS PRELIMINARES, SEGURIDAD Y SALUD. | G13: =+G14 -> 1232461.1
B14: OE.1.1 | C14: OBRAS PROVISIONALES Y TRABAJOS PRELIMINARES | G14: =+G15+G30 -> 1232461.1
B15: OE.1.1.1 | C15: CONSTRUCCIONES PROVISIONALES | G15: =SUM(G16:G29) -> 1208193.6
B16: OE.1.1.1.1 | C16: Oficinas | D16: m² | E16: 200 | F16: 157.37 | G16: =+ROUND(E16*F16,2) -> 31474 | I16: =+H16-F16 -> -157.37
B17: OE.1.1.1.2 | C17: Almacenes | D17: m² | E17: 150 | F17: 109.44 | G17: =+ROUND(E17*F17,2) -> 16416 | I17: =+H17-F17 -> -109.44
B18: OE.1.1.1.3 | C18: Casetas de guardianÍa | D18: m² | E18: 41.47 | F18: 147.84 | G18: =+ROUND(E18*F18,2) -> 6130.92 | I18: =+H18-F18 -> -147.84
B19: OE.1.1.1.5 | C19: Vestuarios | D19: m² | E19: 700 | F19: 130.85 | G19: =+ROUND(E19*F19,2) -> 91595 | I19: =+H19-F19 -> -130.85
B20: OE.1.1.1.6 | C20: Servicios higienicos | D20: m² | E20: 20 | F20: 282.01 | G20: =+ROUND(E20*F20,2) -> 5640.2 | I20: =+H20-F20 -> -282.01
B21: OE.1.1.1.7 | C21: Cercos Provisional de calamina | D21: m | E21: 200 | F21: 53.39 | G21: =+ROUND(E21*F21,2) -> 10678 | I21: =+H21-F21 -> -53.39
B22: OE.1.1.1.16 | C22: Traslado de material con maquinaria de almacen Huancaro a Belempampa-15M3 por viaje (D=1800m) | D22: vje | E22: 800 | F22: 681.84 | G22: =+ROUND(E22*F22,2) -> 545472 | I22: =+H22-F22 -> -681.84
B23: OE.1.1.1.19 | C23: Desmontaje de oficinas y almacenes | D23: m² | E23: 3527.65 | F23: 54.74 | G23: =+ROUND(E23*F23,2) -> 193103.56 | I23: =+H23-F23 -> -54.74
B24: OE.1.1.1.20 | C24: Almacen de estructura metalica | D24: m² | E24: 350 | F24: 486.01 | G24: =+ROUND(E24*F24,2) -> 170103.5 | I24: =+H24-F24 -> -486.01
B25: OE.1.1.1.21 | C25: Embalado de materiales de almacen para traslado | D25: kg | E25: 173846 | F25: 0.34 | G25: =+ROUND(E25*F25,2) -> 59107.64 | I25: =+H25-F25 -> -0.34
B26: OE.1.1.1.23 | C26: Habilitacion de escantillon y soportes para malla de acero | D26: kg | E26: 10000 | F26: 4.16 | G26: =+ROUND(E26*F26,2) -> 41600 | I26: =+H26-F26 -> -4.16
B27: OE.1.1.1.24 | C27: Vaciado de falso piso en ambientes provisionales (almacen, vestuarios, ss.hh y otros) | D27: m² | E27: 100 | F27: 49.16 | G27: =+ROUND(E27*F27,2) -> 4916 | I27: =+H27-F27 -> -49.16
... B29: OE.1.1.1.26 | C29: Mantenimiento de andamios y estructuras metalicas | D29: und | E29: 100 | F29: 242.96 | G29: =+ROUND(E29*F29,2) -> 24296 | I29: =+H29-F29 -> -242.96
B30: OE.1.1.6 | C30: DEMOLICIONES | G30: =SUM(G31:G34) -> 24267.45
B31: OE.1.1.6.1 | C31: Demolicion de muros de ladrillo incluye cimentaciones | D31: m³ | E31: 10.13 | F31: 19.99 | G31: =+ROUND(E31*F31,2) -> 202.5 | I31: =+H31-F31 -> -19.99
B32: OE.1.1.6.5 | C32: Eliminación de Demoliciones | D32: m³ | E32: 61.13 | F32: 94.91 | G32: =+ROUND(E32*F32,2) -> 5801.85 | I32: =+H32-F32 -> -94.91
B33: OE.1.1.6.6 | C33: Demolicion de muros de contencion de concreto soterrado | D33: m³ | E33: 20 | F33: 358.1 | G33: =+ROUND(E33*F33,2) -> 7162 | I33: =+H33-F33 -> -358.1
B34: OE.1.1.6.8 | C34: Demolicion de estructuras de concreto armado (losas, vigas, columnas) | D34: m³ | E34: 31 | F34: 358.1 | G34: =+ROUND(E34*F34,2) -> 11101.1 | I34: =+H34-F34 -> -358.1
B35: OE.2 | C35: ESTRUCTURAS. | G35: =+G36+G44+G47+G74 -> 4525908.7
B36: OE.2.1 | C36: MOVIMIENTO DE TIERRAS | G36: =+G37+G39+G42 -> 372605.41
B37: OE.2.1.3 | C37: CORTE DE PLATAFORMA | G37: =SUM(G38) -> 199270.28
B38: OE.2.1.3.2 | C38: Corte de terreno con maquinaria pesada | D38: m³ | E38: 6626.88 | F38: 30.07 | G38: =+ROUND(E38*F38,2) -> 199270.28 | I38: =+H38-F38 -> -30.07
B39: OE.2.1.4 | C39: RELLENOS | G39: =SUM(G40:G41)/2 -> 123371.13
B40: OE.2.1.4.2 | C40: RELLENOS CON MATERIAL DE PRÉSTAMO | G40: =SUM(G41) -> 123371.13
B41: OE.2.1.4.2.2 | C41: Relleno y compactado con material afirmado + bolonería de diam=6" | D41: m³ | E41: 1560.08 | F41: 79.08 | G41: =+ROUND(E41*F41,2) -> 123371.13 | I41: =+H41-F41 -> -79.08
B42: OE.2.1.6 | C42: ELIMINACION DE MATERIAL EXCEDENTE | G42: =SUM(G43) -> 49964
B43: OE.2.1.6.4 | C43: Remoción de material sobrante mediante maquinaria a DME | D43: m³ | E43: 8084.79 | F43: 6.18 | G43: =+ROUND(E43*F43,2) -> 49964 | I43: =+H43-F43 -> -6.18
B44: OE.2.2 | C44: OBRAS CONCRETO SIMPLE | G44: =+G45 -> 60729.31
B45: OE.2.2.3 | C45: SOLADOS | G45: =SUM(G46) -> 60729.31
B46: OE.2.2.3.1 | C46: Solado f´c=100 kg/cm2, H=10 CM | D46: m² | E46: 1476.88 | F46: 41.12 | G46: =+ROUND(E46*F46,2) -> 60729.31 | I46: =+H46-F46 -> -41.12
B47: OE.2.3 | C47: OBRAS DE CONCRETO ARMADO | G47: =+G48+G51+G55+G61+G64+G67 -> 4017574
B48: OE.2.3.3 | C48: VIGAS DE CIMENTACIÓN | G48: =SUM(G49:G50) -> 55195.92
B49: OE.2.3.3.4 | C49: Vigas de Cimentación - Acero de refuerzo f'y=4200 kg/cm2 | D49: kg | E49: 2632.38 | F49: 6.55 | G49: =+ROUND(E49*F49,2) -> 17242.09 | I49: =+H49-F49 -> -6.55
B50: OE.2.3.3.5 | C50: Vigas de Cimentación - Encofrado y desencofrado con fenolico | D50: m² | E50: 437.71 | F50: 86.71 | G50: =+ROUND(E50*F50,2) -> 37953.83
B51: OE.2.3.4 | C51: LOSAS DE CIMENTACIÓN | G51: =SUM(G52:G54) -> 827759.58
B52: OE.2.3.4.4 | C52: Losa de Cimentación - Acero de refuerzo f'y=4200 kg/cm2 | D52: kg | E52: 98809.88 | F52: 6.55 | G52: =+ROUND(E52*F52,2) -> 647204.71 | I52: =+H52-F52 -> -6.55
B53: OE.2.3.4.5 | C53: Losa de Cimentación - Encofrado y Desencofrado con fenolico | D53: m² | E53: 410.83 | F53: 70.43 | G53: =+ROUND(E53*F53,2) -> 28934.76
B54: OE.2.3.4.6 | C54: Losas de cimentación - Concreto pre mezclado F'C=280 KG/CM2 | D54: m³ | E54: 364.91 | F54: 415.5 | G54: =+ROUND(E54*F54,2) -> 151620.11
B55: OE.2.3.6 | C55: MUROS REFORZADOS | G55: =SUM(G56:G60)/2 -> 2089601.8
B56: OE.2.3.6.1 | C56: MUROS DE CONTENCIÓN | G56: =SUM(G57:G58) -> 1149167
B57: OE.2.3.6.1.7 | C57: Muro de contencion - Acero de refuerzo f'y=4200 kg/cm2 | D57: kg | E57: 121499.08 | F57: 6.55 | G57: =+ROUND(E57*F57,2) -> 795818.97 | I57: =+H57-F57 -> -6.55
B58: OE.2.3.6.1.9 | C58: Muros de contención - Concreto pre mezclado F'C=280 KG/CM2 | D58: m³ | E58: 762.94 | F58: 463.14 | G58: =+ROUND(E58*F58,2) -> 353348.03 | I58: =+H58-F58 -> -463.14
B59: OE.2.3.6.2 | C59: PLACAS | G59: =SUM(G60) -> 940434.79
B60: OE.2.3.6.2.4 | C60: Placas - Acero de refuerzo f'y=4200 kg/cm2 | D60: kg | E60: 96553.88 | F60: 9.74 | G60: =+ROUND(E60*F60,2) -> 940434.79 | I60: =+H60-F60 -> -9.74
B61: OE.2.3.7 | C61: COLUMNAS | G61: =SUM(G62:G63) -> 326776.36
B62: OE.2.3.7.8 | C62: Columnas - acero de refuerzo f'y=4200 Kg/cm2 | D62: kg | E62: 29646.39 | F62: 9.74 | G62: =+ROUND(E62*F62,2) -> 288755.84 | I62: =+H62-F62 -> -9.74
B63: OE.2.3.7.9 | C63: Columnas - Encofrado y Desencofrado con fenolico | D63: m² | E63: 582.69 | F63: 65.25 | G63: =+ROUND(E63*F63,2) -> 38020.52
B64: OE.2.3.8 | C64: VIGAS | G64: =SUM(G65:G66) -> 427878.95
B65: OE.2.3.8.8 | C65: Vigas - Acero de refuerzo f'y=4200 kg/cm2 | D65: kg | E65: 53084.42 | F65: 6.55 | G65: =+ROUND(E65*F65,2) -> 347702.95 | I65: =+H65-F65 -> -6.55
B66: OE.2.3.8.9 | C66: Vigas - Concreto pre mezclado F'C=280 KG/CM2 | D66: m³ | E66: 190.7 | F66: 420.43 | G66: =+ROUND(E66*F66,2) -> 80176
B67: OE.2.3.9 | C67: LOSAS | G67: =SUM(G68:G73)/2 -> 290361.41
B68: OE.2.3.9.1 | C68: LOSA MACISA | G68: =SUM(G69:G70) -> 65948.32
B69: OE.2.3.9.1.4 | C69: Losa Maciza - Encofrado y desencofrado con fenolico | D69: m² | E69: 388.31 | F69: 81.78 | G69: =+ROUND(E69*F69,2) -> 31755.99 | I69: =+H69-F69 -> -81.78
B70: OE.2.3.9.1.6 | C70: Losa Maciza - Concreto pre mezclado F'C=280 KG/CM2 | D70: m³ | E70: 79.53 | F70: 429.93 | G70: =+ROUND(E70*F70,2) -> 34192.33 | I70: =+H70-F70 -> -429.93
B71: OE.2.3.9.2 | C71: LOSA ALIGERADA | G71: =SUM(G72:G73) -> 224413.09
B72: OE.2.3.9.2.9 | C72: Losa aligerada - Acero de refuerzo f'y=4200 kg/cm2 | D72: kg | E72: 27486.37 | F72: 6.55 | G72: =+ROUND(E72*F72,2) -> 180035.72 | I72: =+H72-F72 -> -6.55
B73: OE.2.3.9.2.10 | C73: Losa Aligerada - Concreto pre mezclado F'C=280 KG/CM2 | D73: m³ | E73: 103.22 | F73: 429.93 | G73: =+ROUND(E73*F73,2) -> 44377.37 | I73: =+H73-F73 -> -429.93
B74: OE.2.6 | C74: VARIOS | G74: =+G75 -> 75000
B75: OE.2.6.2 | C75: PRUEBAS DE CONTROL DE CALIDAD | G75: =SUM(G76) -> 75000
B76: OE.2.6.2.4 | C76: Rotura de Briquetas | D76: und | E76: 1500 | F76: 50 | G76: =+ROUND(E76*F76,2) -> 75000 | I76: =+H76-F76 -> -50
B77: OE.3 | C77: ARQUITECTURA | G77: =+G78+G84+G92 -> 545413.94
B78: OE.3.4 | C78: PISOS Y PAVIMENTOS | G78: =+G79 -> 167767.71
B79: OE.3.4.2 | C79: PISOS | G79: =SUM(G80:G83)/2 -> 167767.71
B80: OE.3.4.2.19 | C80: PISOS LAMINADOS | G80: =SUM(G81) -> 38739.99
B81: OE.3.4.2.19.1 | C81: Piso Vinilico flexible en rollo Alto transito E=2mm | D81: m² | E81: 306.9 | F81: 126.23 | G81: =+ROUND(E81*F81,2) -> 38739.99 | I81: =+H81-F81 -> -126.23
B82: OE.3.4.2.20 | C82: PORCELANATOS | G82: =SUM(G83) -> 129027.72
B83: OE.3.4.2.20.1 | C83: Piso Porcelanato de 0.60x0.60 Antideslizante Alto transito. | D83: m² | E83: 1575.43 | F83: 81.9 | G83: =+ROUND(E83*F83,2) -> 129027.72 | I83: =+H83-F83 -> -81.9
B84: OE.3.5 | C84: ZOCALOS Y CONTRAZOCALOS | G84: =+G85+G90 -> 371438.13
B85: OE.3.5.1 | C85: ZOCALOS | G85: =SUM(G86:G89)/2 -> 357359.34
B86: OE.3.5.1.9 | C86: REVESTIMIENTOS ESPECIALES | G86: =SUM(G87) -> 29043.36
B87: OE.3.5.1.9.2 | C87: Zocalo de vinilico flexible en rollo E=2mm | D87: m² | E87: 378.81 | F87: 76.67 | G87: =+ROUND(E87*F87,2) -> 29043.36 | I87: =+H87-F87 -> -76.67
B88: OE.3.5.1.10 | C88: PORCELANATO | G88: =SUM(G89) -> 328315.98
B89: OE.3.5.1.10.1 | C89: Zocalo Porcelanato 0.60x0.60 | D89: m² | E89: 3732.56 | F89: 87.96 | G89: =+ROUND(E89*F89,2) -> 328315.98 | I89: =+H89-F89 -> -87.96
B90: OE.3.5.2 | C90: CONTRAZOCALOS | G90: =SUM(G91) -> 14078.79
B91: OE.3.5.2.8 | C91: Contrazocalo de porcelanato H=0.10m. | D91: m | E91: 250.78 | F91: 56.14 | G91: =+ROUND(E91*F91,2) -> 14078.79 | I91: =+H91-F91 -> -56.14
B92: OE.3.7 | C92: CARPINTERIA DE MADERA | G92: =+G93 -> 6208.1
B93: OE.3.7.1 | C93: PUERTAS DE MADERA | G93: =SUM(G94) -> 6208.1
B94: OE.3.7.1.22 | C94: P-19 (0.90x2.20) puerta de 01 hoja contraplacada con plancha interior de plomo | D94: und | E94: 2 | F94: 3104.05 | G94: =+ROUND(E94*F94,2) -> 6208.1 | I94: =+H94-F94 -> -3104.05
B95: OE.4 | C95: INSTALACIONES SANITARIAS | G95: =+G96+G105+G127+G145+G150+G157+G184+G196 -> 194520.09
B96: OE.4.1 | C96: APARATOS SANITARIOS Y ACCESORIOS | G96: =+G97+G103 -> 7295.78
B97: OE.4.1.1 | C97: SUMINISTRO DE APARATOS SANITARIOS | G97: =SUM(G98:G102) -> 6901.4
B98: OE.4.1.1.3 | C98: Lavatorio tipo A-5 (ceramica vitrificada, ovalin, af de 18" diametro, control) | D98: und | E98: 2 | F98: 662.73 | G98: =+ROUND(E98*F98,2) -> 1325.46 | I98: =+H98-F98 -> -662.73
B99: OE.4.1.1.4 | C99: Lavatorio tipo B-1 (acero inoxidable 1 poza s/ escurridor 18"x20", af y ac) | D99: und | E99: 1 | F99: 348.34 | G99: =+ROUND(E99*F99,2) -> 348.34 | I99: =+H99-F99 -> -348.34
B100: OE.4.1.1.7 | C100: Lavadero tipo B-102a (acero inoxidable 1610x700 para cirujano-griferia cuello de ganso especial con control de rodilla cromada) | D100: und | E100: 1 | F100: 646.8 | G100: =+ROUND(E100*F100,2) -> 646.8 | I100: =+H100-F100 -> -646.8
B101: OE.4.1.1.8 | C101: Lavadero tipo B-11 (acero inox. 21"x42" con 1 poza y 1 escurridero, agua fria y caliente) | D101: und | E101: 6 | F101: 596.8 | G101: =+ROUND(E101*F101,2) -> 3580.8 | I101: =+H101-F101 -> -596.8
B102: OE.4.1.1.16 | C102: Inodoro tipo C-1a discapacitados (ceramica vitrificada con valvula fluxometro) | D102: und | E102: 4 | F102: 250 | G102: =+ROUND(E102*F102,2) -> 1000 | I102: =+H102-F102 -> -250
B103: OE.4.1.3 | C103: INSTALACION DE APARATOS SANITARIOS | G103: =SUM(G104) -> 394.38
B104: OE.4.1.3.1 | C104: Colocacion de aparatos sanitarios | D104: und | E104: 14 | F104: 28.17 | G104: =+ROUND(E104*F104,2) -> 394.38 | I104: =+H104-F104 -> -28.17
B105: OE.4.2 | C105: SISTEMA DE AGUA FRIA | G105: =+G106+G125 -> 27998.08
B106: OE.4.2.4 | C106: ACCESORIOS DE REDES DE AGUA | G106: =SUM(G107:G124)/2 -> 24867.61
...

Sheet PN-5
B1: |
B5: UNIDAD EJECUTORA | C5: : GERENCIA REGIONAL DE GESTION DE INVERSIONES DE INFRAESTRUCTURA - GOBIERNO REGIONAL CUSCO (SEDE CENTRAL)
B6: OBRA | C6: : MEJORAMIENTO Y AMPLIACION DE LOS SERVICIOS DE SALUD DEL ESTABLECIMIENTO DE SALUD DE BELEMPAMPA - DISTRITO DE SANTIAGO - PROVINCIA DE CUSCO - REGION CUSCO
B7: META | C7: : 0160-2025
B9: PARTIDAS NUEVAS N°5
B11: Ítem | C11: DESCRIPCION | D11: Und | E11: Metrado | F11: PU | G11: Parcial
C12: COMPONENTE 01: SUFICIENTE Y ADECUADA INFRAESTRUCTURA Y MANTENIMIENTO PARA LA PRESTACIÓN DE SERVICIOS DE SALUD | G12: =+G13+G124+G173+G218+G507+G521+G545+G548 -> 20834188 | H12: 20834188 | I12: =+H12-G12 -> 0
B13: OE.1 | C13: OBRAS PROVISIONALES, TRABAJOS PRELIMINARES, SEGURIDAD Y SALUD. | G13: =+G14+G59+G102+G105 -> 8675907.1 | H13: 8675907.1 | I13: =+H13-G13 -> 0
B14: OE.1.1 | C14: OBRAS PROVISIONALES Y TRABAJOS PRELIMINARES | G14: =+G15+G26+G33+G48+G51+G53+G55+G57 -> 4287912.9
B15: OE.1.1.1 | C15: CONSTRUCCIONES PROVISIONALES | G15: =SUM(G16:G25)/2 -> 224602.77
B16: OE.1.1.1.27 | C16: PUERTAS PROVISIONALES | G16: =SUM(G17:G18) -> 9234.81
B17: OE.1.1.1.27.1 | C17: Instalación de puerta provisional metálica | D17: m² | E17: 55.99 | F17: 82.63 | G17: =+ROUND(E17*F17,2) -> 4626.45
B18: OE.1.1.1.27.2 | C18: Instalación de puerta provisional de madera para almacén Huancaro | D18: m² | E18: 102 | F18: 45.18 | G18: =+ROUND(E18*F18,2) -> 4608.36
B19: OE.1.1.1.28 | C19: HABILITACION DE MOVILIARIOS PARA OBRA | G19: =SUM(G20:G22) -> 80069.4
B20: OE.1.1.1.28.1 | C20: Habilitación de mobiliario estante L=1.20m x 1.80m | D20: und | E20: 60 | F20: 274.35 | G20: =+ROUND(E20*F20,2) -> 16461
B21: OE.1.1.1.28.2 | C21: Habilitación de pizarra acrílica para obra de 1.20m x 2.40m | D21: und | E21: 20 | F21: 326.52 | G21: =+ROUND(E21*F21,2) -> 6530.4
B22: OE.1.1.1.28.3 | C22: Habilitado de estantes para almacén de 2.50m x 0.90m con rollizo | D22: m | E22: 126 | F22: 453 | G22: =+ROUND(E22*F22,2) -> 57078
B23: OE.1.1.1.29 | C23: CONSTRUCCIONES METALICAS | G23: =SUM(G24:G25) -> 135298.56
B24: OE.1.1.1.29.1 | C24: Habilitado y colocado de escalera metálica provisional | D24: kg | E24: 15601.45 | F24: 7.97 | G24: =+ROUND(E24*F24,2) -> 124343.56
B25: OE.1.1.1.29.2 | C25: Vestuario de estructura metálica | D25: m² | E25: 100 | F25: 109.55 | G25: =+ROUND(E25*F25,2) -> 10955
B26: OE.1.1.2 | C26: INSTALACIONES PROVISIONALES | G26: =SUM(G27:G32)/2 -> 108580
B27: OE.1.1.2.3 | C27: ENERGÍA ELÉCTRICA PROVISIONAL | G27: =SUM(G28:G32) -> 108580
B28: OE.1.1.2.3.6 | C28: Adquisición de tablero de control general | D28: glb | E28: 1 | F28: 6660 | G28: =+ROUND(E28*F28,2) -> 6660
B29: OE.1.1.2.3.7 | C29: Adquisición de tableros de distribución | D29: glb | E29: 1 | F29: 25520 | G29: =+ROUND(E29*F29,2) -> 25520
B30: OE.1.1.2.3.8 | C30: Adquisición de reflectores | D30: glb | E30: 1 | F30: 33600 | G30: =+ROUND(E30*F30,2) -> 33600
B31: OE.1.1.2.3.9 | C31: Adquisición de accesorios | D31: glb | E31: 1 | F31: 29000 | G31: =+ROUND(E31*F31,2) -> 29000
B32: OE.1.1.2.3.10 | C32: Adquisición de cables | D32: glb | E32: 1 | F32: 13800 | G32: =+ROUND(E32*F32,2) -> 13800
B33: OE.1.1.3 | C33: TRABAJOS PRELIMINARES | G33: =SUM(G34:G47)/2 -> 3748374.5
B34: OE.1.1.3.2 | C34: TRABAJOS DE REUBICACION CON MAQUINARIA | G34: =SUM(G35:G39) -> 392060.18
B35: OE.1.1.3.2.1 | C35: Reubicación de material en obra con retroexcavadora D=100 m | D35: m³ | E35: 4032 | F35: 54.04 | G35: =+ROUND(E35*F35,2) -> 217889.28
B36: OE.1.1.3.2.2 | C36: Reubicación de material en obra con maquinaria D=100 m | D36: kg | E36: 81250 | F36: 0.14 | G36: =+ROUND(E36*F36,2) -> 11375
B37: OE.1.1.3.2.3 | C37: Traslado de materiales con camioneta de almacén Huancaro a Belempampa (D=1800m) | D37: vje | E37: 800 | F37: 110.94 | G37: =+ROUND(E37*F37,2) -> 88752
B38: OE.1.1.3.2.4 | C38: Traslado de material en desuso de almacén Huancaro a IPD (D=3.4 KM) | D38: vje | E38: 35 | F38: 986.18 | G38: =+ROUND(E38*F38,2) -> 34516.3
B39: OE.1.1.3.2.5 | C39: Reubicación de material en obra con minicargador frontal D=100 m | D39: m³ | E39: 532 | F39: 74.3 | G39: =+ROUND(E39*F39,2) -> 39527.6
B40: OE.1.1.3.3 | C40: TRABAJOS DE REUBICACION DE MATERIALES | G40: =SUM(G41:G44) -> 3245302.4
B41: OE.1.1.3.3.1 | C41: Acarreo de materiales manual en obra D>150 m | D41: tn | E41: 16171.98 | F41: 148.22 | G41: =+ROUND(E41*F41,2) -> 2397010.9
B42: OE.1.1.3.3.2 | C42: Traslado vertical con winche de material en obra h=16m - Kilogramos | D42: kg | E42: 1068540 | F42: 0.11 | G42: =+ROUND(E42*F42,2) -> 117539.4
B43: OE.1.1.3.3.3 | C43: Traslado vertical con winche de material en obra h=16m - metros cúbicos | D43: m³ | E43: 1284 | F43: 47.94 | G43: =+ROUND(E43*F43,2) -> 61554.96
B44: OE.1.1.3.3.4 | C44: Traslado vertical manual de material en obra h=16 m | D44: kg | E44: 3345985.6 | F44: 0.2 | G44: =+ROUND(E44*F44,2) -> 669197.12
B45: OE.1.1.3.4 | C45: TRABAJOS COMPLEMENTARIOS | G45: =SUM(G46:G47) -> 111011.93
B46: OE.1.1.3.4.1 | C46: Rotura manual de piedra para reducción de diámetro (12" a <8") para empedrado | D46: m³ | E46: 75.89 | F46: 111.16 | G46: =+ROUND(E46*F46,2) -> 8435.93
B47: OE.1.1.3.4.2 | C47: Armado y desarmado de andamios | D47: und | E47: 4800 | F47: 21.37 | G47: =+ROUND(E47*F47,2) -> 102576
B48: OE.1.1.10 | C48: DESMONTAJE Y MONTAJE | G48: =SUM(G49:G50) -> 7282.2
B49: OE.1.1.10.1 | C49: Desmontaje de cerco provisional de calamina | D49: m | E49: 300 | F49: 19.82 | G49: =+ROUND(E49*F49,2) -> 5946
B50: OE.1.1.10.2 | C50: Desmontaje de rampas de acceso | D50: m | E50: 34 | F50: 39.3 | G50: =+ROUND(E50*F50,2) -> 1336.2
B51: OE.1.1.11 | C51: ADQUISICIONES | G51: =SUM(G52) -> 10640
