Workbook
Name \A: #REF!
Name \C: #REF!
Name \D: #REF!
Name \E: #REF!
Name \N: #REF!
Name \P: #REF!
Name \R: #REF!
Name \S: #REF!
Name \W: #REF!
Name \z: '[1]PRES. PRINC.'!$A$374:$A$535
Name ___________________PAG1: #REF!
Name __________________PAG1: #REF!
Name _________________PAG1: #REF!
Name ________________PAG1: #REF!
Name _______________PAG1: #REF!
Name ______________PAG1: #REF!
Name _____________PAG1: #REF!
Name ____________PAG1: #REF!
Name ___________PAG1: #REF!
Name __________PAG1: #REF!
Name _________HOJ1: #REF!
Name _________HOJ2: #REF!
Name _________HOJ3: #REF!
Name _________PAG1: #REF!
Name ________HOJ1: #REF!
Name ________HOJ2: #REF!
Name ________HOJ3: #REF!
Name ________HOJ4: #N/A
Name ________PAG1: #REF!
Name _______HOJ4: #N/A
Name _______PAG1: #REF!
Name ______HOJ1: #REF!
Name ______HOJ2: #REF!
Name ______HOJ3: #REF!
Name ______HOJ4: #N/A
Name ______PAG1: #REF!
Name _____HOJ1: #REF!
Name _____HOJ2: #REF!
Name _____HOJ3: #REF!
Name _____HOJ4: #N/A
Name _____PAG1: #REF!
Name ____h1: #REF!
Name ____h2: #REF!
Name ____HOJ1: #REF!
Name ____HOJ2: #REF!
Name ____HOJ3: #REF!
Name ____HOJ4: #N/A
Name ____PAG1: #REF!
Name ___h1: #REF!
Name ___h2: #REF!
Name ___HOJ1: #REF!
Name ___HOJ2: #REF!
Name ___HOJ3: #REF!
Name ___HOJ4: #N/A
Name ___PAG1: #REF!
Name __CAO1: #REF!
Name __CAO2: #REF!
Name __CAO3: #REF!
Name __CAO4: #REF!
Name __CAO5: #REF!

Sheet Resumen Metrado
B2: RESUMEN DE METRADOS DE ESTRUCTURAS
B4: Proyecto | C4: : | D4: Mejoramiento De Los Servicios De Educacion Primaria De La I.E Nº 50217 De La Comunidad De Umachurco, Distrito San Salvador, Provincia Calca - Cusco
B6: Region | C6: : | D6: Cusco
B7: Provincia | C7: : | D7: Calca
B8: Distrito | C8: : | D8: San Salvador
B9: Ubicación | C9: : | D9: Comunidad de Umachurco
B11: Item | C11: DESCRIPCION | L11: UND | M11: METRADO
B12: 01 | C12: OBRAS PROVISIONALES, TRABAJOS PRELIMINARES, SEGURIDAD Y SALUD
B13: 01.01 | C13: OBRAS PROVISIONALES Y TRABAJOS PRELIMINARES
B14: 01.01 | C14: OBRAS PROVISIONALES
B15: 01.01.01 | C15: CARTEL DE IDENTIFICACION DE OBRA | L15: UND | M15: =+'Metrado Estructuras'!Q9 -> 1498.688
B16: 01.01.02 | C16: LIMPIEZA DE TERRENO | L16: M2 | M16: =+'Metrado Estructuras'!Q14 -> 0
B17: 01.01.03 | C17: CERCO PERIMETRICO CON ARPILLERA | L17: ML | M17: =+'Metrado Estructuras'!Q17 -> 0
B18: 01.01.04 | C18: ALQUILER DE OFICINA, ALMACEN Y GUARDIANIA | L18: MES | M18: =+'Metrado Estructuras'!Q20 -> 0
B19: 01.02 | C19: TRABAJOS PRELIMINARES
B20: 01.02.01 | C20: LIMPIEZA PERMANENTE DE OBRA | L20: MES | M20: =+'Metrado Estructuras'!#REF! -> #REF!
B21: 01.06 | C21: TRAZO, NIVELES Y REPLANTEO
B22: 01.06.01 | C22: TRAZO, NIVELES Y REPLANTEO PRELIMINAR | L22: M2 | M22: =+'Metrado Estructuras'!#REF! -> #REF!
B23: 01.06.01 | C23: TRAZO, NIVELES Y REPLANTEO DURANTE LA EJECUCION | L23: M2 | M23: =+'Metrado Estructuras'!#REF! -> #REF!
B24: 01.03 | C24: MOVILIZACION Y DESMOVILIZACION
B25: 01.03.01 | C25: MOVILIZACION Y DESMOVILIZACION DE EQUIPO Y MAQUINARIA | L25: GBL | M25: =+'Metrado Estructuras'!#REF! -> #REF!
B26: 01.05.01 | C26: TRANSPORTE DE MATERIALES A OBRA | L26: GBL | M26: =+'Metrado Estructuras'!#REF! -> #REF!
B27: 01.03 | C27: REMOCIONES
B28: 01.03.01 | C28: DESMONTAJE DE MODULO PREFABRICADO | L28: GBL | M28: =+'Metrado Estructuras'!#REF! -> #REF!
B29: 01.05.01 | C29: MONTAJE DE MODULO PREFABRICADO EN NUEVA UBICACIÓN | L29: GBL | M29: =+'Metrado Estructuras'!#REF! -> #REF!
B30: 02 | C30: ESTRUCTURAS
B31: 02.01 | C31: MOVIMIENTO DE TIERRAS
B32: 02.01.01 | C32: EXCAVACION MASIVA DE TERRENO MANUAL | L32: M3 | M32: =+'Metrado Estructuras'!#REF! -> #REF!
B33: 02.01.02 | C33: EXCAVACION DE ZANJA PARA CIMIENTOS Y ZAPATAS | L33: M3 | M33: =+'Metrado Estructuras'!#REF! -> #REF!
B34: 02.01.03 | C34: RELLENO CON MATERIAL PROPIO | L34: M3 | M34: =+'Metrado Estructuras'!#REF! -> #REF!
B35: 02.01.04 | C35: ELIMINACION DE MATERIAL EXCEDENTE MANUAL D=40M | L35: M3 | M35: =+'Metrado Estructuras'!#REF! -> #REF!
B36: 02.01.05 | C36: ELIMINACION DE MATERIAL EXCEDENTE CON MAQUINARIA | L36: M3 | M36: =+'Metrado Estructuras'!#REF! -> #REF!
B37: 02.02 | C37: OBRAS DE CONCRETO SIMPLE
B38: 02.02.01 | C38: SOLADOS
B39: 02.02.01.01 | C39: SOLADO E=0.10 M. | L39: M2 | M39: =+'Metrado Estructuras'!#REF! -> #REF!
B40: 02.02.01 | C40: CIMIENTOS CORRIDOS
B41: 02.02.01.01 | C41: CONCRETO CICLOPEO EN CIMIENTOS CORRIDOS (MEZCLA 1:10+30%PG). | L41: M3 | M41: =+'Metrado Estructuras'!#REF! -> #REF!
B42: 02.02.02 | C42: SOBRECIMIENTOS
B43: 02.02.02.02 | C43: CONCRETO EN SOBRECIMIENTOS (MEZCLA 1:8+25%PM). | L43: M3 | M43: =+'Metrado Estructuras'!#REF! -> #REF!
B44: 02.02.02.01 | C44: ENCOFRADO Y DESENCOFRADO NORMAL DE SOBRECIMIENTO | L44: M2 | M44: =+'Metrado Estructuras'!#REF! -> #REF!
B45: 02.03 | C45: CONCRETO ARMADO
B46: 02.03.01 | C46: ZAPATAS
B47: 02.03.01.01 | C47: CONCRETO p/ZAPATAS (f'c = 210 kg/cm2.) | L47: M3 | M47: =+'Metrado Estructuras'!#REF! -> #REF!
B48: 02.03.01.02 | C48: ACERO DE REFUERZO G-60, fy= 4,200 Kg/cm2. p/ZAPATAS | L48: KG | M48: =+'Metrado Estructuras'!#REF! -> #REF!
B49: 02.03.02 | C49: VIGAS DE CONEXIÓN
B50: 02.03.02.01 | C50: CONCRETO p/VIGAS DE CIMENTACION (f'c= 210 Kg/cm2.) | L50: M3 | M50: =+'Metrado Estructuras'!#REF! -> #REF!
B51: 02.03.02.02 | C51: ENCOFRADO Y DESENCOFRADO DE VIGA DE CIMENTACION | L51: M2 | M51: =+'Metrado Estructuras'!#REF! -> #REF!
B52: 02.03.02.03 | C52: ACERO DE REFUERZO G-60, fy = 4,200 Kg/cm2. p/VIGAS DE CIMENTACION | L52: KG | M52: =+'Metrado Estructuras'!#REF! -> #REF!
B53: 02.03.03 | C53: COLUMNAS
B54: 02.03.03.01 | C54: CONCRETO p/COLUMNAS (f'c = 210 kg/cm2.) | L54: M3 | M54: =+'Metrado Estructuras'!#REF! -> #REF!
B55: 02.03.03.02 | C55: ENCOFRADO Y DESENCOFRADO DE COLUMNAS | L55: M2 | M55: =+'Metrado Estructuras'!#REF! -> #REF!
B56: 02.03.03.03 | C56: ACERO DE REFUERZO G-60, fy = 4,200 kg/cm2. p/COLUMNAS | L56: KG | M56: =+'Metrado Estructuras'!#REF! -> #REF!
B57: 02.03.04 | C57: VIGAS
B58: 02.03.04.01 | C58: CONCRETO p/VIGAS (f'c= 210 Kg/cm2.) | L58: M3 | M58: =+'Metrado Estructuras'!#REF! -> #REF!
B59: 02.03.04.02 | C59: ENCOFRADO Y DESENCOFRADO p/VIGAS | L59: M2 | M59: =+'Metrado Estructuras'!#REF! -> #REF!
B60: 02.03.04.03 | C60: ACERO DE REFUERZO G-60, fy = 4,200 Kg/cm2. p/VIGAS | L60: KG | M60: =+'Metrado Estructuras'!#REF! -> #REF!
B61: 02.03.05 | C61: LOSA ALIGERADA
B62: 02.03.05.01 | C62: CONCRETO p/LOSA ALIGERADA (f'c = 210 kg/cm2.) | L62: M3 | M62: =+'Metrado Estructuras'!#REF! -> #REF!
B63: 02.03.05.02 | C63: ENCOFRADO Y DESENCOFRADO p/LOSAS ALIGERADAS | L63: M2 | M63: =+'Metrado Estructuras'!#REF! -> #REF!
B64: 02.03.05.03 | C64: ACERO DE REFUERZO G-60, fy = 4,200 Kg/cm2. p/LOSAS ALIGERADAS | L64: KG | M64: =+'Metrado Estructuras'!#REF! -> #REF!
B65: 02.03.05.04 | C65: LADRILLO HUECO DE ARCILLA H=0.15mts, PARA TECHO ALIGERADO | L65: M2 | M65: =+'Metrado Estructuras'!#REF! -> #REF!
B66: 02.03.06 | C66: LOSA MACIZA
B67: 02.03.06.01 | C67: CONCRETO PARA LOSA MACIZA, f'c = 210 kg/cm2 | L67: M3 | M67: =+'Metrado Estructuras'!#REF! -> #REF!
B68: 02.03.06.02 | C68: ENCOFRADO Y DESENCOFRADO NORMAL DE LOSA MACIZA | L68: M2 | M68: =+'Metrado Estructuras'!#REF! -> #REF!
B69: 02.03.06.03 | C69: ACERO EN LOSA MACIZA, fy=4200 Kg/cm2 | L69: KG | M69: =+'Metrado Estructuras'!#REF! -> #REF!
B70: 02.03.07 | C70: ESCALERAS
B71: 02.03.07.01 | C71: CONCRETO p/ESCALERAS (f'c=210 Kg/cm.) | L71: M3 | M71: =+'Metrado Estructuras'!#REF! -> #REF!
B72: 02.03.07.02 | C72: ENCOFRADO Y DESENCOFRADO DE ESCALERAS | L72: M2 | M72: =+'Metrado Estructuras'!#REF! -> #REF!
B73: 02.03.07.03 | C73: ACERO DE REFUERZO G-60, fy= 4,200 Kg/cm2. p/ESCALERAS | L73: KG | M73: =+'Metrado Estructuras'!#REF! -> #REF!
B74: 02.03.02 | C74: MUROS DE SOSTENIMIENTO DE CONCRETO CICLOPEO
B75: 02.02.01.01 | C75: CONCRETO CICLOPEO (MEZCLA 1:10+30%PG). | L75: M3 | M75: =+'Metrado Estructuras'!#REF! -> #REF!
B76: 02.03.02 | C76: MUROS DE SOSTENIMIENTO DE CONCRETO ARMADO
B77: 02.03.02.03 | C77: CONCRETO p/MUROS (f'c=210 Kg/cm.) | L77: M3 | M77: =+'Metrado Estructuras'!#REF! -> #REF!
B78: 02.03.02.01 | C78: ENCOFRADO Y DESENCOFRADO DE MUROS | L78: M2 | M78: =+'Metrado Estructuras'!#REF! -> #REF!
B79: 02.03.02.02 | C79: ACERO DE REFUERZO G-60, fy= 4,200 Kg/cm2. p/MUROS | L79: KG | M79: =+'Metrado Estructuras'!#REF! -> #REF!
B80: 02.04 | C80: ESTRUCTURA DE ACERO
B81: 02.04.01 | C81: COLUMNAS
B82: 02.04.01.01 | C82: ARMADO DE COLUMNAS | L82: ML | M82: =+'Metrado Estructuras'!#REF! -> #REF!
B83: 02.04.01.03 | C83: MONTAJE DE COLUMNAS | L83: ML | M83: =+'Metrado Estructuras'!#REF! -> #REF!
B84: 02.04.01 | C84: VIGAS
B85: 02.04.01.01 | C85: ARMADO DE VIGAS | L85: ML | M85: =+'Metrado Estructuras'!#REF! -> #REF!
B86: 02.04.01.03 | C86: MONTAJE DE VIGAS | L86: ML | M86: =+'Metrado Estructuras'!#REF! -> #REF!
B87: 02.04.01.03 | C87: CABLE DE ACERO GALVANIZADO | L87: ML | M87: =+'Metrado Estructuras'!#REF! -> #REF!
B88: 02.04.01.03 | C88: MALLA RASCHEL | L88: M2 | M88: =+'Metrado Estructuras'!#REF! -> #REF!

Sheet Metrado Estructuras
H1: HOJA DE METRADOS DIARIOS DE PARTIDAS PROGRAMADAS SEGÚN EXPEDIENTE TECNICO
B2: OBRA
B4: 45809
B5: PARTIDA | C5: DESCRIPCION | D5: CANTIDAD | E5: LONGITUD/AREA | F5: ANCHO | G5: ALTURA | H5: N° VECES | I5: Φ | J5: DIAMETRO DE REFUERZO DE ACERO
J6: 1/4" | K6: 3/8" | L6: 1/2" | M6: | | N6: 3/4" | O6: 1" | P6: SUB-TOTAL | Q6: TOTAL | R6: UND
B7: OE.2.3.7.3 | C7: Columnas - acero f'y=4200 Kg/cm2 | Q7: =SUM(P7:P10) -> 1429.2 | R7: =+'Resumen Metrado'!L13 -> 0
C8: bloque 5 2DO NIVEL
C9: COLUMNA | Q9: =SUM(P9:P14) -> 1498.688 | R9: =+'Resumen Metrado'!L15 -> UND
C10: ACERO LONGUTDINAL | D10: 4 | E10: 4.5 | H10: 20 | I10: 1" | J10: =+IF(I10=$J$6,D10*E10*H10*0.254,0) -> 0 | K10: =+IF(I10=$K$6,D10*E10*H10*0.56,0) -> 0 | L10: =+IF(I10=$L$6,D10*E10*H10*0.994,0) -> 0 | M10: =+IF(I10=$M$6,D10*E10*H10*1.55,0) -> 0 | N10: =+IF(I10=$N$6,D10*E10*H10*2.24,0) -> 0 | O10: =+IF(I10=$O$6,D10*E10*H10*3.97,0) -> 1429.2 | P10: =+SUM(J10:O10) -> 1429.2
C11: EMPALME | D11: 2 | E11: 1.8 | H11: 4 | I11: 1" | J11: =+IF(I11=$J$6,D11*E11*H11*0.254,0) -> 0 | K11: =+IF(I11=$K$6,D11*E11*H11*0.56,0) -> 0 | L11: =+IF(I11=$L$6,D11*E11*H11*0.994,0) -> 0 | M11: =+IF(I11=$M$6,D11*E11*H11*1.55,0) -> 0 | N11: =+IF(I11=$N$6,D11*E11*H11*2.24,0) -> 0 | O11: =+IF(I11=$O$6,D11*E11*H11*3.97,0) -> 57.168 | P11: =+SUM(J11:O11) -> 57.168
D12: 20 | E12: 1.1 | H12: 1 | I12: 3/8" | J12: =+IF(I12=$J$6,D12*E12*H12*0.254,0) -> 0 | K12: =+IF(I12=$K$6,D12*E12*H12*0.56,0) -> 12.32 | L12: =+IF(I12=$L$6,D12*E12*H12*0.994,0) -> 0 | M12: =+IF(I12=$M$6,D12*E12*H12*1.55,0) -> 0 | N12: =+IF(I12=$N$6,D12*E12*H12*2.24,0) -> 0 | O12: =+IF(I12=$O$6,D12*E12*H12*3.97,0) -> 0 | P12: =+SUM(J12:O12) -> 12.32
J13: =+IF(I13=$J$6,D13*E13*H13*0.254,0) -> 0 | K13: =+IF(I13=$K$6,D13*E13*H13*0.56,0) -> 0 | L13: =+IF(I13=$L$6,D13*E13*H13*0.994,0) -> 0 | M13: =+IF(I13=$M$6,D13*E13*H13*1.55,0) -> 0 | N13: =+IF(I13=$N$6,D13*E13*H13*2.24,0) -> 0 | O13: =+IF(I13=$O$6,D13*E13*H13*3.97,0) -> 0
J14: =+IF(I14=$J$6,D14*E14*H14*0.254,0) -> 0 | K14: =+IF(I14=$K$6,D14*E14*H14*0.56,0) -> 0 | L14: =+IF(I14=$L$6,D14*E14*H14*0.994,0) -> 0 | M14: =+IF(I14=$M$6,D14*E14*H14*1.55,0) -> 0 | N14: =+IF(I14=$N$6,D14*E14*H14*2.24,0) -> 0 | O14: =+IF(I14=$O$6,D14*E14*H14*3.97,0) -> 0
J15: =+IF(I15=$J$6,D15*E15*H15*0.254,0) -> 0 | K15: =+IF(I15=$K$6,D15*E15*H15*0.56,0) -> 0 | L15: =+IF(I15=$L$6,D15*E15*H15*0.994,0) -> 0 | M15: =+IF(I15=$M$6,D15*E15*H15*1.55,0) -> 0 | N15: =+IF(I15=$N$6,D15*E15*H15*2.24,0) -> 0 | O15: =+IF(I15=$O$6,D15*E15*H15*3.97,0) -> 0
J16: =+IF(I16=$J$6,D16*E16*H16*0.254,0) -> 0 | K16: =+IF(I16=$K$6,D16*E16*H16*0.56,0) -> 0 | L16: =+IF(I16=$L$6,D16*E16*H16*0.994,0) -> 0 | M16: =+IF(I16=$M$6,D16*E16*H16*1.55,0) -> 0 | N16: =+IF(I16=$N$6,D16*E16*H16*2.24,0) -> 0 | O16: =+IF(I16=$O$6,D16*E16*H16*3.97,0) -> 0
J17: =+IF(I17=$J$6,D17*E17*H17*0.254,0) -> 0 | K17: =+IF(I17=$K$6,D17*E17*H17*0.56,0) -> 0 | L17: =+IF(I17=$L$6,D17*E17*H17*0.994,0) -> 0 | M17: =+IF(I17=$M$6,D17*E17*H17*1.55,0) -> 0 | N17: =+IF(I17=$N$6,D17*E17*H17*2.24,0) -> 0 | O17: =+IF(I17=$O$6,D17*E17*H17*3.97,0) -> 0
J18: =+IF(I18=$J$6,D18*E18*H18*0.254,0) -> 0 | K18: =+IF(I18=$K$6,D18*E18*H18*0.56,0) -> 0 | L18: =+IF(I18=$L$6,D18*E18*H18*0.994,0) -> 0 | M18: =+IF(I18=$M$6,D18*E18*H18*1.55,0) -> 0 | N18: =+IF(I18=$N$6,D18*E18*H18*2.24,0) -> 0 | O18: =+IF(I18=$O$6,D18*E18*H18*3.97,0) -> 0
J19: =+IF(I19=$J$6,D19*E19*H19*0.254,0) -> 0 | K19: =+IF(I19=$K$6,D19*E19*H19*0.56,0) -> 0 | L19: =+IF(I19=$L$6,D19*E19*H19*0.994,0) -> 0 | M19: =+IF(I19=$M$6,D19*E19*H19*1.55,0) -> 0 | N19: =+IF(I19=$N$6,D19*E19*H19*2.24,0) -> 0 | O19: =+IF(I19=$O$6,D19*E19*H19*3.97,0) -> 0
J20: =+IF(I20=$J$6,D20*E20*H20*0.254,0) -> 0 | K20: =+IF(I20=$K$6,D20*E20*H20*0.56,0) -> 0 | L20: =+IF(I20=$L$6,D20*E20*H20*0.994,0) -> 0 | M20: =+IF(I20=$M$6,D20*E20*H20*1.55,0) -> 0 | N20: =+IF(I20=$N$6,D20*E20*H20*2.24,0) -> 0 | O20: =+IF(I20=$O$6,D20*E20*H20*3.97,0) -> 0
J21: =+IF(I21=$J$6,D21*E21*H21*0.254,0) -> 0 | K21: =+IF(I21=$K$6,D21*E21*H21*0.56,0) -> 0 | L21: =+IF(I21=$L$6,D21*E21*H21*0.994,0) -> 0 | M21: =+IF(I21=$M$6,D21*E21*H21*1.55,0) -> 0 | N21: =+IF(I21=$N$6,D21*E21*H21*2.24,0) -> 0 | O21: =+IF(I21=$O$6,D21*E21*H21*3.97,0) -> 0

Sheet METRADO
S1: HOJA DE METRADOS DIARIOS DE PARTIDAS PROGRAMADAS SEGÚN EXPEDIENTE TECNICO
S2: MARZO DEL 2026
B4: OBRA : “MEJORAMIENTO Y AMPLIACION DE LOS SERVICIOS DE SALUD DEL EstABLECIMIENTO DE SALUD DE BELEMPAMPA - DIstRITO DE SANTIAGO - PROVINCIA DE CUSCO - REGION CUSCO - HOSPITAL”
S5: HOJA DE METRADOS DIARIOS DE PARTIDAS NUEVAS POR APROBAR
B7: NIVEL IND. | C7: FECHA | D7: FRENTE | E7: BLOQUE | F7: NIVEL | G7: CODIGO | H7: PARTIDA | I7: DESCRIPCIÓN | J7: CANTIDAD | K7: LONGITUD/AREA | L7: ANCHO / EMPAME | M7: ALTURA / GANCHO | N7: PARCIAL | O7: ACERO | P7: N° VECES2 | Q7: TOTAL | R7: UNIDADES | S7: MOD.
U114: OE.6.2.72 | V114: und | W114: Instalación de Abrazadera unistrut de 3/4" | AG114: 30 | AH114: Conector PVC SAP NTP 399.006 DE 25 mm | AJ114: Und
U115: OE.6.2.73 | V115: und | W115: Instalación de Abrazadera unistrut de 1" | AG115: 31 | AH115: Conector PVC SAP NTP 399.006 DE 20 mm | AJ115: Und
U116: OE.6.3.28 | V116: und | W116: Instalación de salida de datos cat. 7A simple - doble | AG116: 32 | AH116: Riel unistrut 41x21x1.5mmx2.4m | AJ116: m
U117: OE.6.2.62 | V117: und | W117: Instalación de Unión Conduit EMT de 20mm | AG117: 24 | AH117: Curva PVC SAP NTP 399.006 de 25 mm | AJ117: Und
U118: OE.6.2.63 | V118: und | W118: Instalación de Conector CONDUIT EMT de 25 mm | AG118: 25 | AH118: Curva PVC SAP NTP 399.006 DE 20 mm | AJ118: Und
U119: OE.6.2.64 | V119: und | W119: Instalación de Conector CONDUIT EMT de 20 mm | AG119: 26 | AH119: Unión PVC SAP NTP 399.006 DE 50 mm | AJ119: Und
U120: OE.6.2.37 | V120: m | W120: Recubrimiento de tuberia conduit con FILM | AC120: VI | AD120: =+CONCATENATE("BLOQUE ",AC120) -> BLOQUE VI | AG120: 3 | AH120: Unión conduit EMT de 20 mm | AI120: =K128+K151+#REF!+K262+K345 -> #REF! | AJ120: Und
U121: OE.6.2.38 | V121: m | W121: Picado y corte de muros para instalación de tubería PVC | AC121: VII | AD121: =+CONCATENATE("BLOQUE ",AC121) -> BLOQUE VII | AG121: 4 | AH121: Curva conduit EMT de 20 mm | AI121: =K125+K154+K225+K265+K348 -> 0 | AJ121: Und
U122: OE.6.2.39 | V122: m | W122: Trazo y replanteo | AC122: VIII | AD122: =+CONCATENATE("BLOQUE ",AC122) -> BLOQUE VIII | AG122: 5 | AH122: Tubería conduit EMT de 25 mm | AJ122: m
U123: OE.6.2.48 | V123: und | W123: Instalación de Curva PVC SAP NTP 399.006 DE 20 mm | AG123: 12 | AH123: Caja de Paso de F°G° Pesado 15cmx15cmx10cm | AJ123: Und
U124: OE.6.2.49 | V124: und | W124: Instalación de Union PVC SAP NTP 399.006 de 100 mm | AG124: 13 | AH124: Caja de Paso de F°G° cuadrado 10cmx10cmx7.5cm | AI124: =K157+K228+K271+K351 -> 0 | AJ124: Und
U125: OE.6.2.50 | V125: und | W125: Instalación de Unión PVC SAP NTP 399.006 DE 50 mm | AG125: 14 | AH125: Caja de Paso de F°G° Pesado 10cmx10cmx5cm | AJ125: Und
U126: OE.6.2.45 | V126: und | W126: Instalación de Curva PVC SAP NTP 399.006 de 100 mm | AC126: XIV | AD126: =+CONCATENATE("BLOQUE ",AC126) -> BLOQUE XIV | AG126: 9 | AH126: Bandeja tipo malla de 105x100x3000mm electrozincado | AJ126: m
U127: OE.6.2.46 | V127: und | W127: Instalación de Curva PVC SAP NTP 399.006 DE 50 mm | AG127: 10 | AH127: Bandeja tipo malla de 105x300x3000mm electrozincado | AJ127: m
U128: OE.6.2.47 | V128: und | W128: Instalación de Curva PVC SAP NTP 399.006 de 25 mm | AG128: 11 | AH128: Caja de paso de F°G° Pesado 15cmx20cmx20cm | AJ128: Und
U129: OE.6.2.40 | V129: m | W129: Instalación de Riel unistrut 41 X 41 X 1.5mm X 2.4m | AC129: IX | AD129: =+CONCATENATE("BLOQUE ",AC129) -> BLOQUE IX | AG129: 6 | AH129: Conector conduit EMT de 25 mm | AJ129: Und
U130: OE.6.2.41 | V130: m | W130: Instalación de Tuberia Electrica PVC SAP NTP 399.006 DE 100 mm | AC130: X | AD130: =+CONCATENATE("BLOQUE ",AC130) -> BLOQUE X | AG130: 7 | AH130: Unión conduit EMT de 25 mm | AJ130: Und
U131: OE.6.2.42 | V131: m | W131: Instalación de Tuberia Electrica PVC SAP NTP 399.006 DE 50 mm | AC131: XI | AD131: =+CONCATENATE("BLOQUE ",AC131) -> BLOQUE XI | AG131: 8 | AH131: Curva conduit EMT de 25 mm | AJ131: Und
U132: OE.6.2.59 | V132: und | W132: Instalación de Curva Conduit EMT de 25 mm | AG132: 21 | AH132: Tuberia Electrica PVC SAP NTP 399.006 de 25 mm | AJ132: m
U133: OE.6.2.60 | V133: und | W133: Instalación de Curva Conduit EMT de 20 mm | AG133: 22 | AH133: Tuberia Electrica PVC SAP NTP 399.006 de 20 mm | AJ133: m
U134: OE.6.2.61 | V134: und | W134: Instalación de Unión Conduit EMT de 25mm | AG134: 23 | AH134: Curva PVC SAP NTP 399.006 DE 50 mm | AJ134: Und
U135: OE.6.2.67 | V135: und | W135: Instalación de Prensaestopa para tubo PVC flexible de 20 mm | AG135: 27 | AH135: Unión PVC SAP NTP 399.006 DE 25 mm | AJ135: Und
U136: OE.6.2.68 | V136: m | W136: Instalación de Bandeja tipo malla de 105x100x3000mm electrozincado, aterrado y con accesorios de instalacion. | AG136: 28 | AH136: Unión PVC SAP NTP 399.006 DE 20 mm | AJ136: Und
U137: OE.6.2.69 | V137: m | W137: Instalación de Riel unistrut 41 X 21 X 1.5mm X 2.4m | AG137: 29 | AH137: Conector PVC SAP NTP 399.006 DE 50 mm | AJ137: Und
U138: OE.6.2.56 | V138: und | W138: Instalación de Conector PVC SAP NTP 399.006 DE 20 mm | AG138: 18 | AH138: Cajas Octogonal de F°G° pesado 10cmx5cm (DACI) | AI138: =K140+K160+K234+K277+K357 -> 0 | AJ138: Und
U139: OE.6.2.57 | V139: m | W139: Instalación de Tubería conduit EMT de 25 mm | AG139: 19 | AH139: Tuberia Electrica PVC SAP NTP 399.006 DE 100 mm | AJ139: m
U140: OE.6.2.58 | V140: m | W140: Instalación de Tubería conduit EMT de 20 mm | AG140: 20 | AH140: Tuberia Electrica PVC SAP NTP 399.006 DE 50 mm | AJ140: m
U141: OE.6.2.51 | V141: und | W141: Instalación de Unión PVC SAP NTP 399.006 DE 25 mm | AG141: 15 | AH141: Caja de Paso de F°G° Pesado 10cmx10cmx5cm(SALIDA DATA) | AJ141: Und
U142: OE.6.2.52 | V142: und | W142: Instalación de Unión PVC SAP NTP 399.006 DE 20 mm | AG142: 16 | AH142: Cajas Octogonal de F°G° pesado 10cmx5cm | AJ142: Und | AK142: =K231+K274+K354 -> 0
U143: OE.6.2.53 | V143: und | W143: Instalación de Conector PVC SAP NTP 399.006 de 100 mm | AG143: 17 | AH143: Cajas Octogonal de F°G° pesado 10cmx5cm (PERIFORNEO) | AJ143: Und
U190: OE.6.4.7 | V190: m | W190: Relleno y compactado con material propio b=0.50 x h=0.70 m
U191: OE.6.4.8 | V191: und | W191: Construcción de Buzon de Co Ao 0.6x0.6x0.7
U192: OE.6.2.65 | V192: m | W192: Instalacion de Bandeja tipo malla de 105x300x3000mm electrozincado con accesorios de instalacion.
U193: OE.6.4.4 | V193: m³ | W193: Excavación para buzon de comunicaciones | AG193: 34 | AH193: Abrazadera unistrut de ¾” | AJ193: Und
U194: OE.6.4.5 | V194: und | W194: Construcción de tapa de buzón de comunicaciones | AG194: 35 | AH194: Abrazadera unistrut de 1” | AJ194: und
U195: OE.6.4.6 | V195: m | W195: Excavacion de zanja para ducto enterrado b=0.50 x h=0.70 m | AG195: 36 | AH195: Abrazadera de ¾” | AJ195: Und
U196: OE.6.7.10 | V196: und | W196: Pintado y señalización de cajas de pase | AG196: 43 | AH196: Riel dentada | AJ196: m
U197: OE.6.7.11 | V197: und | W197: Instalación de Caja de Paso con tapa Biselada de F°G° 300x300x100 mm | AG197: 44 | AH197: Tirafones, tarugos y arandelas | AJ197: Und
U198: OE.6.7.12 | V198: und | W198: Instalación de Caja de Paso Pesada con tapa Biselada de 200x200x100mm | AG198: 45 | AH198: Clavos | AJ198: Und
U199: OE.6.7.7 | V199: und | W199: Instalación de Cajas octogonal de F°G° pesado 10cmx5cm | AG199: 40 | AH199: Tacos expansivos de 3/8 | AJ199: Und
U200: OE.6.7.8 | V200: und | W200: Instalación de Caja de Paso de F°G° cuadrado 10cmx10cmx7.5cm | AG200: 41 | AH200: Tuercas de 3/8 | AJ200: Und
U201: OE.6.7.9 | V201: und | W201: Instalación de Caja de Paso de F°G° cuadrado 10cmx10cmx5cm | AG201: 42 | AH201: Tirafones, tarugos y arandelas | AJ201: Und
U202: OE.6.4.7 | V202: m | W202: Relleno y compactado con material propio b=0.50 x h=0.70 m | AG202: 37 | AH202: Abrazadera de 1 ” | AJ202: Und
U203: OE.6.4.8 | V203: und | W203: Construcción de Buzon de Co Ao 0.6x0.6x0.7 | AG203: 38 | AH203: Film | AJ203: m
U204: OE.6.7.6 | V204: und | W204: Instalación de Caja de Paso de F°G° Tipo Pesado 15cmx15cmx10cm | AG204: 39 | AH204: Espárragos 3/8 | AJ204: m
U205: OE.6.2.71 | V205: und | W205: Instalación de Abrazadera de 1"
U206: OE.6.3.29 | V206: und | W206: Instalación de punto de datos Cat 7A simple
U207: OE.6.3.30 | V207: und | W207: Instalación de punto de datos Cat 7A doble
U211: OE.6.3.5 | V211: pto | W211: Salida sensor de humo
U212: OE.6.3.15 | V212: pto | W212: Salida parlante
U213: OE.6.2.70 | V213: und | W213: Instalación de Abrazadera de 3/4"
U217: OE.6.7.13 | V217: und | W217: Instalación de Caja de paso Pesada con tapa biselada de 150x150x100mm | AG217: 46 | AH217: Fulminantes | AJ217: Und
U218: OE.6.7.14 | V218: und | W218: Instalación de Caja de pase de fierro galvanizado pesado 15 cm x 20cm x 20cm
U219: OE.6.7.15 | V219: und | W219: Instalación de Caja de Pase de Fierro Galbanizado Pesado 10cmx25cmx25cm

Sheet Hoja1
A2: S10 | I2: Página | J2: 1
F4: Presupuesto
A6: Presupuesto | D6: 0305020 | E6: DISEÑO INTEGRAL DEL NUEVO PUENTE DE PISAC
A9: Cliente | C9: UNIVERSIDAD NACIONAL SAN ANTONIO ABAD DEL CUSCO | H9: Costo al | J9: 01/02/2012
A10: Lugar | C10: CUSCO - CALCA - PISAC
A12: Item | C12: Descripción | G12: Und. | H12: Metrado | I12: Precio S/. | J12: Parcial S/.
A14: 01 | E14: TRABAJOS PRELIMINARES | R14: 23651.77
A16: 01.01 | C16: CAMPAMENTO PROVISIONAL DE LA OBRA | H16: m2 | I16: 18 | K16: 126.58 | O16: 2278.44
A18: 01.02 | C18: SUMINISTRO Y COLOCACION DE CARTEL DE OBRA DE 2.40x3.60mts | H18: und | I18: 1 | K18: 548.21 | O18: 548.21
A20: 01.03 | C20: AGUA PARA LA CONSTRUCCION (Almacenamiento y Distribucion) | H20: mes | K20: 150
A22: 01.03 | C22: ENERGIA ELECTRICA PROVISIONAL (Consumo y Mantenimiento) | H22: mes | K22: 350
A24: 01.04 | C24: MOVILIZACION Y DESMOVILIZACION DE MAQUINARIAS Y MATERIALES | H24: GLB | K24: 5140.74
A26: 01.05 | C26: LIMPIEZA DE TERRENO MANUAL | H26: m2 | K26: 1.8
A28: 01.06 | C28: TRAZO Y REPLANTEO | H28: m2 | I28: 576 | K28: 4.63 | O28: 2666.88
A30: 01.07 | C30: TRAZO Y REPLANTEO DURANTE EL PROCESO | H30: mes | I30: 6 | K30: 4598.63 | O30: 27591.78
A32: 02 | E32: ESTRIBOS | R32: 159927.96
A34: 02.01 | C34: EXCAVACION CON MAQUINARIA | H34: m3 | I34: 378 | K34: 17.01 | O34: 6429.78
A36: 02.02 | C36: EXCAVACION CON MAQUINARIA BAJO AGUA | H36: m3 | K36: 32.26
A38: 02.03 | C38: ELIMINACION DE MATERIAL EXCEDENTE | H38: m3 | I38: 252.5 | K38: 33.18 | O38: 8377.95
A40: 02.04 | C40: ENTIBADO DE ZANJAS | H40: m2 | K40: 62.01
A42: 02.04 | C42: RELLENO Y COMPACTACION CON MATERIAL PROPIO | H42: m3 | I42: 176 | K42: 19.85 | O42: 3493.6
A44: 02.05 | C44: SOLADO PARA ZAPATAS, e=10cm, MEZCLA C:H - 1:10 | H44: m2 | K44: 28.03
A46: 02.06 | C46: ENCOFRADO Y DESENCOFRADO DE ESTRIBOS | H46: m2 | I46: 302.8 | K46: 56.64 | O46: 17150.59
A48: 02.07 | C48: ACERO FY=4200 KG/CM2 | H48: kg | I48: 7724.37 | K48: 5.27 | O48: 40707.43
A50: 02.08 | C50: CONCRETO FC=210 KG/CM2, PARA ESTRIBOS | H50: m3 | K50: 389.41
A52: 03 | E52: FALSO PUENTE | R52: 27798.75
A54: 03.01 | C54: DADO CONCRETO CICLOPEO f'c=140 kg/cm2 + 30%P.G | H54: m3 | K54: 480.33
A56: 03.02 | C56: VIGAS PRINCIPALES DE MADERA ROLLIZO | H56: und | K56: 1563.11
A58: 03.03 | C58: VIGAS TRANSVERSALES DE MADERA | H58: und | K58: 1022.97
A60: 03.04 | C60: PIES DERECHOS DE MADERA | H60: und | K60: 58.57
A62: 03.05 | C62: DESMONTAJE DE FALSO PUENTE | H62: m2 | K62: 61.92
A64: 03.06 | C64: DEMOLICION DE DADOS DE CONCRETO CICLOPEO | H64: m3 | K64: 75.78
A66: 04 | E66: VIGAS POSTENSADAS
A68: 04.01 | C68: ENCOFRADO Y DESENCOFRADO | H68: m2 | I68: 240.95 | K68: 68.25 | O68: 16444.84
A70: 04.02 | C70: ACERO FY=4200 KG/CM2 | H70: kg | I70: 8027.14 | K70: 5.27 | O70: 42303.03
A72: 04.03 | C72: ACERO PARA PRETENSADO | H72: ton-m | K72: 9.31
A74: 04.04 | C74: CONCRETO FC=350 KG/CM2 | H74: m3 | K74: 427.5
A76: 05 | E76: LOSA DE PUENTE
A78: 05.01 | C78: ENCOFRADO Y DESENCOFRADO | H78: m2 | I78: 90 | K78: 68.25 | O78: 6142.5
A80: 05.02 | C80: ACERO FY=4200 KG/CM2 | H80: kg | I80: 3291.79 | K80: 5.27 | O80: 17347.73
A82: 05.03 | C82: CONCRETO FC=280 KG/CM2 | H82: m3 | K82: 431.4
A84: 06 | E84: VEREDAS
A86: 06.01 | C86: ENCOFRADO Y DESENCOFRADO | H86: m2 | I86: 35 | K86: 68.25 | O86: 2388.75
A88: 06.02 | C88: ACERO FY=4200 KG/CM2 | H88: kg | I88: 943.35 | K88: 5.27 | O88: 4971.45
A90: 06.03 | C90: CONCRETO FC=280 KG/CM2 | H90: m3 | K90: 431.4
A92: 07 | E92: ACONDICIONAMIENTO DE ACCESOS
A94: 07.01 | E94: TRABAJOS PRELIMINARES
A96: 07.01.01 | C96: TRAZO Y REPLANTEO | H96: m2 | I96: 576 | K96: 4.63 | O96: 2666.88
A98: 07.02 | E98: MOVIMIENTO DE TIERRAS
A100: 07.02.01 | C100: EXTRACCION Y APILAMIENTO DE MATERIAL DE CANTERA | H100: m3 | I100: 502.8 | K100: 8.85 | O100: 4449.78
A102: 07.02.02 | C102: CARGUIO DE MATERIAL DE CANTERA | H102: m3 | I102: 502.8 | K102: 8.85 | O102: 4449.78
A104: 07.02.03 | C104: TRANSPORTE DE MATERIAL A OBRA | H104: m3 | I104: 502.8 | K104: 4.31 | O104: 2167.07
A106: 07.02.04 | C106: CONFORMACION DE TERRAPLENES | H106: m3 | I106: 502.8 | K106: 22.44 | O106: 11282.83
A108: 07.02.04 | C108: SUB - BASE GRANULAR | H108: m3 | K108: 7.81
A110: 07.02.05 | C110: BASE GRANULAR | H110: m3 | K110: 6.95
A112: 07.02.06 | C112: IMPRIMACION ASFALTICA | H112: m2 | K112: 32.41
A114: 08 | E114: OBRAS DE PROTECCION DEL PUENTE
A116: 08.01 | E116: TRABAJOS PRELIMINARES
A118: 08.01.01 | C118: LIMPIEZA DE TERRENO MANUAL | H118: m2 | K118: 1.8
A120: 08.01.02 | C120: TRAZO Y REPLANTEO | H120: m2 | I120: 576 | K120: 4.63 | O120: 2666.88
A122: 08.02 | E122: MOVIMIENTO DE TIERRAS
A124: 08.02.01 | C124: EXCAVACION CON MAQUINARIA | H124: m3 | I124: 378 | K124: 17.01 | O124: 6429.78
A126: 08.02.02 | C126: ELIMINACION DE MATERIAL EXCEDENTE | H126: m3 | I126: 252.5 | K126: 33.18 | O126: 8377.95
A128: 08.02.03 | C128: ENTIBADO DE ZANJAS | H128: m2 | K128: 62.01
A130: 08.02.04 | C130: RELLENO Y COMPACTACION CON MATERIAL PROPIO | H130: m3 | I130: 176 | K130: 22.07 | O130: 3884.32
A132: 08.03 | E132: GAVIONES
A134: 08.03.01 | C134: GAVION CAJA MALLA H=1M | H134: m3 | K134: 207.31
A136: 08.03.02 | C136: COLCHON ANTISOCAVANTE | H136: m2 | K136: 74.14
A138: 09 | E138: VARIOS | R138: 22667.6
A140: 09.01 | C140: SUMINISTRO Y COLOCACION DE APOYOS FIJOS | H140: und | I140: 2 | K140: 3106.52 | O140: 6213.04
A142: 09.02 | C142: SUMINISTRO Y COLOCACION DE APOYOS MOVILES | H142: und | I142: 2 | K142: 4606.52 | O142: 9213.04
A144: 09.03 | C144: JUNTAS ASFALTICAS | H144: m | I144: 19.2 | K144: 8.7 | O144: 167.04
A146: 09.04 | C146: JUNTA METALICA | H146: m | I146: 7.2 | K146: 166.09 | O146: 1195.85
A148: 09.05 | C148: SUMINISTRO Y COLOCACION DE BARANDA METALICA D=2" | H148: m | I148: 50 | K148: 798.3 | O148: 39915
A150: 09.06 | C150: PINTURA EN BARANDAS CON ESMALTE ANTICORROSIVO | H150: m2 | I150: 81.6 | K150: 8.57 | O150: 699.31
A152: 09.07 | C152: TUBOS DE DRENAJE | H152: m | I152: 6 | K152: 13.27 | O152: 79.62
A154: 09.08 | C154: PLACA RECORDATORIA | H154: und | I154: 1 | K154: 700 | O154: 700
A156: 10 | E156: SEÑALIZACION
A158: 10.01 | C158: SEÑALIZACION PREVENTIVA | H158: und | K158: 486.46
A160: 10.02 | C160: SEÑALIZACION INFORMATIVA | H160: und | K160: 636.46
A162: 10.03 | C162: SEÑALIZACION REGULADORA | H162: und | K162: 536.46
A164: 10.04 | C164: LINEAS CONTINUAS EN PAVIMENTO | H164: m | K164: 10.16
A166: 10.05 | C166: PINTURA ESMALTE PARA ESTRUCTURA DE CONCRETO | H166: m2 | I166: 12.5 | K166: 16.48 | O166: 206
A168: 11 | E168: MITIGACION DE IMPACTO AMBIENTAL | R168: 2800.59
A170: 11.01 | C170: RESTAURACION DE CANTERAS | H170: m2 | I170: 600 | K170: 4.2 | O170: 2520
A172: 11.02 | C172: RESTAURACION DE AREAS AFECTADAS POR CAMPAMENTO | H172: m2 | I172: 18 | K172: 2.01 | O172: 36.18
A174: 12 | E174: CONTROL DE CALIDAD DE OBRA | R174: 5000
A176: 12.01 | C176: CONTROL DE CALIDAD DEL CONCRETO | H176: und | I176: 3 | K176: 1200 | O176: 3600
A178: 12.02 | C178: CONTROL DE CALIDAD DE AGREGADOS | H178: und | I178: 1 | K178: 400 | O178: 400
A180: 12.03 | C180: CONTROL DE CALIDAD DE COMPACTACION DE TERRAPLENES | H180: und | I180: 2 | K180: 500 | O180: 1000
A182: 13 | E182: FLETE | R182: 26167.2
A184: 13.01 | C184: FLETE TERRESTRE | H184: ton | I184: 218.06 | K184: 120 | O184: 26167.2
I186: Fecha : | J186: 41254.839
